Workbook
Name A: #REF!
Name B: #REF!
Name BAJAS2: #REF!
Name ColumnTitle2: #REF!
Name ColumnTitle3: [1]!Exercise[[#Headers],[DATE]]
Name DietLastEnd: '[1]Chart Calculations'!$C$5
Name DietPeriod: #REF!
Name DietRowStart: '[1]Chart Calculations'!$C$4
Name EndDate: #REF!
Name EndWeight: #REF!
Name ExerciseLastEnd: '[1]Chart Calculations'!$C$23
Name ExercisePeriod: [1]!Exercise[DATE]
Name ExerciseRowStart: '[1]Chart Calculations'!$C$22
Name LossPerDay: [2]TABLERO!#REF!
Name PlanDays: [2]TABLERO!#REF!
Name StartDate: #REF!
Name StartWeight: #REF!
Name WeightGoal: #REF!

Sheet Hoja1
B3: Etiquetas de columna
B4: 1 | C4: 2 | D4: 3 | E4: 4 | F4: 5 | G4: 6 | H4: 7 | I4: 8 | J4: 9 | K4: 10 | L4: 11 | M4: 12 | N4: Total general
A5: Cuenta de Mes | B5: 29 | C5: 87 | D5: 143 | E5: 143 | F5: 206 | G5: 208 | H5: 124 | I5: 104 | J5: 146 | K5: 98 | L5: 85 | M5: 26 | N5: 1399
B11: 1 | C11: 2 | D11: 3 | E11: 4 | F11: 5 | G11: 6 | H11: 7 | I11: 8 | J11: 9 | K11: 10 | L11: 11 | M11: 12 | N11: Total general
A12: Cuenta de Mes | B12: 29 | C12: 87 | D12: 143 | E12: 143 | F12: 206 | G12: 208 | H12: 124 | I12: 104 | J12: 146 | K12: 98 | L12: 85 | M12: 26 | N12: 1399
B14: =B12*100/$N$12 -> 2.0729092 | C14: =C12*100/$N$12 -> 6.2187277 | D14: =D12*100/$N$12 -> 10.221587 | E14: =E12*100/$N$12 -> 10.221587 | F14: =F12*100/$N$12 -> 14.724803 | G14: =G12*100/$N$12 -> 14.867763 | H14: =H12*100/$N$12 -> 8.8634739 | I14: =I12*100/$N$12 -> 7.4338813 | ... N14: =N12*100/$N$12 -> 100
B15: =B14 -> 2.0729092 | C15: =C14+B15 -> 8.2916369 | D15: =D14+C15 -> 18.513224 | E15: =E14+D15 -> 28.734811 | F15: =F14+E15 -> 43.459614 | G15: =G14+F15 -> 58.327377 | H15: =H14+G15 -> 67.190851 | I15: =I14+H15 -> 74.624732 | J15: =J14+I15 -> 85.060758 | ... M15: =M14+L15 -> 100

Sheet PICADE
A1: IDSDNCA | B1: IDSAP | C1: Subdirección | D1: Gerencia/Activo | E1: Nombre Evento Original | F1: Ficha Instructor | G1: Nombre Instructor | H1: Asistentes Programados | I1: Fecha de Inicio | J1: Fecha de Termino | K1: Sede | L1: Mes
A2: 56466 | C2: SPRN | D2: ACTIVO DE PRODUCCIÓN POZA RICA - ALTAMIRA | E2: AUDITORÍAS EFECTIVAS (AE) | F2: 457409 | G2: SAVINO COMSILLE MARIA GUADALUPE | H2: 9 | I2: 45103 | J2: 45103 | K2: ALTAMIRA, TAMAULIPAS | L2: =MONTH(J2) -> 6
A3: 48052 | C3: SPRN | D3: ACTIVO DE PRODUCCIÓN POZA RICA - ALTAMIRA | E3: DISCIPLINA OPERATIVA (DO) | F3: 449433 | G3: MORAL JORDAN GONZALO | H3: 15 | I3: 45168 | J3: 45169 | K3: ALTAMIRA, TAMAULIPAS | L3: =MONTH(J3) -> 8
A4: 53782 | C4: SPRN | D4: ACTIVO DE PRODUCCIÓN POZA RICA - ALTAMIRA | E4: BRIGADAS DE BÚSQUEDA Y RESCATE (BBR) | F4: 449433 | G4: MORAL JORDAN GONZALO | H4: 18 | I4: 45243 | J4: 45245 | K4: ALTAMIRA, TAMAULIPAS | L4: =MONTH(J4) -> 11
A5: 51027 | C5: SPRN | D5: ACTIVO DE PRODUCCIÓN POZA RICA - ALTAMIRA | E5: BÁSICO DE SEGURIDAD (BS) | F5: 457409 | G5: SAVINO COMSILLE MARIA GUADALUPE | H5: 9 | I5: 45173 | J5: 45174 | K5: ALTAMIRA, TAMAULIPAS | L5: =MONTH(J5) -> 9
A6: 55346 | C6: SPRN | D6: ACTIVO DE PRODUCCIÓN POZA RICA - ALTAMIRA | E6: SEGURIDAD EN CENTROS ADMINISTRATIVOS (SCA) | F6: 196853 | G6: DEL ANGEL DEL ANGEL JUSTO JESUS | H6: 18 | I6: 44966 | J6: 44966 | K6: NARANJOS | L6: =MONTH(J6) -> 2
A7: 50466 | C7: SPRN | D7: ACTIVO DE PRODUCCIÓN POZA RICA - ALTAMIRA | E7: ÁCIDO SULFHÍDRICO (H2S) | F7: 449433 | G7: MORAL JORDAN GONZALO | H7: 14 | I7: 45054 | J7: 45054 | K7: ALTAMIRA, TAMAULIPAS | L7: =MONTH(J7) -> 5
A8: 53740 | C8: SPRN | D8: ACTIVO DE PRODUCCIÓN POZA RICA - ALTAMIRA | E8: BRIGADAS DE PRIMEROS AUXILIOS (BPA) | F8: 449433 | G8: MORAL JORDAN GONZALO | H8: 14 | I8: 45225 | J8: 45226 | K8: ALTAMIRA, TAMAULIPAS | L8: =MONTH(J8) -> 10
A9: 58434 | C9: SPRN | D9: ACTIVO DE PRODUCCIÓN POZA RICA - ALTAMIRA | E9: AUDITORÍAS EFECTIVAS (AE) | F9: 457409 | G9: SAVINO COMSILLE MARIA GUADALUPE | H9: 14 | I9: 45170 | J9: 45170 | K9: POZA RICA DE HIDALGO,VERACRUZ | L9: =MONTH(J9) -> 9
A10: 47731 | C10: SPRN | D10: ACTIVO DE PRODUCCIÓN POZA RICA - ALTAMIRA | E10: ÁCIDO SULFHÍDRICO (H2S) | F10: 449433 | G10: MORAL JORDAN GONZALO | H10: 12 | I10: 45079 | J10: 45079 | K10: ALTAMIRA, TAMAULIPAS | L10: =MONTH(J10) -> 6
A11: 47721 | C11: SPRN | D11: ACTIVO DE PRODUCCIÓN POZA RICA - ALTAMIRA | E11: MANEJO A LA DEFENSIVA (MD) | F11: 315766 | G11: RANGEL RIVAS ROCIO | H11: 13 | I11: 45071 | J11: 45071 | K11: ALTAMIRA, TAMAULIPAS | L11: =MONTH(J11) -> 5
A12: 59718 | C12: SPRN | D12: ACTIVO DE PRODUCCIÓN POZA RICA - ALTAMIRA | E12: AUDITORÍAS EFECTIVAS (AE) | F12: 457409 | G12: SAVINO COMSILLE MARIA GUADALUPE | H12: 10 | I12: 45233 | J12: 45233 | K12: POZA RICA DE HIDALGO,VERACRUZ | L12: =MONTH(J12) -> 11
A13: 55768 | C13: SPRN | D13: ACTIVO DE PRODUCCIÓN POZA RICA - ALTAMIRA | E13: SEGURIDAD EN CENTROS ADMINISTRATIVOS (SCA) | F13: 372624 | G13: CARRILLO CABELLO JAIR DE JESUS | H13: 18 | I13: 45064 | J13: 45064 | K13: CERRO AZUL,VERACRUZ | L13: =MONTH(J13) -> 5
... A1400: 47975 | C1400: SMLIC | D1400: GERENCIA DE SERVICIOS DE LOGÍSTICA TERRESTRE | E1400: MANEJO A LA DEFENSIVA (MD) | F1400: 372624 | G1400: CARRILLO CABELLO JAIR DE JESUS | H1400: 10 | I1400: 45019 | J1400: 45019 | K1400: NARANJOS | L1400: =MONTH(J1400) -> 4

Sheet Seguimiento
A1: Rsspa
E5: Periodo
C6: PICADE Autorizado | E6: 44927 | I6: al | J6: 45291
B7: PEP | C7: Cursos | D7: Capacitandos | E7: Programados en el periodo | F7: Realizados en el periodo | G7: Cancelados | H7: Adicionales | I7: Total Realizados | J7: Capacitandos programados | K7: Capacitados en el periodo | L7: Capacitados Adicionales | M7: Total Capacitandos | N7: Cumplimiento en el periodo (%) | O7: Avance del PICADE (%) | P7: Cumplimiento del personal capacitado (%) | Q7: Trabajadores por curso
B8: Norte | C8: =C26 -> 387 | D8: =D26 -> 4659 | E8: =E26 -> 387 | F8: =F26 -> 381 | G8: =G26 -> 6 | H8: =H26 -> 3 | I8: =I26 -> 384 | J8: =J26 -> 4659 | ... M8: =M26 -> 4085 | N8: =IFERROR(F8/E8, "-") -> 0.98449612 | O8: =IFERROR(F8/C8, "-") -> 0.98449612 | P8: =IFERROR(M8/D8, "-") -> 0.8767976 | Q8: =IFERROR(M8/I8,"-") -> 10.638021
B9: Sur | C9: =C34 -> 327 | D9: =D34 -> 4751 | E9: =E34 -> 327 | F9: =F34 -> 286 | G9: =G34 -> 41 | H9: =H34 -> 39 | I9: =I34 -> 325 | J9: =J34 -> 4751 | ... M9: =M34 -> 3729 | N9: =IFERROR(F9/E9, "-") -> 0.87461774 | O9: =IFERROR(F9/C9, "-") -> 0.87461774 | P9: =IFERROR(M9/D9, "-") -> 0.78488739 | Q9: =IFERROR(M9/I9,"-") -> 11.473846
B10: CASES Carmen Producción | C10: =C41 -> 147 | D10: =D41 -> 1667 | E10: =E41 -> 147 | F10: =F41 -> 138 | G10: =G41 -> 9 | H10: =H41 -> 12 | I10: =I41 -> 150 | J10: =J41 -> 1667 | ... M10: =M41 -> 1488 | N10: =IFERROR(F10/E10, "-") -> 0.93877551 | O10: =IFERROR(F10/C10, "-") -> 0.93877551 | P10: =IFERROR(M10/D10, "-") -> 0.89262148 | Q10: =IFERROR(M10/I10,"-") -> 9.92
B11: CASES Carmen Perforación | C11: =C37 -> 152 | D11: =D37 -> 2037 | E11: =E37 -> 152 | F11: =F37 -> 151 | G11: =G37 -> 1 | H11: =H37 -> 0 | I11: =I37 -> 151 | J11: =J37 -> 0 | ... M11: =M37 -> 1479 | N11: =IFERROR(F11/E11, "-") -> 0.99342105 | O11: =IFERROR(F11/C11, "-") -> 0.99342105 | P11: =IFERROR(M11/D11, "-") -> 0.72606775 | Q11: =IFERROR(M11/I11,"-") -> 9.794702
B12: CASES DB Producción | C12: =C42 -> 220 | D12: =D42 -> 3153 | E12: =E42 -> 220 | F12: =F42 -> 216 | G12: =G42 -> 4 | H12: =H42 -> 12 | I12: =I42 -> 228 | J12: =J42 -> 3153 | ... M12: =M42 -> 2648 | N12: =IFERROR(F12/E12, "-") -> 0.98181818 | O12: =IFERROR(F12/C12, "-") -> 0.98181818 | P12: =IFERROR(M12/D12, "-") -> 0.83983508 | Q12: =IFERROR(M12/I12,"-") -> 11.614035
B13: CASES DB Perforación | C13: =C38 -> 8 | D13: =D38 -> 62 | E13: =E38 -> 8 | F13: =F38 -> 8 | G13: =G38 -> 0 | H13: =H38 -> 2 | I13: =I38 -> 10 | J13: =J38 -> 0 | ... M13: =M38 -> 59 | N13: =IFERROR(F13/E13, "-") -> 1 | O13: =IFERROR(F13/C13, "-") -> 1 | P13: =IFERROR(M13/D13, "-") -> 0.9516129 | Q13: =IFERROR(M13/I13,"-") -> 5.9
B14: Perforación Terrestre | C14: =C36 -> 158 | D14: =D36 -> 1485 | E14: =E36 -> 158 | F14: =F36 -> 148 | G14: =G36 -> 10 | H14: =H36 -> 5 | I14: =I36 -> 153 | J14: =J36 -> 1485 | ... M14: =M36 -> 1062 | N14: =IFERROR(F14/E14, "-") -> 0.93670886 | O14: =IFERROR(F14/C14, "-") -> 0.93670886 | P14: =IFERROR(M14/D14, "-") -> 0.71515152 | Q14: =IFERROR(M14/I14,"-") -> 6.9411765
B15: Total PEP | C15: =SUM(C26,C34,C39,C43) -> 1399 | D15: =SUM(D26,D34,D39,D43) -> 17814 | E15: =SUM(E26,E34,E39,E43) -> 1399 | F15: =SUM(F26,F34,F39,F43) -> 1328 | G15: =SUM(G26,G34,G39,G43) -> 71 | H15: =SUM(H26,H34,H39,H43) -> 73 | I15: =SUM(I26,I34,I39,I43) -> 1401 | J15: =SUM(J26,J34,J39,J43) -> 15715 | ... M15: =SUM(M26,M34,M39,M43) -> 14550 | N15: =IFERROR(F15/E15, "-") -> 0.94924946 | O15: =IFERROR(F15/C15, "-") -> 0.94924946 | P15: =IFERROR(M15/D15, "-") -> 0.81677332 | Q15: =IFERROR(M15/I15,"-") -> 10.385439
E16: =IF((SUM(F15:G15)<E15),"Faltan ","Correcto") -> Correcto | F16: =IF(E15-SUM(F15:G15)=0,0,E15-SUM(F15:G15)) -> 0 | G16: registros | N16: =1-N15 -> 0.050750536 | O16: =1-O15 -> 0.050750536
B19: Reynosa | C19: =Reynosa!$H$5 -> 66 | D19: =Reynosa!$I$5 -> 869 | E19: =Reynosa!$J$5 -> 66 | F19: =Reynosa!$K$5 -> 66 | G19: =Reynosa!$L$5 -> 0 | H19: =Adicionales!F2 -> 0 | I19: =SUM(F19,H19) -> 66 | J19: =Reynosa!$N$5 -> 869 | K19: =Reynosa!$O$5 -> 825 | L19: =Adicionales!G2 -> 0 | M19: =SUM(K19:L19) -> 825 | N19: =IFERROR(F19/E19, "-") -> 1 | O19: =IFERROR(F19/C19, "-") -> 1
B20: Altamira | C20: =Altamira!$H$5 -> 55 | D20: =Altamira!$I$5 -> 635 | E20: =Altamira!$J$5 -> 55 | F20: =Altamira!$K$5 -> 55 | G20: =Altamira!$L$5 -> 0 | H20: =Adicionales!F3 -> 0 | I20: =SUM(F20,H20) -> 55 | J20: =Altamira!$N$5 -> 635 | K20: =Altamira!$O$5 -> 546 | L20: =Adicionales!G3 -> 0 | M20: =SUM(K20:L20) -> 546 | N20: =IFERROR(F20/E20, "-") -> 1 | O20: =IFERROR(F20/C20, "-") -> 1
B21: Naranjos | C21: =Naranjos!$H$5 -> 21 | D21: =Naranjos!$I$5 -> 328 | E21: =Naranjos!$J$5 -> 21 | F21: =Naranjos!$K$5 -> 21 | G21: =Naranjos!$L$5 -> 0 | H21: =Adicionales!F4 -> 0 | I21: =SUM(F21,H21) -> 21 | J21: =Naranjos!$N$5 -> 328 | K21: =Naranjos!$O$5 -> 300 | L21: =Adicionales!G4 -> 0 | M21: =SUM(K21:L21) -> 300 | N21: =IFERROR(F21/E21, "-") -> 1 | O21: =IFERROR(F21/C21, "-") -> 1
B22: Cerro Azul | C22: =Cerro_Azul!H5 -> 33 | D22: =Cerro_Azul!I5 -> 440 | E22: =Cerro_Azul!J5 -> 33 | F22: =Cerro_Azul!K5 -> 33 | G22: =Cerro_Azul!L5 -> 0 | H22: =Adicionales!F5 -> 0 | I22: =SUM(F22,H22) -> 33 | J22: =Cerro_Azul!N5 -> 440 | K22: =Cerro_Azul!O5 -> 360 | L22: =Adicionales!G5 -> 0 | M22: =SUM(K22:L22) -> 360 | N22: =IFERROR(F22/E22, "-") -> 1 | O22: =IFERROR(F22/C22, "-") -> 1
B23: Poza Rica | C23: =Poza_Rica!$H$5 -> 79 | D23: =Poza_Rica!$I$5 -> 1024 | E23: =Poza_Rica!$J$5 -> 79 | F23: =Poza_Rica!$K$5 -> 75 | G23: =Poza_Rica!$L$5 -> 4 | H23: =Adicionales!F6 -> 3 | I23: =SUM(F23,H23) -> 78 | J23: =Poza_Rica!$N$5 -> 1024 | K23: =Poza_Rica!$O$5 -> 799 | L23: =Adicionales!G6 -> 50 | M23: =SUM(K23:L23) -> 849 | N23: =IFERROR(F23/E23, "-") -> 0.94936709 | O23: =IFERROR(F23/C23, "-") -> 0.94936709
B24: Veracruz | C24: =Veracruz!$H$5 -> 128 | D24: =Veracruz!$I$5 -> 1329 | E24: =Veracruz!$J$5 -> 128 | F24: =Veracruz!$K$5 -> 126 | G24: =Veracruz!$L$5 -> 2 | H24: =Adicionales!F7 -> 0 | I24: =SUM(F24,H24) -> 126 | J24: =Veracruz!$N$5 -> 1329 | K24: =Veracruz!$O$5 -> 1166 | L24: =Adicionales!G7 -> 0 | M24: =SUM(K24:L24) -> 1166 | N24: =IFERROR(F24/E24, "-") -> 0.984375 | O24: =IFERROR(F24/C24, "-") -> 0.984375
B25: Cd. Madero | C25: =Cd_Madero!$H$5 -> 5 | D25: =Cd_Madero!$I$5 -> 34 | E25: =Cd_Madero!$J$5 -> 5 | F25: =Cd_Madero!$K$5 -> 5 | G25: =Cd_Madero!$L$5 -> 0 | H25: =Adicionales!F8 -> 0 | I25: =SUM(F25,H25) -> 5 | J25: =Cd_Madero!$N$5 -> 34 | K25: =Cd_Madero!$O$5 -> 39 | L25: =Adicionales!G8 -> 0 | M25: =SUM(K25:L25) -> 39 | N25: =IFERROR(F25/E25, "-") -> 1 | O25: =IFERROR(F25/C25, "-") -> 1
B26: Región Norte | C26: =SUM(C19:C25) -> 387 | D26: =SUM(D19:D25) -> 4659 | E26: =SUM(E19:E25) -> 387 | F26: =SUM(F19:F25) -> 381 | G26: =SUM(G19:G25) -> 6 | H26: =SUM(H19:H25) -> 3 | I26: =SUM(I19:I25) -> 384 | J26: =SUM(J19:J25) -> 4659 | ... M26: =SUM(M19:M25) -> 4085 | N26: =IFERROR(F26/E26, "-") -> 0.98449612 | O26: =IFERROR(F26/C26, "-") -> 0.98449612
B28: Agua Dulce | C28: =Agua_Dulce!$H$5 -> 85 | D28: =Agua_Dulce!$I$5 -> 1407 | E28: =Agua_Dulce!$J$5 -> 85 | F28: =Agua_Dulce!$K$5 -> 71 | G28: =Agua_Dulce!$L$5 -> 14 | H28: =Adicionales!F9 -> 12 | I28: =SUM(F28,H28) -> 83 | J28: =Agua_Dulce!$N$5 -> 1407 | K28: =Agua_Dulce!$O$5 -> 782 | L28: =Adicionales!G9 -> 201 | M28: =SUM(K28:L28) -> 983 | N28: =IFERROR(F28/E28, "-") -> 0.83529412 | O28: =IFERROR(F28/C28, "-") -> 0.83529412
B29: Comalcalco | C29: =Comalcalco!$H$5 -> 31 | D29: =Comalcalco!$I$5 -> 456 | E29: =Comalcalco!$J$5 -> 31 | F29: =Comalcalco!$K$5 -> 31 | G29: =Comalcalco!$L$5 -> 0 | H29: =Adicionales!F10 -> 8 | I29: =SUM(F29,H29) -> 39 | J29: =Comalcalco!$N$5 -> 456 | K29: =Comalcalco!$O$5 -> 372 | L29: =Adicionales!G10 -> 33 | M29: =SUM(K29:L29) -> 405 | N29: =IFERROR(F29/E29, "-") -> 1 | O29: =IFERROR(F29/C29, "-") -> 1
B30: El Castaño | C30: =El_Castaño!$H$5 -> 35 | D30: =El_Castaño!$I$5 -> 488 | E30: =El_Castaño!$J$5 -> 35 | F30: =El_Castaño!$K$5 -> 33 | G30: =El_Castaño!$L$5 -> 2 | H30: =Adicionales!F11 -> 2 | I30: =SUM(F30,H30) -> 35 | J30: =El_Castaño!$N$5 -> 488 | K30: =El_Castaño!$O$5 -> 370 | L30: =Adicionales!G11 -> 7 | M30: =SUM(K30:L30) -> 377 | N30: =IFERROR(F30/E30, "-") -> 0.94285714 | O30: =IFERROR(F30/C30, "-") -> 0.94285714
B31: Reforma | C31: =Reforma!$H$5 -> 79 | D31: =Reforma!$I$5 -> 916 | E31: =Reforma!$J$5 -> 79 | F31: =Reforma!$K$5 -> 65 | G31: =Reforma!$L$5 -> 14 | H31: =Adicionales!F12 -> 2 | I31: =SUM(F31,H31) -> 67 | J31: =Reforma!$N$5 -> 916 | K31: =Reforma!$O$5 -> 600 | L31: =Adicionales!G12 -> 25 | M31: =SUM(K31:L31) -> 625 | N31: =IFERROR(F31/E31, "-") -> 0.82278481 | O31: =IFERROR(F31/C31, "-") -> 0.82278481
B32: Cunduacán | C32: =Cunduacán!$H$5 -> 63 | D32: =Cunduacán!$I$5 -> 1000 | E32: =Cunduacán!$J$5 -> 63 | F32: =Cunduacán!$K$5 -> 62 | G32: =Cunduacán!$L$5 -> 1 | H32: =Adicionales!F13 -> 3 | I32: =SUM(F32,H32) -> 65 | J32: =Cunduacán!$N$5 -> 1000 | K32: =Cunduacán!$O$5 -> 807 | L32: =Adicionales!G13 -> 30 | M32: =SUM(K32:L32) -> 837 | N32: =IFERROR(F32/E32, "-") -> 0.98412698 | O32: =IFERROR(F32/C32, "-") -> 0.98412698
B33: Villahermosa | C33: =Villahermosa!$H$5 -> 34 | D33: =Villahermosa!$I$5 -> 484 | E33: =Villahermosa!$J$5 -> 34 | F33: =Villahermosa!$K$5 -> 24 | G33: =Villahermosa!$L$5 -> 10 | H33: =Adicionales!F14 -> 12 | I33: =SUM(F33,H33) -> 36 | J33: =Villahermosa!$N$5 -> 484 | K33: =Villahermosa!$O$5 -> 277 | L33: =Adicionales!G14 -> 225 | M33: =SUM(K33:L33) -> 502 | N33: =IFERROR(F33/E33, "-") -> 0.70588235 | O33: =IFERROR(F33/C33, "-") -> 0.70588235
B34: Región Sur | C34: =SUM(C28:C33) -> 327 | D34: =SUM(D28:D33) -> 4751 | E34: =SUM(E28:E33) -> 327 | F34: =SUM(F28:F33) -> 286 | G34: =SUM(G28:G33) -> 41 | H34: =SUM(H28:H33) -> 39 | I34: =SUM(I28:I33) -> 325 | J34: =SUM(J28:J33) -> 4751 | ... M34: =SUM(M28:M33) -> 3729 | N34: =IFERROR(I34/E34, "-") -> 0.99388379 | O34: =IFERROR(F34/C34, "-") -> 0.87461774
B36: SPMP_Tierra | C36: =SPMP_Tierra!H5 -> 158 | D36: =SPMP_Tierra!I5 -> 1485 | E36: =SPMP_Tierra!J5 -> 158 | F36: =SPMP_Tierra!K5 -> 148 | G36: =SPMP_Tierra!L5 -> 10 | H36: =Adicionales!$F$15 -> 5 | I36: =SUM(F36,H36) -> 153 | J36: =SPMP_Tierra!N5 -> 1485 | K36: =SPMP_Tierra!O5 -> 1031 | L36: =Adicionales!$G$15 -> 31 | M36: =SUM(K36:L36) -> 1062 | N36: =IFERROR(F36/E36, "-") -> 0.93670886 | O36: =IFERROR(F36/C36, "-") -> 0.93670886
B37: SPMP_Mar Carmen | C37: =SPMP_Mar!H6 -> 152 | D37: =SPMP_Mar!I6 -> 2037 | E37: =SPMP_Mar!J6 -> 152 | F37: =SPMP_Mar!K6 -> 151 | G37: =SPMP_Mar!L6 -> 1 | H37: =Adicionales!F16 -> 0 | I37: =SUM(F37,H37) -> 151 | J37: =SPMP_Mar!N6 -> 0 | K37: =SPMP_Mar!O6 -> 0 | L37: =SPMP_Mar!P6 -> 2037 | M37: =SPMP_Mar!Q6 -> 1479 | N37: =IFERROR(F37/E37, "-") -> 0.99342105 | O37: =IFERROR(F37/C37, "-") -> 0.99342105
B38: SPMP_Mar DB | C38: =SPMP_Mar!H5 -> 8 | D38: =SPMP_Mar!I5 -> 62 | E38: =SPMP_Mar!J5 -> 8 | F38: =SPMP_Mar!K5 -> 8 | G38: =SPMP_Mar!L5 -> 0 | H38: =Adicionales!F17 -> 2 | I38: =SUM(F38,H38) -> 10 | J38: =SPMP_Mar!N5 -> 0 | K38: =SPMP_Mar!O5 -> 0 | L38: =SPMP_Mar!P5 -> 62 | M38: =SPMP_Mar!Q5 -> 59 | N38: =IFERROR(F38/E38,"-") -> 1 | O38: =IFERROR(F38/C38, "-") -> 1
B39: Perforación | C39: =SUM(C36:C38) -> 318 | D39: =SUM(D36:D38) -> 3584 | E39: =SUM(E36:E38) -> 318 | F39: =SUM(F36:F38) -> 307 | G39: =SUM(G36:G38) -> 11 | H39: =SUM(H36:H38) -> 7 | I39: =SUM(I36:I38) -> 314 | J39: =SUM(J36:J38) -> 1485 | ... M39: =SUM(M36:M38) -> 2600 | N39: =IFERROR(F39/E39, "-") -> 0.96540881 | O39: =IFERROR(F39/C39, "-") -> 0.96540881
B41: CASES Carmen | C41: =CASES_Carmen!H5 -> 147 | D41: =CASES_Carmen!I5 -> 1667 | E41: =CASES_Carmen!J5 -> 147 | F41: =CASES_Carmen!K5 -> 138 | G41: =CASES_Carmen!L5 -> 9 | H41: =Adicionales!F18 -> 12 | I41: =SUM(F41,H41) -> 150 | J41: =CASES_Carmen!N5 -> 1667 | K41: =CASES_Carmen!O5 -> 1358 | L41: =Adicionales!G18 -> 130 | M41: =SUM(K41:L41) -> 1488 | N41: =IFERROR(F41/E41, "-") -> 0.93877551 | O41: =IFERROR(F41/C41, "-") -> 0.93877551
B42: CASES DB | C42: =CASES_DB!H5 -> 220 | D42: =CASES_DB!I5 -> 3153 | E42: =CASES_DB!J5 -> 220 | F42: =CASES_DB!K5 -> 216 | G42: =CASES_DB!L5 -> 4 | H42: =Adicionales!F19 -> 12 | I42: =SUM(F42,H42) -> 228 | J42: =CASES_DB!N5 -> 3153 | K42: =CASES_DB!O5 -> 2418 | L42: =Adicionales!G19 -> 230 | M42: =SUM(K42:L42) -> 2648 | N42: =IFERROR(F42/E42, "-") -> 0.98181818 | O42: =IFERROR(F42/C42, "-") -> 0.98181818
B43: Región Marina | C43: =SUM(C41:C42) -> 367 | D43: =SUM(D41:D42) -> 4820 | E43: =SUM(E41:E42) -> 367 | F43: =SUM(F41:F42) -> 354 | G43: =SUM(G41:G42) -> 13 | H43: =SUM(H41:H42) -> 24 | I43: =SUM(I41:I42) -> 378 | J43: =SUM(J41:J42) -> 4820 | ... M43: =SUM(M41:M42) -> 4136 | N43: =IFERROR(F43/E43, "-") -> 0.96457766 | O43: =IFERROR(F43/C43, "-") -> 0.96457766

Sheet Adicionales
F1: Cursos | G1: Capacitandos | R1: Adicionales | S1: 1 | T1: 2 | U1: 3 | V1: 4 | W1: 5 | X1: 6 | Y1: 7 | Z1: 8 | AA1: 9 | AB1: 10 | AC1: 11 | AD1: 12 | AE1: Total
E2: Reynosa | F2: =COUNTIFS($N$26:$N$290,1,$C$26:$C$290,$E2) -> 0 | G2: =SUMIFS($K$26:$K$290,$N$26:$N$290,1,$C$26:$C$290,$E2) -> 0 | R2: SCOC | S2: =COUNTIFS($P$26:$P$308,S$1,$D$26:$D$308,$R2) -> 0 | T2: =COUNTIFS($P$26:$P$308,T$1,$D$26:$D$308,$R2) -> 0 | U2: =COUNTIFS($P$26:$P$308,U$1,$D$26:$D$308,$R2) -> 0 | V2: =COUNTIFS($P$26:$P$308,V$1,$D$26:$D$308,$R2) -> 0 | W2: =COUNTIFS($P$26:$P$308,W$1,$D$26:$D$308,$R2) -> 3 | X2: =COUNTIFS($P$26:$P$308,X$1,$D$26:$D$308,$R2) -> 6 | Y2: =COUNTIFS($P$26:$P$308,Y$1,$D$26:$D$308,$R2) -> 0 | Z2: =COUNTIFS($P$26:$P$308,Z$1,$D$26:$D$308,$R2) -> 0 | ... AD2: =COUNTIFS($P$26:$P$308,AD$1,$D$26:$D$308,$R2) -> 0 | AE2: =SUM(S2:AD2) -> 9
B3: =Seguimiento!$E$6 -> 44927 | C3: =Seguimiento!$J$6 -> 45291 | E3: Altamira | F3: =COUNTIFS($N$26:$N$290,1,$C$26:$C$290,$E3) -> 0 | G3: =SUMIFS($K$26:$K$290,$N$26:$N$290,1,$C$26:$C$290,$E3) -> 0 | R3: SE | S3: =COUNTIFS($P$26:$P$308,S$1,$D$26:$D$308,$R3) -> 0 | T3: =COUNTIFS($P$26:$P$308,T$1,$D$26:$D$308,$R3) -> 0 | U3: =COUNTIFS($P$26:$P$308,U$1,$D$26:$D$308,$R3) -> 0 | V3: =COUNTIFS($P$26:$P$308,V$1,$D$26:$D$308,$R3) -> 0 | W3: =COUNTIFS($P$26:$P$308,W$1,$D$26:$D$308,$R3) -> 0 | X3: =COUNTIFS($P$26:$P$308,X$1,$D$26:$D$308,$R3) -> 0 | Y3: =COUNTIFS($P$26:$P$308,Y$1,$D$26:$D$308,$R3) -> 0 | Z3: =COUNTIFS($P$26:$P$308,Z$1,$D$26:$D$308,$R3) -> 0 | ... AD3: =COUNTIFS($P$26:$P$308,AD$1,$D$26:$D$308,$R3) -> 0 | AE3: =SUM(S3:AD3) -> 0
E4: Naranjos | F4: =COUNTIFS($N$26:$N$290,1,$C$26:$C$290,$E4) -> 0 | G4: =SUMIFS($K$26:$K$290,$N$26:$N$290,1,$C$26:$C$290,$E4) -> 0 | R4: SEPCA | S4: =COUNTIFS($P$26:$P$308,S$1,$D$26:$D$308,$R4) -> 0 | T4: =COUNTIFS($P$26:$P$308,T$1,$D$26:$D$308,$R4) -> 0 | U4: =COUNTIFS($P$26:$P$308,U$1,$D$26:$D$308,$R4) -> 0 | V4: =COUNTIFS($P$26:$P$308,V$1,$D$26:$D$308,$R4) -> 0 | W4: =COUNTIFS($P$26:$P$308,W$1,$D$26:$D$308,$R4) -> 0 | X4: =COUNTIFS($P$26:$P$308,X$1,$D$26:$D$308,$R4) -> 0 | Y4: =COUNTIFS($P$26:$P$308,Y$1,$D$26:$D$308,$R4) -> 0 | Z4: =COUNTIFS($P$26:$P$308,Z$1,$D$26:$D$308,$R4) -> 0 | ... AD4: =COUNTIFS($P$26:$P$308,AD$1,$D$26:$D$308,$R4) -> 0 | AE4: =SUM(S4:AD4) -> 0
E5: Cerro Azul | F5: =COUNTIFS($N$26:$N$290,1,$C$26:$C$290,$E5) -> 0 | G5: =SUMIFS($K$26:$K$290,$N$26:$N$290,1,$C$26:$C$290,$E5) -> 0 | R5: SMLIC | S5: =COUNTIFS($P$26:$P$308,S$1,$D$26:$D$308,$R5) -> 0 | T5: =COUNTIFS($P$26:$P$308,T$1,$D$26:$D$308,$R5) -> 0 | U5: =COUNTIFS($P$26:$P$308,U$1,$D$26:$D$308,$R5) -> 0 | V5: =COUNTIFS($P$26:$P$308,V$1,$D$26:$D$308,$R5) -> 0 | W5: =COUNTIFS($P$26:$P$308,W$1,$D$26:$D$308,$R5) -> 0 | X5: =COUNTIFS($P$26:$P$308,X$1,$D$26:$D$308,$R5) -> 0 | Y5: =COUNTIFS($P$26:$P$308,Y$1,$D$26:$D$308,$R5) -> 0 | Z5: =COUNTIFS($P$26:$P$308,Z$1,$D$26:$D$308,$R5) -> 0 | ... AD5: =COUNTIFS($P$26:$P$308,AD$1,$D$26:$D$308,$R5) -> 0 | AE5: =SUM(S5:AD5) -> 0
E6: Poza Rica | F6: =COUNTIFS($N$26:$N$290,1,$C$26:$C$290,$E6) -> 3 | G6: =SUMIFS($K$26:$K$290,$N$26:$N$290,1,$C$26:$C$290,$E6) -> 50 | R6: SPEE | S6: =COUNTIFS($P$26:$P$308,S$1,$D$26:$D$308,$R6) -> 0 | T6: =COUNTIFS($P$26:$P$308,T$1,$D$26:$D$308,$R6) -> 0 | U6: =COUNTIFS($P$26:$P$308,U$1,$D$26:$D$308,$R6) -> 0 | V6: =COUNTIFS($P$26:$P$308,V$1,$D$26:$D$308,$R6) -> 0 | W6: =COUNTIFS($P$26:$P$308,W$1,$D$26:$D$308,$R6) -> 0 | X6: =COUNTIFS($P$26:$P$308,X$1,$D$26:$D$308,$R6) -> 0 | Y6: =COUNTIFS($P$26:$P$308,Y$1,$D$26:$D$308,$R6) -> 0 | Z6: =COUNTIFS($P$26:$P$308,Z$1,$D$26:$D$308,$R6) -> 0 | ... AD6: =COUNTIFS($P$26:$P$308,AD$1,$D$26:$D$308,$R6) -> 0 | AE6: =SUM(S6:AD6) -> 0
E7: Veracruz | F7: =COUNTIFS($N$26:$N$290,1,$C$26:$C$290,$E7) -> 0 | G7: =SUMIFS($K$26:$K$290,$N$26:$N$290,1,$C$26:$C$290,$E7) -> 0 | R7: SPMP | S7: =COUNTIFS($P$26:$P$308,S$1,$D$26:$D$308,$R7) -> 0 | T7: =COUNTIFS($P$26:$P$308,T$1,$D$26:$D$308,$R7) -> 0 | U7: =COUNTIFS($P$26:$P$308,U$1,$D$26:$D$308,$R7) -> 0 | V7: =COUNTIFS($P$26:$P$308,V$1,$D$26:$D$308,$R7) -> 0 | W7: =COUNTIFS($P$26:$P$308,W$1,$D$26:$D$308,$R7) -> 7 | X7: =COUNTIFS($P$26:$P$308,X$1,$D$26:$D$308,$R7) -> 2 | Y7: =COUNTIFS($P$26:$P$308,Y$1,$D$26:$D$308,$R7) -> 0 | Z7: =COUNTIFS($P$26:$P$308,Z$1,$D$26:$D$308,$R7) -> 0 | ... AD7: =COUNTIFS($P$26:$P$308,AD$1,$D$26:$D$308,$R7) -> 0 | AE7: =SUM(S7:AD7) -> 9
E8: Cd. Madero | F8: =COUNTIFS($N$26:$N$290,1,$C$26:$C$290,$E8) -> 0 | G8: =SUMIFS($K$26:$K$290,$N$26:$N$290,1,$C$26:$C$290,$E8) -> 0 | R8: SPRMNE | S8: =COUNTIFS($P$26:$P$308,S$1,$D$26:$D$308,$R8) -> 0 | T8: =COUNTIFS($P$26:$P$308,T$1,$D$26:$D$308,$R8) -> 0 | U8: =COUNTIFS($P$26:$P$308,U$1,$D$26:$D$308,$R8) -> 0 | V8: =COUNTIFS($P$26:$P$308,V$1,$D$26:$D$308,$R8) -> 0 | W8: =COUNTIFS($P$26:$P$308,W$1,$D$26:$D$308,$R8) -> 0 | X8: =COUNTIFS($P$26:$P$308,X$1,$D$26:$D$308,$R8) -> 0 | Y8: =COUNTIFS($P$26:$P$308,Y$1,$D$26:$D$308,$R8) -> 0 | Z8: =COUNTIFS($P$26:$P$308,Z$1,$D$26:$D$308,$R8) -> 0 | ... AD8: =COUNTIFS($P$26:$P$308,AD$1,$D$26:$D$308,$R8) -> 1 | AE8: =SUM(S8:AD8) -> 1
E9: Agua Dulce | F9: =COUNTIFS($N$26:$N$290,1,$C$26:$C$290,$E9) -> 12 | G9: =SUMIFS($K$26:$K$290,$N$26:$N$290,1,$C$26:$C$290,$E9) -> 201 | R9: SPRMSO | S9: =COUNTIFS($P$26:$P$308,S$1,$D$26:$D$308,$R9) -> 0 | T9: =COUNTIFS($P$26:$P$308,T$1,$D$26:$D$308,$R9) -> 0 | U9: =COUNTIFS($P$26:$P$308,U$1,$D$26:$D$308,$R9) -> 0 | V9: =COUNTIFS($P$26:$P$308,V$1,$D$26:$D$308,$R9) -> 0 | W9: =COUNTIFS($P$26:$P$308,W$1,$D$26:$D$308,$R9) -> 0 | X9: =COUNTIFS($P$26:$P$308,X$1,$D$26:$D$308,$R9) -> 0 | Y9: =COUNTIFS($P$26:$P$308,Y$1,$D$26:$D$308,$R9) -> 0 | Z9: =COUNTIFS($P$26:$P$308,Z$1,$D$26:$D$308,$R9) -> 0 | ... AD9: =COUNTIFS($P$26:$P$308,AD$1,$D$26:$D$308,$R9) -> 0 | AE9: =SUM(S9:AD9) -> 0
E10: Comalcalco | F10: =COUNTIFS($N$26:$N$290,1,$C$26:$C$290,$E10) -> 8 | G10: =SUMIFS($K$26:$K$290,$N$26:$N$290,1,$C$26:$C$290,$E10) -> 33 | R10: SPRN | S10: =COUNTIFS($P$26:$P$308,S$1,$D$26:$D$308,$R10) -> 0 | T10: =COUNTIFS($P$26:$P$308,T$1,$D$26:$D$308,$R10) -> 0 | U10: =COUNTIFS($P$26:$P$308,U$1,$D$26:$D$308,$R10) -> 0 | V10: =COUNTIFS($P$26:$P$308,V$1,$D$26:$D$308,$R10) -> 0 | W10: =COUNTIFS($P$26:$P$308,W$1,$D$26:$D$308,$R10) -> 0 | X10: =COUNTIFS($P$26:$P$308,X$1,$D$26:$D$308,$R10) -> 0 | Y10: =COUNTIFS($P$26:$P$308,Y$1,$D$26:$D$308,$R10) -> 0 | Z10: =COUNTIFS($P$26:$P$308,Z$1,$D$26:$D$308,$R10) -> 0 | ... AD10: =COUNTIFS($P$26:$P$308,AD$1,$D$26:$D$308,$R10) -> 0 | AE10: =SUM(S10:AD10) -> 0
E11: El Castaño | F11: =COUNTIFS($N$26:$N$290,1,$C$26:$C$290,$E11) -> 2 | G11: =SUMIFS($K$26:$K$290,$N$26:$N$290,1,$C$26:$C$290,$E11) -> 7 | R11: SPRS | S11: =COUNTIFS($P$26:$P$308,S$1,$D$26:$D$308,$R11) -> 0 | T11: =COUNTIFS($P$26:$P$308,T$1,$D$26:$D$308,$R11) -> 0 | U11: =COUNTIFS($P$26:$P$308,U$1,$D$26:$D$308,$R11) -> 0 | V11: =COUNTIFS($P$26:$P$308,V$1,$D$26:$D$308,$R11) -> 0 | W11: =COUNTIFS($P$26:$P$308,W$1,$D$26:$D$308,$R11) -> 0 | X11: =COUNTIFS($P$26:$P$308,X$1,$D$26:$D$308,$R11) -> 4 | Y11: =COUNTIFS($P$26:$P$308,Y$1,$D$26:$D$308,$R11) -> 0 | Z11: =COUNTIFS($P$26:$P$308,Z$1,$D$26:$D$308,$R11) -> 4 | ... AD11: =COUNTIFS($P$26:$P$308,AD$1,$D$26:$D$308,$R11) -> 0 | AE11: =SUM(S11:AD11) -> 13
E12: Reforma | F12: =COUNTIFS($N$26:$N$290,1,$C$26:$C$290,$E12) -> 2 | G12: =SUMIFS($K$26:$K$290,$N$26:$N$290,1,$C$26:$C$290,$E12) -> 25 | R12: SSSTPA | S12: =COUNTIFS($P$26:$P$308,S$1,$D$26:$D$308,$R12) -> 0 | T12: =COUNTIFS($P$26:$P$308,T$1,$D$26:$D$308,$R12) -> 1 | U12: =COUNTIFS($P$26:$P$308,U$1,$D$26:$D$308,$R12) -> 4 | V12: =COUNTIFS($P$26:$P$308,V$1,$D$26:$D$308,$R12) -> 1 | W12: =COUNTIFS($P$26:$P$308,W$1,$D$26:$D$308,$R12) -> 4 | X12: =COUNTIFS($P$26:$P$308,X$1,$D$26:$D$308,$R12) -> 2 | Y12: =COUNTIFS($P$26:$P$308,Y$1,$D$26:$D$308,$R12) -> 0 | Z12: =COUNTIFS($P$26:$P$308,Z$1,$D$26:$D$308,$R12) -> 12 | ... AD12: =COUNTIFS($P$26:$P$308,AD$1,$D$26:$D$308,$R12) -> 1 | AE12: =SUM(S12:AD12) -> 31
E13: Cunduacán | F13: =COUNTIFS($N$26:$N$290,1,$C$26:$C$290,$E13) -> 3 | G13: =SUMIFS($K$26:$K$290,$N$26:$N$290,1,$C$26:$C$290,$E13) -> 30 | R13: Total | S13: =SUM(S2:S12) -> 0 | T13: =SUM(T2:T12) -> 1 | U13: =SUM(U2:U12) -> 4 | V13: =SUM(V2:V12) -> 1 | W13: =SUM(W2:W12) -> 14 | X13: =SUM(X2:X12) -> 14 | Y13: =SUM(Y2:Y12) -> 0 | Z13: =SUM(Z2:Z12) -> 16 | ... AE13: =SUM(AE2:AE12) -> 63
E14: Villahermosa | F14: =COUNTIFS($N$26:$N$290,1,$C$26:$C$290,$E14) -> 12 | G14: =SUMIFS($K$26:$K$290,$N$26:$N$290,1,$C$26:$C$290,$E14) -> 225
E15: SPMP Tierra | F15: =COUNTIFS($N$26:$N$290,1,$C$26:$C$290,$E15) -> 5 | G15: =SUMIFS($K$26:$K$290,$N$26:$N$290,1,$C$26:$C$290,$E15) -> 31
E16: SPMP_Mar Carmen | F16: =COUNTIFS($N$26:$N$290,1,$C$26:$C$290,$E16) -> 0 | G16: =SUMIFS($K$26:$K$290,$N$26:$N$290,1,$C$26:$C$290,$E16) -> 0
E17: SPMP_Mar DB | F17: =COUNTIFS($N$26:$N$290,1,$C$26:$C$290,$E17) -> 2 | G17: =SUMIFS($K$26:$K$290,$N$26:$N$290,1,$C$26:$C$290,$E17) -> 13
E18: Ciudad del Carmen | F18: =COUNTIFS($N$26:$N$290,1,$C$26:$C$290,$E18) -> 12 | G18: =SUMIFS($K$26:$K$290,$N$26:$N$290,1,$C$26:$C$290,$E18) -> 130
E19: Dos Bocas | F19: =COUNTIFS($N$26:$N$290,1,$C$26:$C$290,$E19) -> 12 | G19: =SUMIFS($K$26:$K$290,$N$26:$N$290,1,$C$26:$C$290,$E19) -> 230
E20: PLOG | F20: =COUNTIFS($N$26:$N$290,1,$D$26:$D$290,$E20) -> 10 | G20: =SUMIFS($K$26:$K$290,$N$26:$N$290,1,$D$26:$D$290,$E20) -> 113
E21: Totales | F21: =SUM(F2:F20) -> 83 | G21: =SUM(G2:G20) -> 1088
C23: Cursos adicionales al PICADE original
A25: Cons | B25: Clave | C25: CASES | D25: Subdirección | E25: Gerencia/Activo | F25: Curso | G25: Tipo de Impartición | H25: Ficha | I25: Instructor | J25: Duración (Horas) | K25: Asistentes Totales | L25: Fecha de Inicio | M25: Fecha de Termino | N25: Periodo | O25: Observaciones | P25: MES
A26: 1 | B26: 50650305 | C26: Villahermosa | D26: SSSTPA | E26: GSPSSPAIP | F26: Concepos Básicos de ARP | G26: Presencial | H26: Externo | I26: =IFERROR((VLOOKUP(H26,Padrón[[Ficha]:[Nombre]],2,FALSE)),"-") -> - | J26: 24 | K26: 17 | L26: 44972 | M26: 44974 | N26: =IF(AND(M26>=$B$3,M26<=$C$3),1,"-") -> 1 | P26: =IF(M26="","0",(MONTH(M26))) -> 2
A27: 2 | B27: 50649861 | C27: Villahermosa | D27: SSSTPA | E27: GSPSSPAIP | F27: Curso PHAST instalaciones terrestres | G27: Presencial | H27: Externo | I27: =IFERROR((VLOOKUP(H27,Padrón[[Ficha]:[Nombre]],2,FALSE)),"-") -> - | J27: 40 | K27: 20 | L27: 44984 | M27: 44988 | N27: =IF(AND(M27>=$B$3,M27<=$C$3),1,"-") -> 1 | P27: =IF(M27="","0",(MONTH(M27))) -> 3
A28: 3 | B28: 50649912 | C28: Ciudad del Carmen | D28: SSSTPA | E28: GSPSSPAIP | F28: Curso Análisis de Capas de Protección LOPA | G28: Presencial | H28: Externo | I28: =IFERROR((VLOOKUP(H28,Padrón[[Ficha]:[Nombre]],2,FALSE)),"-") -> - | J28: 24 | K28: 14 | L28: 44986 | M28: 44988 | N28: =IF(AND(M28>=$B$3,M28<=$C$3),1,"-") -> 1 | P28: =IF(M28="","0",(MONTH(M28))) -> 3
A29: 4 | B29: 50649950 | C29: Ciudad del Carmen | D29: SSSTPA | E29: GSPSSPAIP | F29: Curso PHAST instalaciones marinas | G29: Presencial | H29: Externo | I29: =IFERROR((VLOOKUP(H29,Padrón[[Ficha]:[Nombre]],2,FALSE)),"-") -> - | J29: 40 | K29: 12 | L29: 45012 | M29: 45016 | N29: =IF(AND(M29>=$B$3,M29<=$C$3),1,"-") -> 1 | P29: =IF(M29="","0",(MONTH(M29))) -> 3
A30: 5 | B30: 50650022 | C30: Villahermosa | D30: SSSTPA | E30: GSPSSPAIP | F30: Instrumentación de Proyectos de Mejora de Procesos | G30: Distancia | H30: 495716 | I30: =IFERROR((VLOOKUP(H30,Padrón[[Ficha]:[Nombre]],2,FALSE)),"-") -> ENRIQUE GABRIEL ALVAREZ ALMAZAN | J30: 10 | K30: 19 | L30: 45012 | M30: 45016 | N30: =IF(AND(M30>=$B$3,M30<=$C$3),1,"-") -> 1 | P30: =IF(M30="","0",(MONTH(M30))) -> 3
A31: 6 | B31: 50656014 | C31: Ciudad del Carmen | D31: SSSTPA | E31: GSPSSPAIP | F31: Capacitación en Conceptos Básicos de Análisis de Riesgo de Proceso | G31: Presencial | H31: Externo | I31: =IFERROR((VLOOKUP(H31,Padrón[[Ficha]:[Nombre]],2,FALSE)),"-") -> - | J31: 24 | K31: 11 | L31: 45035 | M31: 45037 | N31: =IF(AND(M31>=$B$3,M31<=$C$3),1,"-") -> 1 | P31: =IF(M31="","0",(MONTH(M31))) -> 4
A32: 7 | B32: 50656016 | C32: Villahermosa | D32: SSSTPA | E32: GSPSSPAIP | F32: Conceptos Básicos de ARP | G32: Presencial | H32: Externo | I32: =IFERROR((VLOOKUP(#REF!,Padrón[[Ficha]:[Nombre]],2,FALSE)),"-") -> - | J32: 24 | K32: 23 | L32: 45056 | M32: 45058 | N32: =IF(AND(M32>=$B$3,M32<=$C$3),1,"-") -> 1 | P32: =IF(M32="","0",(MONTH(M32))) -> 5
A33: 8 | B33: 50656018 | C33: Villahermosa | D33: SSSTPA | E33: GSPSSPAIP | F33: Métodos Cualitativos | G33: Presencial | H33: Externo | I33: =IFERROR((VLOOKUP(H33,Padrón[[Ficha]:[Nombre]],2,FALSE)),"-") -> - | J33: 40 | K33: 21 | L33: 45061 | M33: 45065 | N33: =IF(AND(M33>=$B$3,M33<=$C$3),1,"-") -> 1 | P33: =IF(M33="","0",(MONTH(M33))) -> 5
A34: 9 | B34: 50656019 | C34: Poza Rica | D34: SSSTPA | E34: GSPSSPAIP | F34: Métodos Cualitativos | G34: Presencial | H34: Externo | I34: =IFERROR((VLOOKUP(H34,Padrón[[Ficha]:[Nombre]],2,FALSE)),"-") -> - | J34: 40 | K34: 21 | L34: 45061 | M34: 45065 | N34: =IF(AND(M33>=$B$3,M33<=$C$3),1,"-") -> 1 | P34: =IF(M34="","0",(MONTH(M34))) -> 5
A35: 10 | B35: 50656020 | C35: Ciudad del Carmen | D35: SSSTPA | E35: GSPSSPAIP | F35: Métodos Cualitativos | G35: Presencial | H35: Externo | I35: =IFERROR((VLOOKUP(H35,Padrón[[Ficha]:[Nombre]],2,FALSE)),"-") -> - | J35: 40 | K35: 13 | L35: 45075 | M35: 45079 | N35: =IF(AND(M35>=$B$3,M35<=$C$3),1,"-") -> 1 | P35: =IF(M35="","0",(MONTH(M35))) -> 6
A36: 11 | B36: 50664522 | C36: SPMP_Mar DB | D36: SPMP | E36: GOME | F36: BÁSICO DE SEGURIDAD (BS) | G36: Presencial | H36: 384599 | I36: =IFERROR((VLOOKUP(H36,Padrón[[Ficha]:[Nombre]],2,FALSE)),"-") -> MARLON DANIEL MARTINEZ COBA | J36: 16 | K36: 6 | L36: 45049 | M36: 45050 | N36: =IF(AND(M36>=$B$3,M36<=$C$3),1,"-") -> 1 | P36: =IF(M36="","0",(MONTH(M36))) -> 5
A37: 12 | B37: 50664523 | C37: SPMP_Mar DB | D37: SPMP | E37: GOME | F37: BÁSICO DE SEGURIDAD (BS) | G37: Presencial | H37: 384599 | I37: =IFERROR((VLOOKUP(H37,Padrón[[Ficha]:[Nombre]],2,FALSE)),"-") -> MARLON DANIEL MARTINEZ COBA | J37: 16 | K37: 7 | L37: 45055 | M37: 45056 | N37: =IF(AND(M37>=$B$3,M37<=$C$3),1,"-") -> 1 | P37: =IF(M37="","0",(MONTH(M37))) -> 5
A38: 13 | B38: 50655529 | C38: SPMP Tierra | D38: SPMP | E38: GSSTPAP | F38: PROCEDIMIENTOS CRÍTICOS (PC) | G38: Presencial | I38: =IFERROR((VLOOKUP(H38,Padrón[[Ficha]:[Nombre]],2,FALSE)),"-") -> - | K38: 4 | L38: 45051 | M38: 45052 | N38: =IF(AND(M38>=$B$3,M38<=$C$3),1,"-") -> 1 | P38: =IF(M38="","0",(MONTH(M38))) -> 5
A39: 14 | B39: 50655530 | C39: SPMP Tierra | D39: SPMP | E39: GSSTPAP | F39: PROCEDIMIENTOS CRÍTICOS (PC) | G39: Presencial | I39: =IFERROR((VLOOKUP(H39,Padrón[[Ficha]:[Nombre]],2,FALSE)),"-") -> - | K39: 4 | L39: 45054 | M39: 45055 | N39: =IF(AND(M39>=$B$3,M39<=$C$3),1,"-") -> 1 | P39: =IF(M39="","0",(MONTH(M39))) -> 5
A40: 15 | B40: 50655056 | C40: SPMP Tierra | D40: SPMP | E40: GSSTPAP | F40: PROCEDIMIENTO TÉCNICO OPERATIVO ANÁLISIS DE SEGURIDAD AST | G40: Presencial | I40: =IFERROR((VLOOKUP(H40,Padrón[[Ficha]:[Nombre]],2,FALSE)),"-") -> - | K40: 10 | L40: 45048 | M40: 45049 | N40: =IF(AND(M40>=$B$3,M40<=$C$3),1,"-") -> 1 | P40: =IF(M40="","0",(MONTH(M40))) -> 5
A41: 16 | B41: 50655058 | C41: SPMP Tierra | D41: SPMP | E41: GSSTPAP | F41: PROCEDIMIENTO TÉCNICO OPERATIVO ANÁLISIS DE SEGURIDAD AST | G41: Presencial | I41: =IFERROR((VLOOKUP(H41,Padrón[[Ficha]:[Nombre]],2,FALSE)),"-") -> - | K41: 6 | L41: 45054 | M41: 45055 | N41: =IF(AND(M41>=$B$3,M41<=$C$3),1,"-") -> 1 | P41: =IF(M41="","0",(MONTH(M41))) -> 5
A42: 17 | B42: 50655065 | C42: SPMP Tierra | D42: SPMP | E42: GSSTPAP | F42: PROCEDIMIENTO TÉCNICO OPERATIVO ANÁLISIS DE SEGURIDAD AST | G42: Presencial | I42: =IFERROR((VLOOKUP(H42,Padrón[[Ficha]:[Nombre]],2,FALSE)),"-") -> - | K42: 7 | L42: 45057 | M42: 45058 | N42: =IF(AND(M42>=$B$3,M42<=$C$3),1,"-") -> 1 | P42: =IF(M42="","0",(MONTH(M42))) -> 5
A43: 18 | B43: 50665751 | C43: Dos Bocas | D43: SCOC | E43: SCOC | F43: SISTEMA DE PERMISOS PARA TRABAJOS CON RIESGO (SPTR) | G43: Presencial | H43: 971841 | I43: =IFERROR((VLOOKUP(H43,Padrón[[Ficha]:[Nombre]],2,FALSE)),"-") -> TOBIAS MAGAÑA RUIZ | J43: 24 | K43: 24 | L43: 45065 | M43: 45067 | N43: =IF(AND(M43>=$B$3,M43<=$C$3),1,"-") -> 1 | P43: =IF(M43="","0",(MONTH(M43))) -> 5
A44: 19 | B44: 50665602 | C44: Villahermosa | D44: SSSTPA | E44: GSPSSPAIP | F44: Adiestramiento en el uso de tecnología del software para realizar ARP aplicando la metodología Bow Tie | G44: Presencial | H44: Externo | I44: =IFERROR((VLOOKUP(H44,Padrón[[Ficha]:[Nombre]],2,FALSE)),"-") -> - | J44: 40 | K44: 13 | L44: 45068 | M44: 45072 | N44: =IF(AND(M44>=$B$3,M44<=$C$3),1,"-") -> 1 | P44: =IF(M44="","0",(MONTH(M44))) -> 5
A45: 20 | B45: 50665752 | C45: Dos Bocas | D45: SCOC | E45: SCOC | F45: SEGURIDAD SOBREVIVENCIA COSTA AFUERA | G45: Presencial | H45: 370733 | I45: =IFERROR((VLOOKUP(H45,Padrón[[Ficha]:[Nombre]],2,FALSE)),"-") -> JOSE GUADALUPE RESENDIZ ROBLES | J45: 24 | K45: 25 | L45: 45068 | M45: 45070 | N45: =IF(AND(M45>=$B$3,M45<=$C$3),1,"-") -> 1 | P45: =IF(M45="","0",(MONTH(M45))) -> 5
A46: 21 | B46: 50666002 | C46: Dos Bocas | D46: SCOC | E46: SCOC | F46: SISTEMA DE PERMISOS PARA TRABAJOS CON RIESGO (SPTR) | G46: Presencial | H46: 322115 | I46: =IFERROR((VLOOKUP(H46,Padrón[[Ficha]:[Nombre]],2,FALSE)),"-") -> EDUARDO MOHENO TORRES | J46: 24 | K46: 25 | L46: 31/05/20223 | M46: 45079 | N46: =IF(AND(M46>=$B$3,M46<=$C$3),1,"-") -> 1 | P46: =IF(M46="","0",(MONTH(M46))) -> 6
A47: 22 | B47: 50656810 | C47: Ciudad del Carmen | D47: PLOG | E47: GOTLPM | F47: BÁSICO DE SEGURIDAD (BS) (CC) | G47: Presencial | H47: 405175 | I47: =IFERROR((VLOOKUP(H47,Padrón[[Ficha]:[Nombre]],2,FALSE)),"-") -> ANGEL ISRAEL ESCASENA MARTINEZ | J47: 16 | K47: 11 | L47: 45075 | M47: 45076 | N47: =IF(AND(M47>=$B$3,M47<=$C$3),1,"-") -> 1 | P47: =IF(M47="","0",(MONTH(M47))) -> 5
A48: 23 | B48: 50655617 | C48: Dos Bocas | D48: SPMP | E48: GOME | F48: BRIGADAS DE PRIMEROS AUXILIOS | G48: Presencial | H48: 415202 | I48: =IFERROR((VLOOKUP(H48,Padrón[[Ficha]:[Nombre]],2,FALSE)),"-") -> HERMILO VAZQUEZ HERNANDEZ | J48: 16 | K48: 6 | L48: 45080 | M48: 45081 | N48: =IF(AND(M48>=$B$3,M48<=$C$3),1,"-") -> 1 | P48: =IF(M48="","0",(MONTH(M48))) -> 6
A49: 24 | B49: 50655567 | C49: Dos Bocas | D49: SPMP | E49: GOME | F49: BRIGADAS CONTRAINCENDIOS | G49: Presencial | H49: 415202 | I49: =IFERROR((VLOOKUP(H49,Padrón[[Ficha]:[Nombre]],2,FALSE)),"-") -> HERMILO VAZQUEZ HERNANDEZ | J49: 24 | K49: 6 | L49: 45082 | M49: 45084 | N49: =IF(AND(M49>=$B$3,M49<=$C$3),1,"-") -> 1 | P49: =IF(M49="","0",(MONTH(M49))) -> 6
A50: 25 | B50: 50665601 | C50: Poza Rica | D50: SSSTPA | E50: GSPSSPAIP | F50: Adiestramiento en el uso de tecnología del software para realizar ARP aplicando la metodología Bow Tie | G50: Presencial | H50: Externo | I50: =IFERROR((VLOOKUP(H50,Padrón[[Ficha]:[Nombre]],2,FALSE)),"-") -> - | J50: 40 | K50: 19 | L50: 45096 | M50: 45100 | N50: =IF(AND(M50>=$B$3,M50<=$C$3),1,"-") -> 1 | P50: =IF(M50="","0",(MONTH(M50))) -> 6
A51: 26 | B51: 50666001 | C51: Dos Bocas | D51: SCOC | E51: SCOC | F51: SEGURIDAD SOBREVIVENCIA COSTA AFUERA | G51: Presencial | H51: 384599 | I51: =IFERROR((VLOOKUP(H51,Padrón[[Ficha]:[Nombre]],2,FALSE)),"-") -> MARLON DANIEL MARTINEZ COBA | J51: 24 | K51: 25 | L51: 45074 | M51: 45076 | N51: =IF(AND(M51>=$B$3,M51<=$C$3),1,"-") -> 1 | P51: =IF(M51="","0",(MONTH(M51))) -> 5
A52: 27 | B52: 50666325 | C52: Dos Bocas | D52: SCOC | E52: SCOC | F52: BÁSICO DE SEGURIDAD (BS) | G52: Presencial | H52: 322115 | I52: =IFERROR((VLOOKUP(H52,Padrón[[Ficha]:[Nombre]],2,FALSE)),"-") -> EDUARDO MOHENO TORRES | J52: 16 | K52: 25 | L52: 45092 | M52: 45093 | N52: =IF(AND(M52>=$B$3,M52<=$C$3),1,"-") -> 1 | P52: =IF(M52="","0",(MONTH(M52))) -> 6
A53: 28 | B53: 50666326 | C53: Dos Bocas | D53: SCOC | E53: SCOC | F53: SISTEMA DE PERMISOS PARA TRABAJOS CON RIESGO (SPTR) | G53: Presencial | H53: 245435 | I53: =IFERROR((VLOOKUP(H53,Padrón[[Ficha]:[Nombre]],2,FALSE)),"-") -> CESAR VALENCIA VIVEROS | J53: 24 | K53: 22 | L53: 16/06/20232 | M53: 45095 | N53: =IF(AND(M53>=$B$3,M53<=$C$3),1,"-") -> 1 | P53: =IF(M53="","0",(MONTH(M53))) -> 6
A54: 29 | B54: 50666380 | C54: Dos Bocas | D54: SCOC | E54: SCOC | F54: BÁSICO DE SEGURIDAD (BS) | G54: Presencial | H54: 384599 | I54: =IFERROR((VLOOKUP(H54,Padrón[[Ficha]:[Nombre]],2,FALSE)),"-") -> MARLON DANIEL MARTINEZ COBA | J54: 16 | K54: 23 | L54: 45096 | M54: 45097 | N54: =IF(AND(M54>=$B$3,M54<=$C$3),1,"-") -> 1 | P54: =IF(M54="","0",(MONTH(M54))) -> 6
A55: 30 | B55: 50656816 | C55: Reforma | D55: PLOG | E55: GOTLPM | F55: ANALISIS DE SEGURIDAD EN EL TRABAJO PRE(REFORMA) | G55: Presencial | H55: 395269 | I55: =IFERROR((VLOOKUP(H55,Padrón[[Ficha]:[Nombre]],2,FALSE)),"-") -> MAXIMILIANO JIMENEZ MARTINEZ | J55: 8 | K55: 9 | L55: 45075 | M55: 45075 | N55: =IF(AND(M55>=$B$3,M55<=$C$3),1,"-") -> 1 | P55: =IF(M55="","0",(MONTH(M55))) -> 5
A56: 31 | B56: 50656819 | C56: Cunduacán | D56: PLOG | E56: GOTLPM | F56: ANALISIS DE SEGURIDAD EN EL TRABAJO PRE (CUNDUACAN) | G56: Presencial | H56: 395269 | I56: =IFERROR((VLOOKUP(H56,Padrón[[Ficha]:[Nombre]],2,FALSE)),"-") -> MAXIMILIANO JIMENEZ MARTINEZ | J56: 8 | K56: 8 | L56: 45079 | M56: 45079 | N56: =IF(AND(M56>=$B$3,M56<=$C$3),1,"-") -> 1 | P56: =IF(M56="","0",(MONTH(M56))) -> 6
A57: 32 | B57: 50655848 | C57: Agua Dulce | D57: SPRS | E57: CMEDO | F57: NOM-017-STPS-2008 | G57: Presencial | H57: 495454 | I57: =IFERROR((VLOOKUP(H57,Padrón[[Ficha]:[Nombre]],2,FALSE)),"-") -> LUCY LENNY GARCIA RODRIGUEZ | J57: 24 | K57: 13 | L57: 45082 | M57: 45086 | N57: =IF(AND(M57>=$B$3,M57<=$C$3),1,"-") -> 1 | P57: =IF(M57="","0",(MONTH(M57))) -> 6
A58: 33 | B58: 50655853 | C58: Agua Dulce | D58: SPRS | E58: CMEDO | F58: NOM-017-STPS-2008 | G58: Presencial | H58: 583035 | I58: =IFERROR((VLOOKUP(H58,Padrón[[Ficha]:[Nombre]],2,FALSE)),"-") -> FERDY RAUL ARCIQUE DOMINGUEZ | J58: 24 | K58: 19 | L58: 45089 | M58: 45093 | N58: =IF(AND(M58>=$B$3,M58<=$C$3),1,"-") -> 1 | P58: =IF(M58="","0",(MONTH(M58))) -> 6
A59: 34 | B59: 50656821 | C59: Reforma | D59: PLOG | E59: SOGT | F59: AUDITORIAS EFECTIVAS (CUANDUACAN) | G59: Presencial | I59: =IFERROR((VLOOKUP(H59,Padrón[[Ficha]:[Nombre]],2,FALSE)),"-") -> - | J59: 8 | K59: 16 | L59: 45085 | M59: 45085 | N59: =IF(AND(M59>=$B$3,M59<=$C$3),1,"-") -> 1 | P59: =IF(M59="","0",(MONTH(M59))) -> 6
A60: 35 | B60: 50666381 | C60: Dos Bocas | D60: SCOC | E60: SCOC | F60: SISTEMA DE PERMISOS PARA TRABAJOS CON RIESGO (SPTR) | G60: Presencial | H60: 322115 | I60: =IFERROR((VLOOKUP(H60,Padrón[[Ficha]:[Nombre]],2,FALSE)),"-") -> EDUARDO MOHENO TORRES | J60: 24 | K60: 18 | L60: 45101 | M60: 45103 | N60: =IF(AND(M60>=$B$3,M60<=$C$3),1,"-") -> 1 | P60: =IF(M60="","0",(MONTH(M60))) -> 6
A61: 36 | B61: 50666382 | C61: Dos Bocas | D61: SCOC | E61: SCOC | F61: BÁSICO DE SEGURIDAD (BS) | G61: Presencial | H61: 384599 | I61: =IFERROR((VLOOKUP(H61,Padrón[[Ficha]:[Nombre]],2,FALSE)),"-") -> MARLON DANIEL MARTINEZ COBA | J61: 16 | K61: 17 | L61: 45103 | M61: 45104 | N61: =IF(AND(M61>=$B$3,M61<=$C$3),1,"-") -> 1 | P61: =IF(M61="","0",(MONTH(M61))) -> 6
A62: 37 | B62: 50655858 | C62: Villahermosa | D62: SPRS | E62: CMEDO | F62: NOM-017-STPS-2008 | G62: Presencial | H62: 598694 | I62: =IFERROR((VLOOKUP(H62,Padrón[[Ficha]:[Nombre]],2,FALSE)),"-") -> GUADALUPE SANCHEZ QUINTANA | J62: 24 | K62: 19 | L62: 45096 | M62: 45100 | N62: =IF(AND(M62>=$B$3,M62<=$C$3),1,"-") -> 1 | P62: =IF(M62="","0",(MONTH(M62))) -> 6
A63: 38 | B63: 50656811 | C63: Ciudad del Carmen | D63: PLOG | E63: GOTLPM | F63: BRIGADA DE BUSQUEDA Y RESCATE (CC) | G63: Presencial | H63: 600496 | I63: =IFERROR((VLOOKUP(H63,Padrón[[Ficha]:[Nombre]],2,FALSE)),"-") -> LUIS ALEXANDRO ORTEGA MORENO | J63: 24 | K63: 8 | L63: 45096 | M63: 45098 | N63: =IF(AND(M63>=$B$3,M63<=$C$3),1,"-") -> 1 | P63: =IF(M63="","0",(MONTH(M63))) -> 6
A64: 39 | B64: 50655865 | C64: Villahermosa | D64: SPRS | E64: CMEDO | F64: NOM-017-STPS-2008 | G64: Presencial | H64: 598694 | I64: =IFERROR((VLOOKUP(H64,Padrón[[Ficha]:[Nombre]],2,FALSE)),"-") -> GUADALUPE SANCHEZ QUINTANA | J64: 24 | K64: 18 | L64: 45103 | M64: 45107 | N64: =IF(AND(M64>=$B$3,M64<=$C$3),1,"-") -> 1 | P64: =IF(M64="","0",(MONTH(M64))) -> 6
A65: 40 | B65: 50656824 | C65: Villahermosa | D65: PLOG | E65: GOTLPM | F65: ANALISIS DE SEGURIDAD EN EL TRABAJO PRE (vhsa) | G65: Presencial | H65: 395269 | I65: =IFERROR((VLOOKUP(H65,Padrón[[Ficha]:[Nombre]],2,FALSE)),"-") -> MAXIMILIANO JIMENEZ MARTINEZ | J65: 8 | K65: 18 | L65: 45103 | M65: 45103 | N65: =IF(AND(M65>=$B$3,M65<=$C$3),1,"-") -> 1 | P65: =IF(M65="","0",(MONTH(M65))) -> 6
A66: 41 | B66: 50656812 | C66: Ciudad del Carmen | D66: PLOG | E66: GOTLPM | F66: BÁSICO DE SEGURIDAD (BS) | G66: Presencial | H66: 600496 | I66: =IFERROR((VLOOKUP(H66,Padrón[[Ficha]:[Nombre]],2,FALSE)),"-") -> LUIS ALEXANDRO ORTEGA MORENO | J66: 16 | K66: 9 | L66: 45119 | M66: 45120 | N66: =IF(AND(M66>=$B$3,M66<=$C$3),1,"-") -> 1 | P66: =IF(M66="","0",(MONTH(M66))) -> 7
A67: 42 | B67: 50656813 | C67: Ciudad del Carmen | D67: PLOG | E67: GOTLPM | F67: ENTRENAMIENTO BÁSICO EN SISTEMA PEMEX SSPA (EB SSPA) | G67: Presencial | H67: 206830 | I67: =IFERROR((VLOOKUP(H67,Padrón[[Ficha]:[Nombre]],2,FALSE)),"-") -> JOSE TRINIDAD OSORNO REQUENA | J67: 16 | K67: 5 | L67: 45145 | M67: 45146 | N67: =IF(AND(M67>=$B$3,M67<=$C$3),1,"-") -> 1 | P67: =IF(M67="","0",(MONTH(M67))) -> 8
A68: 43 | B68: 50656021 | C68: Villahermosa | D68: SSSTPA | E68: GSPSSPAIP | F68: Métodos Cuantitativos para la identificación de peligros, evaluación y jerarquización de riesgos | G68: Presencial | H68: Externo | I68: =IFERROR((VLOOKUP(H68,Padrón[[Ficha]:[Nombre]],2,FALSE)),"-") -> - | J68: 40 | K68: 22 | L68: 45145 | M68: 45149 | N68: =IF(AND(M68>=$B$3,M68<=$C$3),1,"-") -> 1 | P68: =IF(M68="","0",(MONTH(M68))) -> 8
A69: 44 | B69: 50656022 | C69: Poza Rica | D69: SSSTPA | E69: GSPSSPAIP | F69: Métodos Cuantitativos para la identificación de peligros, evaluación y jerarquización de riesgos | G69: Presencial | H69: Externo | I69: =IFERROR((VLOOKUP(H69,Padrón[[Ficha]:[Nombre]],2,FALSE)),"-") -> - | J69: 40 | K69: 10 | L69: 45152 | M69: 45156 | N69: =IF(AND(M69>=$B$3,M69<=$C$3),1,"-") -> 1 | P69: =IF(M69="","0",(MONTH(M69))) -> 8
A70: 45 | B70: 50656061 | C70: El Castaño | D70: SSSTPA | E70: GSSTPARS | F70: SISTEMAS CONTRAINCENDIO: FUNCIONAMIENTO Y PRÁCTICAS | G70: Presencial | H70: 395269 | I70: =IFERROR((VLOOKUP(H70,Padrón[[Ficha]:[Nombre]],2,FALSE)),"-") -> MAXIMILIANO JIMENEZ MARTINEZ | J70: 24 | K70: 4 | L70: 45138 | M70: 45140 | N70: =IF(AND(M70>=$B$3,M70<=$C$3),1,"-") -> 1 | P70: =IF(M70="","0",(MONTH(M70))) -> 8
A71: 46 | B71: 50656062 | C71: Comalcalco | D71: SSSTPA | E71: GSSTPARS | F71: EQUIPOS CONTRAINCENDIO | G71: Presencial | H71: 395269 | I71: =IFERROR((VLOOKUP(H71,Padrón[[Ficha]:[Nombre]],2,FALSE)),"-") -> MAXIMILIANO JIMENEZ MARTINEZ | J71: 16 | K71: 4 | L71: 45141 | M71: 45142 | N71: =IF(AND(M71>=$B$3,M71<=$C$3),1,"-") -> 1 | P71: =IF(M71="","0",(MONTH(M71))) -> 8
A72: 47 | B72: 50655818 | C72: Agua Dulce | D72: SPRS | E72: CMEDO | F72: NOM-026-STPS-2008 Colores y Señales de Seguridad e Higiene, e Identificación de Riesgos por Fluidos conducidos en Tuberías | G72: Presencial | H72: 598694 | I72: =IFERROR((VLOOKUP(H72,Padrón[[Ficha]:[Nombre]],2,FALSE)),"-") -> GUADALUPE SANCHEZ QUINTANA | J72: 24 | K72: 11 | L72: 45138 | M72: 45140 | N72: =IF(AND(M72>=$B$3,M72<=$C$3),1,"-") -> 1 | P72: =IF(M72="","0",(MONTH(M72))) -> 8
A73: 48 | B73: 50656062 | C73: Comalcalco | D73: SSSTPA | E73: GSSTPARS | F73: EQUIPOS CONTRAINCENDIO | G73: Presencial | H73: 395269 | I73: =IFERROR((VLOOKUP(H73,Padrón[[Ficha]:[Nombre]],2,FALSE)),"-") -> MAXIMILIANO JIMENEZ MARTINEZ | J73: 24 | K73: 3 | L73: 45148 | M73: 45149 | N73: =IF(AND(M73>=$B$3,M73<=$C$3),1,"-") -> 1 | P73: =IF(M73="","0",(MONTH(M73))) -> 8
A74: 49 | B74: 50656063 | C74: Comalcalco | D74: SSSTPA | E74: GSSTPARS | F74: SISTEMAS CONTRAINCENDIO: FUNCIONAMIENTO Y PRÁCTICAS | G74: Presencial | H74: 395269 | I74: =IFERROR((VLOOKUP(H74,Padrón[[Ficha]:[Nombre]],2,FALSE)),"-") -> MAXIMILIANO JIMENEZ MARTINEZ | J74: 24 | K74: 5 | L74: 45145 | M74: 45147 | N74: =IF(AND(M74>=$B$3,M74<=$C$3),1,"-") -> 1 | P74: =IF(M74="","0",(MONTH(M74))) -> 8
A75: 50 | B75: 50655820 | C75: Agua Dulce | D75: SSSTPA | E75: GSSTPARS | F75: NOM-026-STPS-2008 Colores y Señales de Seguridad e Higiene, e Identificación de Riesgos por Fluidos conducidos en Tuberías | G75: Presencial | H75: 395269 | I75: =IFERROR((VLOOKUP(H75,Padrón[[Ficha]:[Nombre]],2,FALSE)),"-") -> MAXIMILIANO JIMENEZ MARTINEZ | J75: 24 | K75: 14 | L75: 45145 | M75: 45149 | N75: =IF(AND(M75>=$B$3,M75<=$C$3),1,"-") -> 1 | P75: =IF(M75="","0",(MONTH(M75))) -> 8
A76: 51 | B76: 50656003 | C76: Comalcalco | D76: SSSTPA | E76: GSSTPARS | F76: SISTEMAS CONTRAINCENDIO: FUNCIONAMIENTO Y PRÁCTICAS | G76: Presencial | H76: 395269 | I76: =IFERROR((VLOOKUP(H76,Padrón[[Ficha]:[Nombre]],2,FALSE)),"-") -> MAXIMILIANO JIMENEZ MARTINEZ | J76: 24 | K76: 4 | L76: 45152 | M76: 45154 | N76: =IF(AND(M76>=$B$3,M76<=$C$3),1,"-") -> 1 | P76: =IF(M76="","0",(MONTH(M76))) -> 8
A77: 52 | B77: 50656004 | C77: Comalcalco | D77: SSSTPA | E77: GSSTPARS | F77: EQUIPOS CONTRAINCENDIO | G77: Presencial | H77: 395269 | I77: =IFERROR((VLOOKUP(H77,Padrón[[Ficha]:[Nombre]],2,FALSE)),"-") -> MAXIMILIANO JIMENEZ MARTINEZ | J77: 24 | K77: 5 | L77: 45155 | M77: 45156 | N77: =IF(AND(M77>=$B$3,M77<=$C$3),1,"-") -> 1 | P77: =IF(M77="","0",(MONTH(M77))) -> 8
A78: 53 | B78: 50656005 | C78: Comalcalco | D78: SSSTPA | E78: GSSTPARS | F78: SISTEMAS CONTRAINCENDIO: FUNCIONAMIENTO Y PRÁCTICAS | G78: Presencial | H78: 395269 | I78: =IFERROR((VLOOKUP(H78,Padrón[[Ficha]:[Nombre]],2,FALSE)),"-") -> MAXIMILIANO JIMENEZ MARTINEZ | J78: 24 | K78: 4 | L78: 45159 | M78: 45161 | N78: =IF(AND(M78>=$B$3,M78<=$C$3),1,"-") -> 1 | P78: =IF(M78="","0",(MONTH(M78))) -> 8
A79: 54 | B79: 50656006 | C79: El Castaño | D79: SSSTPA | E79: GSSTPARS | F79: EQUIPOS CONTRAINCENDIO | G79: Presencial | H79: 395269 | I79: =IFERROR((VLOOKUP(H79,Padrón[[Ficha]:[Nombre]],2,FALSE)),"-") -> MAXIMILIANO JIMENEZ MARTINEZ | J79: 24 | K79: 3 | L79: 45162 | M79: 45163 | N79: =IF(AND(M79>=$B$3,M79<=$C$3),1,"-") -> 1 | P79: =IF(M79="","0",(MONTH(M79))) -> 8
A80: 55 | C80: Agua Dulce | D80: SPRS | E80: CMEDO | F80: NOM-026-STPS-2008 Colores y Señales de Seguridad e Higiene, e Identificación de Riesgos por Fluidos conducidos en Tuberías | G80: Presencial | H80: 598694 | I80: =IFERROR((VLOOKUP(H80,Padrón[[Ficha]:[Nombre]],2,FALSE)),"-") -> GUADALUPE SANCHEZ QUINTANA | J80: 24 | K80: 10 | L80: 45159 | M80: 45161 | N80: =IF(AND(M80>=$B$3,M80<=$C$3),1,"-") -> 1 | P80: =IF(M80="","0",(MONTH(M80))) -> 8
A81: 56 | C81: Agua Dulce | D81: SPRS | E81: CMEDO | F81: NOM-026-STPS-2008 Colores y Señales de Seguridad e Higiene, e Identificación de Riesgos por Fluidos conducidos en Tuberías | G81: Presencial | H81: 395269 | I81: =IFERROR((VLOOKUP(H81,Padrón[[Ficha]:[Nombre]],2,FALSE)),"-") -> MAXIMILIANO JIMENEZ MARTINEZ | J81: 24 | K81: 19 | L81: 45159 | M81: 45161 | N81: =IF(AND(M81>=$B$3,M81<=$C$3),1,"-") -> 1 | P81: =IF(M81="","0",(MONTH(M81))) -> 8
A82: 57 | C82: Agua Dulce | D82: SPRS | E82: CMEDO | F82: NOM-026-STPS-2008 Colores y Señales de Seguridad e Higiene, e Identificación de Riesgos por Fluidos conducidos en Tuberías | G82: Presencial | H82: 395269 | I82: =IFERROR((VLOOKUP(H82,Padrón[[Ficha]:[Nombre]],2,FALSE)),"-") -> MAXIMILIANO JIMENEZ MARTINEZ | J82: 24 | K82: 21 | L82: 45166 | M82: 45168 | N82: =IF(AND(M82>=$B$3,M82<=$C$3),1,"-") -> 1 | P82: =IF(M82="","0",(MONTH(M82))) -> 8
A83: 58 | B83: 50656007 | C83: Comalcalco | D83: SSSTPA | E83: GSSTPARS | F83: Sistema Contraincendio- Funcioanmiento y Prácticas | G83: Presencial | H83: 332755 | I83: =IFERROR((VLOOKUP(H83,Padrón[[Ficha]:[Nombre]],2,FALSE)),"-") -> RUFINO GARCIA AQUINO | J83: 24 | K83: 5 | L83: 45166 | M83: 45168 | N83: =IF(AND(M83>=$B$3,M83<=$C$3),1,"-") -> 1 | P83: =IF(M83="","0",(MONTH(M83))) -> 8
A84: 59 | B84: 50656009 | C84: Cunduacán | D84: SSSTPA | E84: GSSTPARS | F84: OPERACIÓN Y MANEJO DE MOTOBOMBAS | G84: Presencial | H84: 332755 | I84: =IFERROR((VLOOKUP(H84,Padrón[[Ficha]:[Nombre]],2,FALSE)),"-") -> RUFINO GARCIA AQUINO | J84: 8 | K84: 10 | L84: 45170 | M84: 45170 | N84: =IF(AND(M84>=$B$3,M84<=$C$3),1,"-") -> 1 | P84: =IF(M84="","0",(MONTH(M84))) -> 9
A85: 60 | C85: Agua Dulce | D85: SPRS | E85: CMEDO | F85: NOM-026-STPS-2008 Colores y Señales de Seguridad e Higiene, e Identificación de Riesgos por Fluidos conducidos en Tuberías | G85: Presencial | H85: 395269 | I85: =IFERROR((VLOOKUP(H85,Padrón[[Ficha]:[Nombre]],2,FALSE)),"-") -> MAXIMILIANO JIMENEZ MARTINEZ | J85: 24 | K85: 20 | L85: 45173 | M85: 45175 | N85: =IF(AND(M85>=$B$3,M85<=$C$3),1,"-") -> 1 | P85: =IF(M85="","0",(MONTH(M85))) -> 9
A86: 61 | B86: 50656009 | C86: Cunduacán | D86: SSSTPA | E86: GSSTPARS | F86: MANEJO Y OPERACIÓN DE EQUIPOS CONTRAINCENDIO | G86: Presencial | H86: 201275 | I86: =IFERROR((VLOOKUP(H86,Padrón[[Ficha]:[Nombre]],2,FALSE)),"-") -> RONNIE MUÑOZ POTENCIANO | J86: 24 | K86: 12 | L86: 45173 | M86: 45175 | N86: =IF(AND(M86>=$B$3,M86<=$C$3),1,"-") -> 1 | P86: =IF(M86="","0",(MONTH(M86))) -> 9
A87: 62 | B87: 50656010 | C87: Comalcalco | D87: SSSTPA | E87: GSSTPARS | F87: Sistema Contraincendio- Funcioanmiento y Prácticas | G87: Presencial | H87: 395269 | I87: =IFERROR((VLOOKUP(H87,Padrón[[Ficha]:[Nombre]],2,FALSE)),"-") -> MAXIMILIANO JIMENEZ MARTINEZ | J87: 24 | K87: 3 | L87: 45173 | M87: 45175 | N87: =IF(AND(M87>=$B$3,M87<=$C$3),1,"-") -> 1 | P87: =IF(M87="","0",(MONTH(M87))) -> 9
A88: 63 | B88: 50656024 | C88: Villahermosa | D88: SSSTPA | E88: GSPSSPAIP | F88: Capacitacion para la Certificación en Seguridad Funcional | G88: Presencial | H88: Externo | I88: =IFERROR((VLOOKUP(H88,Padrón[[Ficha]:[Nombre]],2,FALSE)),"-") -> - | J88: 40 | K88: 15 | L88: 45173 | M88: 45191 | N88: =IF(AND(M88>=$B$3,M88<=$C$3),1,"-") -> 1 | O88: UNA SEMANA DE CURSO Y UNA DE SEPARACION | P88: =IF(M88="","0",(MONTH(M88))) -> 9
A89: 64 | C89: Agua Dulce | D89: SPRS | E89: CMEDO | F89: NOM-018 STPS-2015 Sistema Armonizado para la identififcación y comunicación de pligros y riesgos por sustancias quimímas peligrosas en los centros de trabajo | G89: Presencial | H89: 598694 | I89: =IFERROR((VLOOKUP(H89,Padrón[[Ficha]:[Nombre]],2,FALSE)),"-") -> GUADALUPE SANCHEZ QUINTANA | J89: 24 | K89: 20 | L89: 45180 | M89: 45182 | N89: =IF(AND(M89>=$B$3,M89<=$C$3),1,"-") -> 1 | P89: =IF(M89="","0",(MONTH(M89))) -> 9
A90: 65 | C90: Agua Dulce | D90: SPRS | E90: CMEDO | F90: NOM-018 STPS-2015 Sistema Armonizado para la identififcación y comunicación de pligros y riesgos por sustancias quimímas peligrosas en los centros de trabajo | G90: Presencial | H90: 598694 | I90: =IFERROR((VLOOKUP(H90,Padrón[[Ficha]:[Nombre]],2,FALSE)),"-") -> GUADALUPE SANCHEZ QUINTANA | J90: 24 | K90: 13 | L90: 45187 | M90: 45189 | N90: =IF(AND(M90>=$B$3,M90<=$C$3),1,"-") -> 1 | P90: =IF(M90="","0",(MONTH(M90))) -> 9
A91: 66 | B91: 50656753 | C91: Ciudad del Carmen | D91: PLOG | E91: GOTLPM | F91: BÁSICO DE SEGURIDAD (BS) (CC) | G91: Presencial | H91: 496969 | I91: =IFERROR((VLOOKUP(H91,Padrón[[Ficha]:[Nombre]],2,FALSE)),"-") -> EMMANUEL ALONSO SANCHEZ DOMINGUEZ | J91: 16 | K91: 17 | L91: 45180 | M91: 45181 | N91: =IF(AND(M91>=$B$3,M91<=$C$3),1,"-") -> 1 | P91: =IF(M91="","0",(MONTH(M91))) -> 9
A92: 67 | C92: Agua Dulce | D92: SPRS | E92: CMEDO | F92: NOM-018-STPS-2015 Sistema Armonizado para la Identificación y Comunicación de Peligros y Riesgos por Sustancias Químicas Peligrosas en los Centros de Trabajo | G92: Presencial | H92: 598694 | I92: =IFERROR((VLOOKUP(H92,Padrón[[Ficha]:[Nombre]],2,FALSE)),"-") -> GUADALUPE SANCHEZ QUINTANA | J92: 24 | K92: 22 | L92: 45201 | M92: 45203 | N92: =IF(AND(M92>=$B$3,M92<=$C$3),1,"-") -> 1 | P92: =IF(M92="","0",(MONTH(M92))) -> 10
A93: 68 | C93: Villahermosa | D93: SSSTPA | E93: GSPSSPAIP | F93: Adiestramiento en el uso de tecnología del software para realizar ARP aplicando la metodología Bow Tie | G93: Presencial | H93: EXTERNO | I93: =IFERROR((VLOOKUP(H93,Padrón[[Ficha]:[Nombre]],2,FALSE)),"-") -> - | J93: 40 | K93: 20 | L93: 45222 | M93: 45226 | N93: =IF(AND(M93>=$B$3,M93<=$C$3),1,"-") -> 1 | P93: =IF(M93="","0",(MONTH(M93))) -> 10
A94: 69 | B94: 50656756 | C94: Ciudad del Carmen | D94: PLOG | E94: GOTLPM | F94: BÁSICO DE SEGURIDAD (BS) | G94: Presencial | H94: 496969 | I94: =IFERROR((VLOOKUP(H94,Padrón[[Ficha]:[Nombre]],2,FALSE)),"-") -> EMMANUEL ALONSO SANCHEZ DOMINGUEZ | J94: 16 | K94: 12 | L94: 45222 | M94: 45223 | N94: =IF(AND(M94>=$B$3,M94<=$C$3),1,"-") -> 1 | P94: =IF(M94="","0",(MONTH(M94))) -> 10
A95: 70 | C95: Agua Dulce | D95: SPRS | E95: CMEDO | F95: NOM-018-STPS-2015 Sistema Armonizado para la Identificación y Comunicación de Peligros y Riesgos por Sustancias Químicas Peligrosas en los Centros de Trabajo | G95: Presencial | H95: 496969 | I95: =IFERROR((VLOOKUP(H95,Padrón[[Ficha]:[Nombre]],2,FALSE)),"-") -> EMMANUEL ALONSO SANCHEZ DOMINGUEZ | J95: 24 | K95: 19 | L95: 45215 | M95: 45217 | N95: =IF(AND(M95>=$B$3,M95<=$C$3),1,"-") -> 1 | P95: =IF(M95="","0",(MONTH(M95))) -> 10
A96: 71 | C96: Ciudad del Carmen | D96: SSSTPA | E96: GSPSSPAIP | F96: Adiestramiento en el uso de tecnología del software para realizar ARP aplicando la metodología Bow Tie | G96: Presencial | H96: EXTERNO | I96: =IFERROR((VLOOKUP(H96,Padrón[[Ficha]:[Nombre]],2,FALSE)),"-") -> - | J96: 40 | K96: 10 | L96: 45257 | M96: 45261 | N96: =IF(AND(M96>=$B$3,M96<=$C$3),1,"-") -> 1 | P96: =IF(M96="","0",(MONTH(M96))) -> 12
A97: 72 | B97: 50669075 | C97: Dos Bocas | D97: SSSTPA | E97: GSSTPA RM | F97: TÁCTICAS DE ATAQUE DE INCENDIO | G97: Presencial | H97: 225108 | I97: =IFERROR((VLOOKUP(H97,Padrón[[Ficha]:[Nombre]],2,FALSE)),"-") -> OSCAR ARTURO CARREON NOGUERA | J97: 24 | K97: 14 | L97: 45258 | M97: 45260 | N97: =IF(AND(M97>=$B$3,M97<=$C$3),1,"-") -> 1 | P97: =IF(M97="","0",(MONTH(M97))) -> 11
A98: 73 | B98: 50669003 | C98: Ciudad del Carmen | D98: SPRMNE | E98: CANTARELL | F98: SEGURIDAD SOBREVIVENCIA COSTA AFUERA | G98: Presencial | H98: 481436 | I98: =IFERROR((VLOOKUP(H98,Padrón[[Ficha]:[Nombre]],2,FALSE)),"-") -> JESUS XAVIER MADRIGAL PAEZ | J98: 24 | K98: 8 | L98: 45273 | M98: 45275 | N98: =IF(AND(M98>=$B$3,M98<=$C$3),1,"-") -> 1 | P98: =IF(M98="","0",(MONTH(M98))) -> 12
A99: 74 | I99: =IFERROR((VLOOKUP(H99,Padrón[[Ficha]:[Nombre]],2,FALSE)),"-") -> - | N99: =IF(AND(M99>=$B$3,M99<=$C$3),1,"-") -> - | P99: =IF(M99="","0",(MONTH(M99))) -> 0
A100: 75 | I100: =IFERROR((VLOOKUP(H100,Padrón[[Ficha]:[Nombre]],2,FALSE)),"-") -> - | N100: =IF(AND(M100>=$B$3,M100<=$C$3),1,"-") -> - | P100: =IF(M100="","0",(MONTH(M100))) -> 0
A101: 76 | I101: =IFERROR((VLOOKUP(H101,Padrón[[Ficha]:[Nombre]],2,FALSE)),"-") -> - | N101: =IF(AND(M101>=$B$3,M101<=$C$3),1,"-") -> - | P101: =IF(M101="","0",(MONTH(M101))) -> 0
A102: 77 | I102: =IFERROR((VLOOKUP(H102,Padrón[[Ficha]:[Nombre]],2,FALSE)),"-") -> - | N102: =IF(AND(M102>=$B$3,M102<=$C$3),1,"-") -> - | P102: =IF(M102="","0",(MONTH(M102))) -> 0
...

Sheet Hoja20
C6: Realizado | F6: Reynosa | H6: SCOC
C7: Diferido | F7: Altamira | H7: SE
C8: Cancelado | F8: Naranjos | H8: SEPCA
F9: Cerro Azul | H9: SMLIC
F10: Poza Rica | H10: SPEE
F11: Veracruz | H11: SPMP
F12: Cd. Madero | H12: SPRMNE
F13: Agua Dulce | H13: SPRMSO
F14: Comalcalco | H14: PLOG
F15: El Castaño | H15: SPRN
F16: Reforma | H16: SPRS
F17: Cunduacán | H17: SSSTPA
F18: Villahermosa
F19: SPMP_Mar Carmen
F20: SPMP_Mar DB
F21: SPMP Tierra
F22: Dos Bocas
F23: Ciudad del Carmen

Sheet Reynosa
B1: Fecha inicial | C1: Fecha final | U1: Programa | V1: 1 | W1: 2 | X1: 3 | Y1: 4 | Z1: 5 | AA1: 6 | AB1: 7 | AC1: 8 | AD1: 9 | AE1: 10 | AF1: 11 | AG1: 12 | AH1: Total
B2: =Seguimiento!$E$6 -> 44927 | C2: =Seguimiento!$J$6 -> 45291 | U2: SCOC | V2: =COUNTIFS($L$14:$L$300,V$1,$C$14:$C$300,$U2) -> 0 | W2: =COUNTIFS($L$14:$L$300,W$1,$C$14:$C$300,$U2) -> 0 | X2: =COUNTIFS($L$14:$L$300,X$1,$C$14:$C$300,$U2) -> 0 | Y2: =COUNTIFS($L$14:$L$300,Y$1,$C$14:$C$300,$U2) -> 0 | Z2: =COUNTIFS($L$14:$L$300,Z$1,$C$14:$C$300,$U2) -> 0 | AA2: =COUNTIFS($L$14:$L$300,AA$1,$C$14:$C$300,$U2) -> 0 | AB2: =COUNTIFS($L$14:$L$300,AB$1,$C$14:$C$300,$U2) -> 0 | AC2: =COUNTIFS($L$14:$L$300,AC$1,$C$14:$C$300,$U2) -> 0 | ... AG2: =COUNTIFS($L$14:$L$300,AG$1,$C$14:$C$300,$U2) -> 0 | AH2: =SUM(V2:AG2) -> 0
H3: PICADE | U3: SE | V3: =COUNTIFS($L$14:$L$300,V$1,$C$14:$C$300,$U3) -> 0 | W3: =COUNTIFS($L$14:$L$300,W$1,$C$14:$C$300,$U3) -> 0 | X3: =COUNTIFS($L$14:$L$300,X$1,$C$14:$C$300,$U3) -> 0 | Y3: =COUNTIFS($L$14:$L$300,Y$1,$C$14:$C$300,$U3) -> 0 | Z3: =COUNTIFS($L$14:$L$300,Z$1,$C$14:$C$300,$U3) -> 0 | AA3: =COUNTIFS($L$14:$L$300,AA$1,$C$14:$C$300,$U3) -> 0 | AB3: =COUNTIFS($L$14:$L$300,AB$1,$C$14:$C$300,$U3) -> 0 | AC3: =COUNTIFS($L$14:$L$300,AC$1,$C$14:$C$300,$U3) -> 0 | ... AG3: =COUNTIFS($L$14:$L$300,AG$1,$C$14:$C$300,$U3) -> 0 | AH3: =SUM(V3:AG3) -> 0
H4: Cursos | I4: Capacitandos | J4: Cursos Programados | K4: Realizados en prog. | L4: Cancelados | N4: Capacitandos programados | O4: Capacitandos | U4: SEPCA | V4: =COUNTIFS($L$14:$L$300,V$1,$C$14:$C$300,$U4) -> 0 | W4: =COUNTIFS($L$14:$L$300,W$1,$C$14:$C$300,$U4) -> 0 | X4: =COUNTIFS($L$14:$L$300,X$1,$C$14:$C$300,$U4) -> 0 | Y4: =COUNTIFS($L$14:$L$300,Y$1,$C$14:$C$300,$U4) -> 0 | Z4: =COUNTIFS($L$14:$L$300,Z$1,$C$14:$C$300,$U4) -> 0 | AA4: =COUNTIFS($L$14:$L$300,AA$1,$C$14:$C$300,$U4) -> 0 | AB4: =COUNTIFS($L$14:$L$300,AB$1,$C$14:$C$300,$U4) -> 0 | AC4: =COUNTIFS($L$14:$L$300,AC$1,$C$14:$C$300,$U4) -> 0 | ... AG4: =COUNTIFS($L$14:$L$300,AG$1,$C$14:$C$300,$U4) -> 0 | AH4: =SUM(V4:AG4) -> 0
H5: =COUNT(A14:A300) -> 66 | I5: =SUM(H14:H300) -> 869 | J5: =COUNTIF($M$14:$M$300,1) -> 66 | K5: =COUNTIFS($M$14:$M$300,1,$N$14:$N$300,"Realizado") -> 66 | L5: =COUNTIFS($M$14:$M$300,1,$N$14:$N$300,"Cancelado") -> 0 | N5: =+SUMIF($M$14:$M$300,1,$H$14:$H$300) -> 869 | O5: =+SUMIF($M$14:$M$300,1,$O$14:$O$300) -> 825 | U5: SMLIC | V5: =COUNTIFS($L$14:$L$300,V$1,$C$14:$C$300,$U5) -> 0 | W5: =COUNTIFS($L$14:$L$300,W$1,$C$14:$C$300,$U5) -> 0 | X5: =COUNTIFS($L$14:$L$300,X$1,$C$14:$C$300,$U5) -> 0 | Y5: =COUNTIFS($L$14:$L$300,Y$1,$C$14:$C$300,$U5) -> 0 | Z5: =COUNTIFS($L$14:$L$300,Z$1,$C$14:$C$300,$U5) -> 0 | AA5: =COUNTIFS($L$14:$L$300,AA$1,$C$14:$C$300,$U5) -> 5 | AB5: =COUNTIFS($L$14:$L$300,AB$1,$C$14:$C$300,$U5) -> 0 | AC5: =COUNTIFS($L$14:$L$300,AC$1,$C$14:$C$300,$U5) -> 0 | ... AG5: =COUNTIFS($L$14:$L$300,AG$1,$C$14:$C$300,$U5) -> 0 | AH5: =SUM(V5:AG5) -> 7
U6: SPEE | V6: =COUNTIFS($L$14:$L$300,V$1,$C$14:$C$300,$U6) -> 0 | W6: =COUNTIFS($L$14:$L$300,W$1,$C$14:$C$300,$U6) -> 0 | X6: =COUNTIFS($L$14:$L$300,X$1,$C$14:$C$300,$U6) -> 0 | Y6: =COUNTIFS($L$14:$L$300,Y$1,$C$14:$C$300,$U6) -> 0 | Z6: =COUNTIFS($L$14:$L$300,Z$1,$C$14:$C$300,$U6) -> 0 | AA6: =COUNTIFS($L$14:$L$300,AA$1,$C$14:$C$300,$U6) -> 0 | AB6: =COUNTIFS($L$14:$L$300,AB$1,$C$14:$C$300,$U6) -> 0 | AC6: =COUNTIFS($L$14:$L$300,AC$1,$C$14:$C$300,$U6) -> 0 | ... AG6: =COUNTIFS($L$14:$L$300,AG$1,$C$14:$C$300,$U6) -> 0 | AH6: =SUM(V6:AG6) -> 0
U7: SPMP | V7: =COUNTIFS($L$14:$L$300,V$1,$C$14:$C$300,$U7) -> 0 | W7: =COUNTIFS($L$14:$L$300,W$1,$C$14:$C$300,$U7) -> 0 | X7: =COUNTIFS($L$14:$L$300,X$1,$C$14:$C$300,$U7) -> 0 | Y7: =COUNTIFS($L$14:$L$300,Y$1,$C$14:$C$300,$U7) -> 0 | Z7: =COUNTIFS($L$14:$L$300,Z$1,$C$14:$C$300,$U7) -> 0 | AA7: =COUNTIFS($L$14:$L$300,AA$1,$C$14:$C$300,$U7) -> 0 | AB7: =COUNTIFS($L$14:$L$300,AB$1,$C$14:$C$300,$U7) -> 0 | AC7: =COUNTIFS($L$14:$L$300,AC$1,$C$14:$C$300,$U7) -> 0 | ... AG7: =COUNTIFS($L$14:$L$300,AG$1,$C$14:$C$300,$U7) -> 0 | AH7: =SUM(V7:AG7) -> 0
U8: SPRMNE | V8: =COUNTIFS($L$14:$L$300,V$1,$C$14:$C$300,$U8) -> 0 | W8: =COUNTIFS($L$14:$L$300,W$1,$C$14:$C$300,$U8) -> 0 | X8: =COUNTIFS($L$14:$L$300,X$1,$C$14:$C$300,$U8) -> 0 | Y8: =COUNTIFS($L$14:$L$300,Y$1,$C$14:$C$300,$U8) -> 0 | Z8: =COUNTIFS($L$14:$L$300,Z$1,$C$14:$C$300,$U8) -> 0 | AA8: =COUNTIFS($L$14:$L$300,AA$1,$C$14:$C$300,$U8) -> 0 | AB8: =COUNTIFS($L$14:$L$300,AB$1,$C$14:$C$300,$U8) -> 0 | AC8: =COUNTIFS($L$14:$L$300,AC$1,$C$14:$C$300,$U8) -> 0 | ... AG8: =COUNTIFS($L$14:$L$300,AG$1,$C$14:$C$300,$U8) -> 0 | AH8: =SUM(V8:AG8) -> 0
U9: SPRMSO | V9: =COUNTIFS($L$14:$L$300,V$1,$C$14:$C$300,$U9) -> 0 | W9: =COUNTIFS($L$14:$L$300,W$1,$C$14:$C$300,$U9) -> 0 | X9: =COUNTIFS($L$14:$L$300,X$1,$C$14:$C$300,$U9) -> 0 | Y9: =COUNTIFS($L$14:$L$300,Y$1,$C$14:$C$300,$U9) -> 0 | Z9: =COUNTIFS($L$14:$L$300,Z$1,$C$14:$C$300,$U9) -> 0 | AA9: =COUNTIFS($L$14:$L$300,AA$1,$C$14:$C$300,$U9) -> 0 | AB9: =COUNTIFS($L$14:$L$300,AB$1,$C$14:$C$300,$U9) -> 0 | AC9: =COUNTIFS($L$14:$L$300,AC$1,$C$14:$C$300,$U9) -> 0 | ... AG9: =COUNTIFS($L$14:$L$300,AG$1,$C$14:$C$300,$U9) -> 0 | AH9: =SUM(V9:AG9) -> 0
U10: SPRN | V10: =COUNTIFS($L$14:$L$300,V$1,$C$14:$C$300,$U10) -> 0 | W10: =COUNTIFS($L$14:$L$300,W$1,$C$14:$C$300,$U10) -> 1 | X10: =COUNTIFS($L$14:$L$300,X$1,$C$14:$C$300,$U10) -> 4 | Y10: =COUNTIFS($L$14:$L$300,Y$1,$C$14:$C$300,$U10) -> 8 | Z10: =COUNTIFS($L$14:$L$300,Z$1,$C$14:$C$300,$U10) -> 13 | AA10: =COUNTIFS($L$14:$L$300,AA$1,$C$14:$C$300,$U10) -> 9 | AB10: =COUNTIFS($L$14:$L$300,AB$1,$C$14:$C$300,$U10) -> 0 | AC10: =COUNTIFS($L$14:$L$300,AC$1,$C$14:$C$300,$U10) -> 1 | ... AG10: =COUNTIFS($L$14:$L$300,AG$1,$C$14:$C$300,$U10) -> 0 | AH10: =SUM(V10:AG10) -> 50
U11: SPRS | V11: =COUNTIFS($L$14:$L$300,V$1,$C$14:$C$300,$U11) -> 0 | W11: =COUNTIFS($L$14:$L$300,W$1,$C$14:$C$300,$U11) -> 0 | X11: =COUNTIFS($L$14:$L$300,X$1,$C$14:$C$300,$U11) -> 0 | Y11: =COUNTIFS($L$14:$L$300,Y$1,$C$14:$C$300,$U11) -> 0 | Z11: =COUNTIFS($L$14:$L$300,Z$1,$C$14:$C$300,$U11) -> 0 | AA11: =COUNTIFS($L$14:$L$300,AA$1,$C$14:$C$300,$U11) -> 0 | AB11: =COUNTIFS($L$14:$L$300,AB$1,$C$14:$C$300,$U11) -> 0 | AC11: =COUNTIFS($L$14:$L$300,AC$1,$C$14:$C$300,$U11) -> 0 | ... AG11: =COUNTIFS($L$14:$L$300,AG$1,$C$14:$C$300,$U11) -> 0 | AH11: =SUM(V11:AG11) -> 0
U12: SSSTPA | V12: =COUNTIFS($L$14:$L$300,V$1,$C$14:$C$300,$U12) -> 0 | W12: =COUNTIFS($L$14:$L$300,W$1,$C$14:$C$300,$U12) -> 0 | X12: =COUNTIFS($L$14:$L$300,X$1,$C$14:$C$300,$U12) -> 0 | Y12: =COUNTIFS($L$14:$L$300,Y$1,$C$14:$C$300,$U12) -> 0 | Z12: =COUNTIFS($L$14:$L$300,Z$1,$C$14:$C$300,$U12) -> 4 | AA12: =COUNTIFS($L$14:$L$300,AA$1,$C$14:$C$300,$U12) -> 5 | AB12: =COUNTIFS($L$14:$L$300,AB$1,$C$14:$C$300,$U12) -> 0 | AC12: =COUNTIFS($L$14:$L$300,AC$1,$C$14:$C$300,$U12) -> 0 | ... AG12: =COUNTIFS($L$14:$L$300,AG$1,$C$14:$C$300,$U12) -> 0 | AH12: =SUM(V12:AG12) -> 9
A13: IDSDNCA | B13: IDSAP | C13: Subdirección | D13: Gerencia/Activo | E13: Nombre Evento Original | F13: Ficha Instructor | G13: Nombre Instructor | H13: Asistentes Programados | I13: Fecha de Inicio | J13: Fecha de Termino | K13: Sede | L13: Mes | M13: Periodo | N13: Estatus curso | O13: Capacitandos | P13: Ficha Inst | Q13: Instructor | R13: Observaciones | U13: Total | V13: =SUM(V2:V12) -> 0 | W13: =SUM(W2:W12) -> 1 | X13: =SUM(X2:X12) -> 4 | Y13: =SUM(Y2:Y12) -> 8 | Z13: =SUM(Z2:Z12) -> 17 | AA13: =SUM(AA2:AA12) -> 19 | AB13: =SUM(AB2:AB12) -> 0 | AC13: =SUM(AC2:AC12) -> 1 | ... AH13: =SUM(AH2:AH12) -> 66
A14: 52339 | C14: SPRN | D14: ACTIVO DE PRODUCCIÓN REYNOSA | E14: SEGURIDAD EN CENTROS ADMINISTRATIVOS (SCA) | F14: 375324 | G14: MADRIGAL ELISEO DAVID MICHAEL | H14: 12 | I14: 44958 | J14: 44958 | K14: REYNOSA, TAMAULIPAS | L14: =MONTH(J14) -> 2 | M14: =IF(AND(J14>=$B$2,J14<=$C$2),1,0) -> 1 | N14: Realizado | O14: 12 | P14: 375324 | Q14: =IFERROR((VLOOKUP(P14,Padrón[[Ficha]:[Nombre]],2,FALSE)),"-") -> DAVID MICHAEL MADRIGAL ELISEO | S14: =IF(N14="Cancelado","◄ ◄ ◄ Favor de indicar la causa","-") -> -
A15: 52298 | C15: SPRN | D15: ACTIVO DE PRODUCCIÓN REYNOSA | E15: BÁSICO DE SEGURIDAD (BS) | F15: 196157 | G15: POSADAS RAMÍREZ LUCIO ALFONSO | H15: 14 | I15: 44992 | J15: 44993 | K15: REYNOSA, TAMAULIPAS | L15: =MONTH(J15) -> 3 | M15: =IF(AND(J15>=$B$2,J15<=$C$2),1,0) -> 1 | N15: Realizado | O15: 13 | P15: 375324 | Q15: =IFERROR((VLOOKUP(P15,Padrón[[Ficha]:[Nombre]],2,FALSE)),"-") -> DAVID MICHAEL MADRIGAL ELISEO | S15: =IF(N15="Cancelado","◄ ◄ ◄ Favor de indicar la causa","-") -> - | U15: Realizados | V15: 1 | W15: 2 | X15: 3 | Y15: 4 | Z15: 5 | AA15: 6 | AB15: 7 | AC15: 8 | AD15: 9 | AE15: 10 | AF15: 11 | AG15: 12 | AH15: Total
A16: 57979 | C16: SPRN | D16: ACTIVO DE PRODUCCIÓN REYNOSA | E16: PREVENCIÓN DE RIESGOS LABORALES (PRL) | F16: 196157 | G16: POSADAS RAMÍREZ LUCIO ALFONSO | H16: 14 | I16: 45006 | J16: 45009 | K16: REYNOSA, TAMAULIPAS | L16: =MONTH(J16) -> 3 | M16: =IF(AND(J16>=$B$2,J16<=$C$2),1,0) -> 1 | N16: Realizado | O16: 14 | P16: 196157 | Q16: =IFERROR((VLOOKUP(P16,Padrón[[Ficha]:[Nombre]],2,FALSE)),"-") -> LUCIO ALFONSO POSADAS RAMIREZ | S16: =IF(N16="Cancelado","◄ ◄ ◄ Favor de indicar la causa","-") -> - | U16: SCOC | V16: =COUNTIFS($L$14:$L$300,V$15,$C$14:$C$300,$U16,$N$14:$N$300,"Realizado") -> 0 | W16: =COUNTIFS($L$14:$L$300,W$15,$C$14:$C$300,$U16,$N$14:$N$300,"Realizado") -> 0 | X16: =COUNTIFS($L$14:$L$300,X$15,$C$14:$C$300,$U16,$N$14:$N$300,"Realizado") -> 0 | Y16: =COUNTIFS($L$14:$L$300,Y$15,$C$14:$C$300,$U16,$N$14:$N$300,"Realizado") -> 0 | Z16: =COUNTIFS($L$14:$L$300,Z$15,$C$14:$C$300,$U16,$N$14:$N$300,"Realizado") -> 0 | AA16: =COUNTIFS($L$14:$L$300,AA$15,$C$14:$C$300,$U16,$N$14:$N$300,"Realizado") -> 0 | AB16: =COUNTIFS($L$14:$L$300,AB$15,$C$14:$C$300,$U16,$N$14:$N$300,"Realizado") -> 0 | AC16: =COUNTIFS($L$14:$L$300,AC$15,$C$14:$C$300,$U16,$N$14:$N$300,"Realizado") -> 0 | ... AG16: =COUNTIFS($L$14:$L$300,AG$15,$C$14:$C$300,$U16,$N$14:$N$300,"Realizado") -> 0 | AH16: =SUM(V16:AG16) -> 0
A17: 60088 | C17: SPRN | D17: ACTIVO DE PRODUCCIÓN REYNOSA | E17: BÁSICO DE SEGURIDAD (BS) | F17: 196157 | G17: POSADAS RAMÍREZ LUCIO ALFONSO | H17: 8 | I17: 45012 | J17: 45013 | K17: REYNOSA, TAMAULIPAS | L17: =MONTH(J17) -> 3 | M17: =IF(AND(J17>=$B$2,J17<=$C$2),1,0) -> 1 | N17: Realizado | O17: 7 | P17: 196157 | Q17: =IFERROR((VLOOKUP(P17,Padrón[[Ficha]:[Nombre]],2,FALSE)),"-") -> LUCIO ALFONSO POSADAS RAMIREZ | S17: =IF(N17="Cancelado","◄ ◄ ◄ Favor de indicar la causa","-") -> - | U17: SE | V17: =COUNTIFS($L$14:$L$300,V$15,$C$14:$C$300,$U17,$N$14:$N$300,"Realizado") -> 0 | W17: =COUNTIFS($L$14:$L$300,W$15,$C$14:$C$300,$U17,$N$14:$N$300,"Realizado") -> 0 | X17: =COUNTIFS($L$14:$L$300,X$15,$C$14:$C$300,$U17,$N$14:$N$300,"Realizado") -> 0 | Y17: =COUNTIFS($L$14:$L$300,Y$15,$C$14:$C$300,$U17,$N$14:$N$300,"Realizado") -> 0 | Z17: =COUNTIFS($L$14:$L$300,Z$15,$C$14:$C$300,$U17,$N$14:$N$300,"Realizado") -> 0 | AA17: =COUNTIFS($L$14:$L$300,AA$15,$C$14:$C$300,$U17,$N$14:$N$300,"Realizado") -> 0 | AB17: =COUNTIFS($L$14:$L$300,AB$15,$C$14:$C$300,$U17,$N$14:$N$300,"Realizado") -> 0 | AC17: =COUNTIFS($L$14:$L$300,AC$15,$C$14:$C$300,$U17,$N$14:$N$300,"Realizado") -> 0 | ... AG17: =COUNTIFS($L$14:$L$300,AG$15,$C$14:$C$300,$U17,$N$14:$N$300,"Realizado") -> 0 | AH17: =SUM(V17:AG17) -> 0
A18: 52040 | C18: SPRN | D18: ACTIVO DE PRODUCCIÓN REYNOSA | E18: BRIGADAS DE PRIMEROS AUXILIOS (BPA) | F18: 228486 | G18: HERNANDEZ GALVAN JORGE EDUARDO | H18: 16 | I18: 45014 | J18: 45015 | K18: REYNOSA, TAMAULIPAS | L18: =MONTH(J18) -> 3 | M18: =IF(AND(J18>=$B$2,J18<=$C$2),1,0) -> 1 | N18: Realizado | O18: 17 | P18: 228486 | Q18: =IFERROR((VLOOKUP(P18,Padrón[[Ficha]:[Nombre]],2,FALSE)),"-") -> JORGE EDUARDO HERNANDEZ GALVAN | S18: =IF(N18="Cancelado","◄ ◄ ◄ Favor de indicar la causa","-") -> - | U18: SEPCA | V18: =COUNTIFS($L$14:$L$300,V$15,$C$14:$C$300,$U18,$N$14:$N$300,"Realizado") -> 0 | W18: =COUNTIFS($L$14:$L$300,W$15,$C$14:$C$300,$U18,$N$14:$N$300,"Realizado") -> 0 | X18: =COUNTIFS($L$14:$L$300,X$15,$C$14:$C$300,$U18,$N$14:$N$300,"Realizado") -> 0 | Y18: =COUNTIFS($L$14:$L$300,Y$15,$C$14:$C$300,$U18,$N$14:$N$300,"Realizado") -> 0 | Z18: =COUNTIFS($L$14:$L$300,Z$15,$C$14:$C$300,$U18,$N$14:$N$300,"Realizado") -> 0 | AA18: =COUNTIFS($L$14:$L$300,AA$15,$C$14:$C$300,$U18,$N$14:$N$300,"Realizado") -> 0 | AB18: =COUNTIFS($L$14:$L$300,AB$15,$C$14:$C$300,$U18,$N$14:$N$300,"Realizado") -> 0 | AC18: =COUNTIFS($L$14:$L$300,AC$15,$C$14:$C$300,$U18,$N$14:$N$300,"Realizado") -> 0 | ... AG18: =COUNTIFS($L$14:$L$300,AG$15,$C$14:$C$300,$U18,$N$14:$N$300,"Realizado") -> 0 | AH18: =SUM(V18:AG18) -> 0
A19: 52471 | C19: SPRN | D19: ACTIVO DE PRODUCCIÓN REYNOSA | E19: REACREDITACIÓN DE SIGNATARIOS DEL SPPTR (RSPTR) | F19: 196157 | G19: POSADAS RAMÍREZ LUCIO ALFONSO | H19: 10 | I19: 45019 | J19: 45019 | K19: REYNOSA, TAMAULIPAS | L19: =MONTH(J19) -> 4 | M19: =IF(AND(J19>=$B$2,J19<=$C$2),1,0) -> 1 | N19: Realizado | O19: 9 | P19: 196157 | Q19: =IFERROR((VLOOKUP(P19,Padrón[[Ficha]:[Nombre]],2,FALSE)),"-") -> LUCIO ALFONSO POSADAS RAMIREZ | S19: =IF(N19="Cancelado","◄ ◄ ◄ Favor de indicar la causa","-") -> - | U19: SMLIC | V19: =COUNTIFS($L$14:$L$300,V$15,$C$14:$C$300,$U19,$N$14:$N$300,"Realizado") -> 0 | W19: =COUNTIFS($L$14:$L$300,W$15,$C$14:$C$300,$U19,$N$14:$N$300,"Realizado") -> 0 | X19: =COUNTIFS($L$14:$L$300,X$15,$C$14:$C$300,$U19,$N$14:$N$300,"Realizado") -> 0 | Y19: =COUNTIFS($L$14:$L$300,Y$15,$C$14:$C$300,$U19,$N$14:$N$300,"Realizado") -> 0 | Z19: =COUNTIFS($L$14:$L$300,Z$15,$C$14:$C$300,$U19,$N$14:$N$300,"Realizado") -> 0 | AA19: =COUNTIFS($L$14:$L$300,AA$15,$C$14:$C$300,$U19,$N$14:$N$300,"Realizado") -> 5 | AB19: =COUNTIFS($L$14:$L$300,AB$15,$C$14:$C$300,$U19,$N$14:$N$300,"Realizado") -> 0 | AC19: =COUNTIFS($L$14:$L$300,AC$15,$C$14:$C$300,$U19,$N$14:$N$300,"Realizado") -> 0 | ... AG19: =COUNTIFS($L$14:$L$300,AG$15,$C$14:$C$300,$U19,$N$14:$N$300,"Realizado") -> 0 | AH19: =SUM(V19:AG19) -> 7
A20: 52462 | C20: SPRN | D20: ACTIVO DE PRODUCCIÓN REYNOSA | E20: REACREDITACIÓN DE SIGNATARIOS DEL SPPTR (RSPTR) | F20: 196157 | G20: POSADAS RAMÍREZ LUCIO ALFONSO | H20: 13 | I20: 45026 | J20: 45026 | K20: REYNOSA, TAMAULIPAS | L20: =MONTH(J20) -> 4 | M20: =IF(AND(J20>=$B$2,J20<=$C$2),1,0) -> 1 | N20: Realizado | O20: 12 | P20: 196157 | Q20: =IFERROR((VLOOKUP(P20,Padrón[[Ficha]:[Nombre]],2,FALSE)),"-") -> LUCIO ALFONSO POSADAS RAMIREZ | S20: =IF(N20="Cancelado","◄ ◄ ◄ Favor de indicar la causa","-") -> - | U20: SPEE | V20: =COUNTIFS($L$14:$L$300,V$15,$C$14:$C$300,$U20,$N$14:$N$300,"Realizado") -> 0 | W20: =COUNTIFS($L$14:$L$300,W$15,$C$14:$C$300,$U20,$N$14:$N$300,"Realizado") -> 0 | X20: =COUNTIFS($L$14:$L$300,X$15,$C$14:$C$300,$U20,$N$14:$N$300,"Realizado") -> 0 | Y20: =COUNTIFS($L$14:$L$300,Y$15,$C$14:$C$300,$U20,$N$14:$N$300,"Realizado") -> 0 | Z20: =COUNTIFS($L$14:$L$300,Z$15,$C$14:$C$300,$U20,$N$14:$N$300,"Realizado") -> 0 | AA20: =COUNTIFS($L$14:$L$300,AA$15,$C$14:$C$300,$U20,$N$14:$N$300,"Realizado") -> 0 | AB20: =COUNTIFS($L$14:$L$300,AB$15,$C$14:$C$300,$U20,$N$14:$N$300,"Realizado") -> 0 | AC20: =COUNTIFS($L$14:$L$300,AC$15,$C$14:$C$300,$U20,$N$14:$N$300,"Realizado") -> 0 | ... AG20: =COUNTIFS($L$14:$L$300,AG$15,$C$14:$C$300,$U20,$N$14:$N$300,"Realizado") -> 0 | AH20: =SUM(V20:AG20) -> 0
A21: 52266 | C21: SPRN | D21: ACTIVO DE PRODUCCIÓN REYNOSA | E21: ÁCIDO SULFHÍDRICO (H2S) | F21: 361575 | G21: BRIZUELA JASSO JOSE ENRIQUE | H21: 9 | I21: 45027 | J21: 45027 | K21: REYNOSA, TAMAULIPAS | L21: =MONTH(J21) -> 4 | M21: =IF(AND(J21>=$B$2,J21<=$C$2),1,0) -> 1 | N21: Realizado | O21: 9 | P21: 361575 | Q21: =IFERROR((VLOOKUP(P21,Padrón[[Ficha]:[Nombre]],2,FALSE)),"-") -> JOSE ENRIQUE BRIZUELA JASSO | S21: =IF(N21="Cancelado","◄ ◄ ◄ Favor de indicar la causa","-") -> - | U21: SPMP | V21: =COUNTIFS($L$14:$L$300,V$15,$C$14:$C$300,$U21,$N$14:$N$300,"Realizado") -> 0 | W21: =COUNTIFS($L$14:$L$300,W$15,$C$14:$C$300,$U21,$N$14:$N$300,"Realizado") -> 0 | X21: =COUNTIFS($L$14:$L$300,X$15,$C$14:$C$300,$U21,$N$14:$N$300,"Realizado") -> 0 | Y21: =COUNTIFS($L$14:$L$300,Y$15,$C$14:$C$300,$U21,$N$14:$N$300,"Realizado") -> 0 | Z21: =COUNTIFS($L$14:$L$300,Z$15,$C$14:$C$300,$U21,$N$14:$N$300,"Realizado") -> 0 | AA21: =COUNTIFS($L$14:$L$300,AA$15,$C$14:$C$300,$U21,$N$14:$N$300,"Realizado") -> 0 | AB21: =COUNTIFS($L$14:$L$300,AB$15,$C$14:$C$300,$U21,$N$14:$N$300,"Realizado") -> 0 | AC21: =COUNTIFS($L$14:$L$300,AC$15,$C$14:$C$300,$U21,$N$14:$N$300,"Realizado") -> 0 | ... AG21: =COUNTIFS($L$14:$L$300,AG$15,$C$14:$C$300,$U21,$N$14:$N$300,"Realizado") -> 0 | AH21: =SUM(V21:AG21) -> 0
A22: 47728 | C22: SPRN | D22: ACTIVO DE PRODUCCIÓN REYNOSA | E22: DISCIPLINA OPERATIVA (DO) | F22: 196157 | G22: POSADAS RAMÍREZ LUCIO ALFONSO | H22: 17 | I22: 45029 | J22: 45030 | K22: REYNOSA, TAMAULIPAS | L22: =MONTH(J22) -> 4 | M22: =IF(AND(J22>=$B$2,J22<=$C$2),1,0) -> 1 | N22: Realizado | O22: 15 | P22: 196157 | Q22: =IFERROR((VLOOKUP(P22,Padrón[[Ficha]:[Nombre]],2,FALSE)),"-") -> LUCIO ALFONSO POSADAS RAMIREZ | S22: =IF(N22="Cancelado","◄ ◄ ◄ Favor de indicar la causa","-") -> - | U22: SPRMNE | V22: =COUNTIFS($L$14:$L$300,V$15,$C$14:$C$300,$U22,$N$14:$N$300,"Realizado") -> 0 | W22: =COUNTIFS($L$14:$L$300,W$15,$C$14:$C$300,$U22,$N$14:$N$300,"Realizado") -> 0 | X22: =COUNTIFS($L$14:$L$300,X$15,$C$14:$C$300,$U22,$N$14:$N$300,"Realizado") -> 0 | Y22: =COUNTIFS($L$14:$L$300,Y$15,$C$14:$C$300,$U22,$N$14:$N$300,"Realizado") -> 0 | Z22: =COUNTIFS($L$14:$L$300,Z$15,$C$14:$C$300,$U22,$N$14:$N$300,"Realizado") -> 0 | AA22: =COUNTIFS($L$14:$L$300,AA$15,$C$14:$C$300,$U22,$N$14:$N$300,"Realizado") -> 0 | AB22: =COUNTIFS($L$14:$L$300,AB$15,$C$14:$C$300,$U22,$N$14:$N$300,"Realizado") -> 0 | AC22: =COUNTIFS($L$14:$L$300,AC$15,$C$14:$C$300,$U22,$N$14:$N$300,"Realizado") -> 0 | ... AG22: =COUNTIFS($L$14:$L$300,AG$15,$C$14:$C$300,$U22,$N$14:$N$300,"Realizado") -> 0 | AH22: =SUM(V22:AG22) -> 0
A23: 47010 | C23: SPRN | D23: GERENCIA DE MANTENIMIENTO, CONFIABILIDAD Y CONSTRUCCIÓN | E23: BÁSICO DE SEGURIDAD (BS) | F23: 196157 | G23: POSADAS RAMÍREZ LUCIO ALFONSO | H23: 10 | I23: 45033 | J23: 45034 | K23: REYNOSA, TAMAULIPAS | L23: =MONTH(J23) -> 4 | M23: =IF(AND(J23>=$B$2,J23<=$C$2),1,0) -> 1 | N23: Realizado | O23: 11 | P23: 196157 | Q23: =IFERROR((VLOOKUP(P23,Padrón[[Ficha]:[Nombre]],2,FALSE)),"-") -> LUCIO ALFONSO POSADAS RAMIREZ | S23: =IF(N23="Cancelado","◄ ◄ ◄ Favor de indicar la causa","-") -> - | U23: SPRMSO | V23: =COUNTIFS($L$14:$L$300,V$15,$C$14:$C$300,$U23,$N$14:$N$300,"Realizado") -> 0 | W23: =COUNTIFS($L$14:$L$300,W$15,$C$14:$C$300,$U23,$N$14:$N$300,"Realizado") -> 0 | X23: =COUNTIFS($L$14:$L$300,X$15,$C$14:$C$300,$U23,$N$14:$N$300,"Realizado") -> 0 | Y23: =COUNTIFS($L$14:$L$300,Y$15,$C$14:$C$300,$U23,$N$14:$N$300,"Realizado") -> 0 | Z23: =COUNTIFS($L$14:$L$300,Z$15,$C$14:$C$300,$U23,$N$14:$N$300,"Realizado") -> 0 | AA23: =COUNTIFS($L$14:$L$300,AA$15,$C$14:$C$300,$U23,$N$14:$N$300,"Realizado") -> 0 | AB23: =COUNTIFS($L$14:$L$300,AB$15,$C$14:$C$300,$U23,$N$14:$N$300,"Realizado") -> 0 | AC23: =COUNTIFS($L$14:$L$300,AC$15,$C$14:$C$300,$U23,$N$14:$N$300,"Realizado") -> 0 | ... AG23: =COUNTIFS($L$14:$L$300,AG$15,$C$14:$C$300,$U23,$N$14:$N$300,"Realizado") -> 0 | AH23: =SUM(V23:AG23) -> 0
A24: 52274 | C24: SPRN | D24: ACTIVO DE PRODUCCIÓN REYNOSA | E24: PROCEDIMIENTOS CRÍTICOS (PC) | F24: 196157 | G24: POSADAS RAMÍREZ LUCIO ALFONSO | H24: 14 | I24: 45036 | J24: 45037 | K24: REYNOSA, TAMAULIPAS | L24: =MONTH(J24) -> 4 | M24: =IF(AND(J24>=$B$2,J24<=$C$2),1,0) -> 1 | N24: Realizado | O24: 13 | P24: 196157 | Q24: =IFERROR((VLOOKUP(P24,Padrón[[Ficha]:[Nombre]],2,FALSE)),"-") -> LUCIO ALFONSO POSADAS RAMIREZ | S24: =IF(N24="Cancelado","◄ ◄ ◄ Favor de indicar la causa","-") -> - | U24: SPRN | V24: =COUNTIFS($L$14:$L$300,V$15,$C$14:$C$300,$U24,$N$14:$N$300,"Realizado") -> 0 | W24: =COUNTIFS($L$14:$L$300,W$15,$C$14:$C$300,$U24,$N$14:$N$300,"Realizado") -> 1 | X24: =COUNTIFS($L$14:$L$300,X$15,$C$14:$C$300,$U24,$N$14:$N$300,"Realizado") -> 4 | Y24: =COUNTIFS($L$14:$L$300,Y$15,$C$14:$C$300,$U24,$N$14:$N$300,"Realizado") -> 8 | Z24: =COUNTIFS($L$14:$L$300,Z$15,$C$14:$C$300,$U24,$N$14:$N$300,"Realizado") -> 13 | AA24: =COUNTIFS($L$14:$L$300,AA$15,$C$14:$C$300,$U24,$N$14:$N$300,"Realizado") -> 9 | AB24: =COUNTIFS($L$14:$L$300,AB$15,$C$14:$C$300,$U24,$N$14:$N$300,"Realizado") -> 0 | AC24: =COUNTIFS($L$14:$L$300,AC$15,$C$14:$C$300,$U24,$N$14:$N$300,"Realizado") -> 1 | ... AG24: =COUNTIFS($L$14:$L$300,AG$15,$C$14:$C$300,$U24,$N$14:$N$300,"Realizado") -> 0 | AH24: =SUM(V24:AG24) -> 50
A25: 47009 | C25: SPRN | D25: GERENCIA DE MANTENIMIENTO, CONFIABILIDAD Y CONSTRUCCIÓN | E25: BÁSICO DE SEGURIDAD (BS) | F25: 196157 | G25: POSADAS RAMÍREZ LUCIO ALFONSO | H25: 14 | I25: 45040 | J25: 45041 | K25: REYNOSA, TAMAULIPAS | L25: =MONTH(J25) -> 4 | M25: =IF(AND(J25>=$B$2,J25<=$C$2),1,0) -> 1 | N25: Realizado | O25: 14 | P25: 196157 | Q25: =IFERROR((VLOOKUP(P25,Padrón[[Ficha]:[Nombre]],2,FALSE)),"-") -> LUCIO ALFONSO POSADAS RAMIREZ | S25: =IF(N25="Cancelado","◄ ◄ ◄ Favor de indicar la causa","-") -> - | U25: SPRS | V25: =COUNTIFS($L$14:$L$300,V$15,$C$14:$C$300,$U25,$N$14:$N$300,"Realizado") -> 0 | W25: =COUNTIFS($L$14:$L$300,W$15,$C$14:$C$300,$U25,$N$14:$N$300,"Realizado") -> 0 | X25: =COUNTIFS($L$14:$L$300,X$15,$C$14:$C$300,$U25,$N$14:$N$300,"Realizado") -> 0 | Y25: =COUNTIFS($L$14:$L$300,Y$15,$C$14:$C$300,$U25,$N$14:$N$300,"Realizado") -> 0 | Z25: =COUNTIFS($L$14:$L$300,Z$15,$C$14:$C$300,$U25,$N$14:$N$300,"Realizado") -> 0 | AA25: =COUNTIFS($L$14:$L$300,AA$15,$C$14:$C$300,$U25,$N$14:$N$300,"Realizado") -> 0 | AB25: =COUNTIFS($L$14:$L$300,AB$15,$C$14:$C$300,$U25,$N$14:$N$300,"Realizado") -> 0 | AC25: =COUNTIFS($L$14:$L$300,AC$15,$C$14:$C$300,$U25,$N$14:$N$300,"Realizado") -> 0 | ... AG25: =COUNTIFS($L$14:$L$300,AG$15,$C$14:$C$300,$U25,$N$14:$N$300,"Realizado") -> 0 | AH25: =SUM(V25:AG25) -> 0
A26: 47004 | C26: SPRN | D26: GERENCIA DE MANTENIMIENTO, CONFIABILIDAD Y CONSTRUCCIÓN | E26: BÁSICO DE SEGURIDAD (BS) | F26: 196157 | G26: POSADAS RAMÍREZ LUCIO ALFONSO | H26: 15 | I26: 45042 | J26: 45043 | K26: REYNOSA, TAMAULIPAS | L26: =MONTH(J26) -> 4 | M26: =IF(AND(J26>=$B$2,J26<=$C$2),1,0) -> 1 | N26: Realizado | O26: 14 | P26: 196157 | Q26: =IFERROR((VLOOKUP(P26,Padrón[[Ficha]:[Nombre]],2,FALSE)),"-") -> LUCIO ALFONSO POSADAS RAMIREZ | S26: =IF(N26="Cancelado","◄ ◄ ◄ Favor de indicar la causa","-") -> - | U26: SSSTPA | V26: =COUNTIFS($L$14:$L$300,V$15,$C$14:$C$300,$U26,$N$14:$N$300,"Realizado") -> 0 | W26: =COUNTIFS($L$14:$L$300,W$15,$C$14:$C$300,$U26,$N$14:$N$300,"Realizado") -> 0 | X26: =COUNTIFS($L$14:$L$300,X$15,$C$14:$C$300,$U26,$N$14:$N$300,"Realizado") -> 0 | Y26: =COUNTIFS($L$14:$L$300,Y$15,$C$14:$C$300,$U26,$N$14:$N$300,"Realizado") -> 0 | Z26: =COUNTIFS($L$14:$L$300,Z$15,$C$14:$C$300,$U26,$N$14:$N$300,"Realizado") -> 4 | AA26: =COUNTIFS($L$14:$L$300,AA$15,$C$14:$C$300,$U26,$N$14:$N$300,"Realizado") -> 5 | AB26: =COUNTIFS($L$14:$L$300,AB$15,$C$14:$C$300,$U26,$N$14:$N$300,"Realizado") -> 0 | AC26: =COUNTIFS($L$14:$L$300,AC$15,$C$14:$C$300,$U26,$N$14:$N$300,"Realizado") -> 0 | ... AG26: =COUNTIFS($L$14:$L$300,AG$15,$C$14:$C$300,$U26,$N$14:$N$300,"Realizado") -> 0 | AH26: =SUM(V26:AG26) -> 9
A27: 58119 | C27: SPRN | D27: ACTIVO DE PRODUCCIÓN REYNOSA | E27: ADMINISTRACIÓN DE RIESGOS EN LOS PROCESOS DE PEMEX EXPLORACIÓN Y PRODUCCIÓN (ARP PEP) | F27: 375324 | G27: MADRIGAL ELISEO DAVID MICHAEL | H27: 7 | I27: 45054 | J27: 45054 | K27: REYNOSA, TAMAULIPAS | L27: =MONTH(J27) -> 5 | M27: =IF(AND(J27>=$B$2,J27<=$C$2),1,0) -> 1 | N27: Realizado | O27: 7 | P27: 375324 | Q27: =IFERROR((VLOOKUP(P27,Padrón[[Ficha]:[Nombre]],2,FALSE)),"-") -> DAVID MICHAEL MADRIGAL ELISEO | S27: =IF(N27="Cancelado","◄ ◄ ◄ Favor de indicar la causa","-") -> - | U27: Total | V27: =SUM(V16:V26) -> 0 | W27: =SUM(W16:W26) -> 1 | X27: =SUM(X16:X26) -> 4 | Y27: =SUM(Y16:Y26) -> 8 | Z27: =SUM(Z16:Z26) -> 17 | AA27: =SUM(AA16:AA26) -> 19 | AB27: =SUM(AB16:AB26) -> 0 | AC27: =SUM(AC16:AC26) -> 1 | ... AH27: =SUM(AH16:AH26) -> 66
A28: 47023 | C28: SPRN | D28: GERENCIA DE MANTENIMIENTO, CONFIABILIDAD Y CONSTRUCCIÓN | E28: REVALIDACIÓN BÁSICO DE SEGURIDAD (BS) | F28: 196157 | G28: POSADAS RAMÍREZ LUCIO ALFONSO | H28: 18 | I28: 45054 | J28: 45054 | K28: REYNOSA, TAMAULIPAS | L28: =MONTH(J28) -> 5 | M28: =IF(AND(J28>=$B$2,J28<=$C$2),1,0) -> 1 | N28: Realizado | O28: 20 | P28: 348492 | Q28: CLAUDIA CONSUELO CUÉLLAR BURELA | S28: =IF(N28="Cancelado","◄ ◄ ◄ Favor de indicar la causa","-") -> -
A29: 47971 | C29: SPRN | D29: ACTIVO DE PRODUCCIÓN REYNOSA | E29: DISCIPLINA OPERATIVA (DO) | F29: 196157 | G29: POSADAS RAMÍREZ LUCIO ALFONSO | H29: 19 | I29: 45057 | J29: 45058 | K29: REYNOSA, TAMAULIPAS | L29: =MONTH(J29) -> 5 | M29: =IF(AND(J29>=$B$2,J29<=$C$2),1,0) -> 1 | N29: Realizado | O29: 16 | P29: 196157 | Q29: =IFERROR((VLOOKUP(P29,Padrón[[Ficha]:[Nombre]],2,FALSE)),"-") -> LUCIO ALFONSO POSADAS RAMIREZ | S29: =IF(N29="Cancelado","◄ ◄ ◄ Favor de indicar la causa","-") -> - | U29: Cancelados | V29: 1 | W29: 2 | X29: 3 | Y29: 4 | Z29: 5 | AA29: 6 | AB29: 7 | AC29: 8 | AD29: 9 | AE29: 10 | AF29: 11 | AG29: 12 | AH29: Total
A30: 52285 | C30: SPRN | D30: ACTIVO DE PRODUCCIÓN REYNOSA | E30: PREVENCIÓN DE RIESGOS LABORALES (PRL) | F30: 196157 | G30: POSADAS RAMÍREZ LUCIO ALFONSO | H30: 23 | I30: 45061 | J30: 45062 | K30: REYNOSA, TAMAULIPAS | L30: =MONTH(J30) -> 5 | M30: =IF(AND(J30>=$B$2,J30<=$C$2),1,0) -> 1 | N30: Realizado | O30: 19 | P30: 196157 | Q30: =IFERROR((VLOOKUP(P30,Padrón[[Ficha]:[Nombre]],2,FALSE)),"-") -> LUCIO ALFONSO POSADAS RAMIREZ | R30: Reprogramado al 9 y 10 de mayo del 2023 | S30: =IF(N30="Cancelado","◄ ◄ ◄ Favor de indicar la causa","-") -> - | U30: SCOC | V30: =COUNTIFS($L$14:$L$300,V$15,$C$14:$C$300,$U30,$N$14:$N$300,"Cancelado") -> 0 | W30: =COUNTIFS($L$14:$L$300,W$15,$C$14:$C$300,$U30,$N$14:$N$300,"Cancelado") -> 0 | X30: =COUNTIFS($L$14:$L$300,X$15,$C$14:$C$300,$U30,$N$14:$N$300,"Cancelado") -> 0 | Y30: =COUNTIFS($L$14:$L$300,Y$15,$C$14:$C$300,$U30,$N$14:$N$300,"Cancelado") -> 0 | Z30: =COUNTIFS($L$14:$L$300,Z$15,$C$14:$C$300,$U30,$N$14:$N$300,"Cancelado") -> 0 | AA30: =COUNTIFS($L$14:$L$300,AA$15,$C$14:$C$300,$U30,$N$14:$N$300,"Cancelado") -> 0 | AB30: =COUNTIFS($L$14:$L$300,AB$15,$C$14:$C$300,$U30,$N$14:$N$300,"Cancelado") -> 0 | AC30: =COUNTIFS($L$14:$L$300,AC$15,$C$14:$C$300,$U30,$N$14:$N$300,"Cancelado") -> 0 | ... AG30: =COUNTIFS($L$14:$L$300,AG$15,$C$14:$C$300,$U30,$N$14:$N$300,"Cancelado") -> 0 | AH30: =SUM(V30:AG30) -> 0
A31: 52307 | C31: SPRN | D31: ACTIVO DE PRODUCCIÓN REYNOSA | E31: REVALIDACIÓN BÁSICO DE SEGURIDAD (BS) | F31: 226488 | G31: SÁNCHEZ GARCÍA ERNESTO | H31: 9 | I31: 45068 | J31: 45068 | K31: REYNOSA, TAMAULIPAS | L31: =MONTH(J31) -> 5 | M31: =IF(AND(J31>=$B$2,J31<=$C$2),1,0) -> 1 | N31: Realizado | O31: 9 | P31: 348492 | Q31: CLAUDIA CONSUELO CUÉLLAR BURELA | S31: =IF(N31="Cancelado","◄ ◄ ◄ Favor de indicar la causa","-") -> - | U31: SE | V31: =COUNTIFS($L$14:$L$300,V$15,$C$14:$C$300,$U31,$N$14:$N$300,"Cancelado") -> 0 | W31: =COUNTIFS($L$14:$L$300,W$15,$C$14:$C$300,$U31,$N$14:$N$300,"Cancelado") -> 0 | X31: =COUNTIFS($L$14:$L$300,X$15,$C$14:$C$300,$U31,$N$14:$N$300,"Cancelado") -> 0 | Y31: =COUNTIFS($L$14:$L$300,Y$15,$C$14:$C$300,$U31,$N$14:$N$300,"Cancelado") -> 0 | Z31: =COUNTIFS($L$14:$L$300,Z$15,$C$14:$C$300,$U31,$N$14:$N$300,"Cancelado") -> 0 | AA31: =COUNTIFS($L$14:$L$300,AA$15,$C$14:$C$300,$U31,$N$14:$N$300,"Cancelado") -> 0 | AB31: =COUNTIFS($L$14:$L$300,AB$15,$C$14:$C$300,$U31,$N$14:$N$300,"Cancelado") -> 0 | AC31: =COUNTIFS($L$14:$L$300,AC$15,$C$14:$C$300,$U31,$N$14:$N$300,"Cancelado") -> 0 | ... AG31: =COUNTIFS($L$14:$L$300,AG$15,$C$14:$C$300,$U31,$N$14:$N$300,"Cancelado") -> 0 | AH31: =SUM(V31:AG31) -> 0
A32: 47022 | C32: SPRN | D32: GERENCIA DE MANTENIMIENTO, CONFIABILIDAD Y CONSTRUCCIÓN | E32: SEGURIDAD EN CENTROS ADMINISTRATIVOS (SCA) | F32: 147188 | G32: GONZALEZ LOREDO ALEJANDRA L. | H32: 9 | I32: 45068 | J32: 45068 | K32: REYNOSA, TAMAULIPAS | L32: =MONTH(J32) -> 5 | M32: =IF(AND(J32>=$B$2,J32<=$C$2),1,0) -> 1 | N32: Realizado | O32: 10 | P32: 147188 | Q32: GONZALEZ LOREDO ALEJANDRA L. | S32: =IF(N32="Cancelado","◄ ◄ ◄ Favor de indicar la causa","-") -> - | U32: SEPCA | V32: =COUNTIFS($L$14:$L$300,V$15,$C$14:$C$300,$U32,$N$14:$N$300,"Cancelado") -> 0 | W32: =COUNTIFS($L$14:$L$300,W$15,$C$14:$C$300,$U32,$N$14:$N$300,"Cancelado") -> 0 | X32: =COUNTIFS($L$14:$L$300,X$15,$C$14:$C$300,$U32,$N$14:$N$300,"Cancelado") -> 0 | Y32: =COUNTIFS($L$14:$L$300,Y$15,$C$14:$C$300,$U32,$N$14:$N$300,"Cancelado") -> 0 | Z32: =COUNTIFS($L$14:$L$300,Z$15,$C$14:$C$300,$U32,$N$14:$N$300,"Cancelado") -> 0 | AA32: =COUNTIFS($L$14:$L$300,AA$15,$C$14:$C$300,$U32,$N$14:$N$300,"Cancelado") -> 0 | AB32: =COUNTIFS($L$14:$L$300,AB$15,$C$14:$C$300,$U32,$N$14:$N$300,"Cancelado") -> 0 | AC32: =COUNTIFS($L$14:$L$300,AC$15,$C$14:$C$300,$U32,$N$14:$N$300,"Cancelado") -> 0 | ... AG32: =COUNTIFS($L$14:$L$300,AG$15,$C$14:$C$300,$U32,$N$14:$N$300,"Cancelado") -> 0 | AH32: =SUM(V32:AG32) -> 0
A33: 48078 | C33: SSSTPA | D33: GERENCIA DE SEGURIDAD, SALUD EN EL TRABAJO Y PROTECCIÓN AMBIENTAL REGIÓN NORTE | E33: PROCEDIMIENTOS CRÍTICOS (PC) | F33: 375324 | G33: MADRIGAL ELISEO DAVID MICHAEL | H33: 15 | I33: 45068 | J33: 45069 | K33: REYNOSA, TAMAULIPAS | L33: =MONTH(J33) -> 5 | M33: =IF(AND(J33>=$B$2,J33<=$C$2),1,0) -> 1 | N33: Realizado | O33: 13 | P33: 375324 | Q33: MADRIGAL ELISEO DAVID MICHAEL | R33: VACACIONES MANUEL ANTONIO MARTÍNEZ PALOS | S33: =IF(N33="Cancelado","◄ ◄ ◄ Favor de indicar la causa","-") -> - | U33: SMLIC | V33: =COUNTIFS($L$14:$L$300,V$15,$C$14:$C$300,$U33,$N$14:$N$300,"Cancelado") -> 0 | W33: =COUNTIFS($L$14:$L$300,W$15,$C$14:$C$300,$U33,$N$14:$N$300,"Cancelado") -> 0 | X33: =COUNTIFS($L$14:$L$300,X$15,$C$14:$C$300,$U33,$N$14:$N$300,"Cancelado") -> 0 | Y33: =COUNTIFS($L$14:$L$300,Y$15,$C$14:$C$300,$U33,$N$14:$N$300,"Cancelado") -> 0 | Z33: =COUNTIFS($L$14:$L$300,Z$15,$C$14:$C$300,$U33,$N$14:$N$300,"Cancelado") -> 0 | AA33: =COUNTIFS($L$14:$L$300,AA$15,$C$14:$C$300,$U33,$N$14:$N$300,"Cancelado") -> 0 | AB33: =COUNTIFS($L$14:$L$300,AB$15,$C$14:$C$300,$U33,$N$14:$N$300,"Cancelado") -> 0 | AC33: =COUNTIFS($L$14:$L$300,AC$15,$C$14:$C$300,$U33,$N$14:$N$300,"Cancelado") -> 0 | ... AG33: =COUNTIFS($L$14:$L$300,AG$15,$C$14:$C$300,$U33,$N$14:$N$300,"Cancelado") -> 0 | AH33: =SUM(V33:AG33) -> 0
A34: 57850 | C34: SPRN | D34: ACTIVO DE PRODUCCIÓN REYNOSA | E34: MANEJO A LA DEFENSIVA (MD) | F34: 317251 | G34: ALEMAN GARCIA FELIX HORACIO | H34: 17 | I34: 45069 | J34: 45070 | K34: REYNOSA, TAMAULIPAS | L34: =MONTH(J34) -> 5 | M34: =IF(AND(J34>=$B$2,J34<=$C$2),1,0) -> 1 | N34: Realizado | O34: 20 | P34: 317251 | Q34: ALEMAN GARCIA FELIX HORACIO | S34: =IF(N34="Cancelado","◄ ◄ ◄ Favor de indicar la causa","-") -> - | U34: SPEE | V34: =COUNTIFS($L$14:$L$300,V$15,$C$14:$C$300,$U34,$N$14:$N$300,"Cancelado") -> 0 | W34: =COUNTIFS($L$14:$L$300,W$15,$C$14:$C$300,$U34,$N$14:$N$300,"Cancelado") -> 0 | X34: =COUNTIFS($L$14:$L$300,X$15,$C$14:$C$300,$U34,$N$14:$N$300,"Cancelado") -> 0 | Y34: =COUNTIFS($L$14:$L$300,Y$15,$C$14:$C$300,$U34,$N$14:$N$300,"Cancelado") -> 0 | Z34: =COUNTIFS($L$14:$L$300,Z$15,$C$14:$C$300,$U34,$N$14:$N$300,"Cancelado") -> 0 | AA34: =COUNTIFS($L$14:$L$300,AA$15,$C$14:$C$300,$U34,$N$14:$N$300,"Cancelado") -> 0 | AB34: =COUNTIFS($L$14:$L$300,AB$15,$C$14:$C$300,$U34,$N$14:$N$300,"Cancelado") -> 0 | AC34: =COUNTIFS($L$14:$L$300,AC$15,$C$14:$C$300,$U34,$N$14:$N$300,"Cancelado") -> 0 | ... AG34: =COUNTIFS($L$14:$L$300,AG$15,$C$14:$C$300,$U34,$N$14:$N$300,"Cancelado") -> 0 | AH34: =SUM(V34:AG34) -> 0
A35: 53958 | C35: SPRN | D35: ACTIVO DE PRODUCCIÓN REYNOSA | E35: PREVENCIÓN DE RIESGOS LABORALES (PRL) | F35: 196157 | G35: POSADAS RAMÍREZ LUCIO ALFONSO | H35: 15 | I35: 45069 | J35: 45070 | K35: REYNOSA, TAMAULIPAS | L35: =MONTH(J35) -> 5 | M35: =IF(AND(J35>=$B$2,J35<=$C$2),1,0) -> 1 | N35: Realizado | O35: 14 | P35: 196157 | Q35: POSADAS RAMÍREZ LUCIO ALFONSO | S35: =IF(N35="Cancelado","◄ ◄ ◄ Favor de indicar la causa","-") -> - | U35: SPMP | V35: =COUNTIFS($L$14:$L$300,V$15,$C$14:$C$300,$U35,$N$14:$N$300,"Cancelado") -> 0 | W35: =COUNTIFS($L$14:$L$300,W$15,$C$14:$C$300,$U35,$N$14:$N$300,"Cancelado") -> 0 | X35: =COUNTIFS($L$14:$L$300,X$15,$C$14:$C$300,$U35,$N$14:$N$300,"Cancelado") -> 0 | Y35: =COUNTIFS($L$14:$L$300,Y$15,$C$14:$C$300,$U35,$N$14:$N$300,"Cancelado") -> 0 | Z35: =COUNTIFS($L$14:$L$300,Z$15,$C$14:$C$300,$U35,$N$14:$N$300,"Cancelado") -> 0 | AA35: =COUNTIFS($L$14:$L$300,AA$15,$C$14:$C$300,$U35,$N$14:$N$300,"Cancelado") -> 0 | AB35: =COUNTIFS($L$14:$L$300,AB$15,$C$14:$C$300,$U35,$N$14:$N$300,"Cancelado") -> 0 | AC35: =COUNTIFS($L$14:$L$300,AC$15,$C$14:$C$300,$U35,$N$14:$N$300,"Cancelado") -> 0 | ... AG35: =COUNTIFS($L$14:$L$300,AG$15,$C$14:$C$300,$U35,$N$14:$N$300,"Cancelado") -> 0 | AH35: =SUM(V35:AG35) -> 0
A36: 52322 | C36: SPRN | D36: ACTIVO DE PRODUCCIÓN REYNOSA | E36: REVALIDACIÓN BÁSICO DE SEGURIDAD (BS) | F36: 226488 | G36: SÁNCHEZ GARCÍA ERNESTO | H36: 9 | I36: 45070 | J36: 45070 | K36: REYNOSA, TAMAULIPAS | L36: =MONTH(J36) -> 5 | M36: =IF(AND(J36>=$B$2,J36<=$C$2),1,0) -> 1 | N36: Realizado | O36: 9 | P36: 348492 | Q36: CLAUDIA CONSUELO CUÉLLAR BURELA | S36: =IF(N36="Cancelado","◄ ◄ ◄ Favor de indicar la causa","-") -> - | U36: SPRMNE | V36: =COUNTIFS($L$14:$L$300,V$15,$C$14:$C$300,$U36,$N$14:$N$300,"Cancelado") -> 0 | W36: =COUNTIFS($L$14:$L$300,W$15,$C$14:$C$300,$U36,$N$14:$N$300,"Cancelado") -> 0 | X36: =COUNTIFS($L$14:$L$300,X$15,$C$14:$C$300,$U36,$N$14:$N$300,"Cancelado") -> 0 | Y36: =COUNTIFS($L$14:$L$300,Y$15,$C$14:$C$300,$U36,$N$14:$N$300,"Cancelado") -> 0 | Z36: =COUNTIFS($L$14:$L$300,Z$15,$C$14:$C$300,$U36,$N$14:$N$300,"Cancelado") -> 0 | AA36: =COUNTIFS($L$14:$L$300,AA$15,$C$14:$C$300,$U36,$N$14:$N$300,"Cancelado") -> 0 | AB36: =COUNTIFS($L$14:$L$300,AB$15,$C$14:$C$300,$U36,$N$14:$N$300,"Cancelado") -> 0 | AC36: =COUNTIFS($L$14:$L$300,AC$15,$C$14:$C$300,$U36,$N$14:$N$300,"Cancelado") -> 0 | ... AG36: =COUNTIFS($L$14:$L$300,AG$15,$C$14:$C$300,$U36,$N$14:$N$300,"Cancelado") -> 0 | AH36: =SUM(V36:AG36) -> 0
A37: 48103 | C37: SSSTPA | D37: GERENCIA DE SEGURIDAD, SALUD EN EL TRABAJO Y PROTECCIÓN AMBIENTAL REGIÓN NORTE | E37: PROCEDIMIENTOS CRÍTICOS (PC) | F37: 375324 | G37: MADRIGAL ELISEO DAVID MICHAEL | H37: 11 | I37: 45070 | J37: 45071 | K37: REYNOSA, TAMAULIPAS | L37: =MONTH(J37) -> 5 | M37: =IF(AND(J37>=$B$2,J37<=$C$2),1,0) -> 1 | N37: Realizado | O37: 9 | P37: 375324 | Q37: MADRIGAL ELISEO DAVID MICHAEL | R37: OFICIO PEP-DG-SSSTPA-GSSTPARN-CSSTPA-APR-150-2023 (DOS JUBILADOS) | S37: =IF(N37="Cancelado","◄ ◄ ◄ Favor de indicar la causa","-") -> - | U37: SPRMSO | V37: =COUNTIFS($L$14:$L$300,V$15,$C$14:$C$300,$U37,$N$14:$N$300,"Cancelado") -> 0 | W37: =COUNTIFS($L$14:$L$300,W$15,$C$14:$C$300,$U37,$N$14:$N$300,"Cancelado") -> 0 | X37: =COUNTIFS($L$14:$L$300,X$15,$C$14:$C$300,$U37,$N$14:$N$300,"Cancelado") -> 0 | Y37: =COUNTIFS($L$14:$L$300,Y$15,$C$14:$C$300,$U37,$N$14:$N$300,"Cancelado") -> 0 | Z37: =COUNTIFS($L$14:$L$300,Z$15,$C$14:$C$300,$U37,$N$14:$N$300,"Cancelado") -> 0 | AA37: =COUNTIFS($L$14:$L$300,AA$15,$C$14:$C$300,$U37,$N$14:$N$300,"Cancelado") -> 0 | AB37: =COUNTIFS($L$14:$L$300,AB$15,$C$14:$C$300,$U37,$N$14:$N$300,"Cancelado") -> 0 | AC37: =COUNTIFS($L$14:$L$300,AC$15,$C$14:$C$300,$U37,$N$14:$N$300,"Cancelado") -> 0 | ... AG37: =COUNTIFS($L$14:$L$300,AG$15,$C$14:$C$300,$U37,$N$14:$N$300,"Cancelado") -> 0 | AH37: =SUM(V37:AG37) -> 0
A38: 52146 | C38: SPRN | D38: ACTIVO DE PRODUCCIÓN REYNOSA | E38: REVALIDACIÓN BÁSICO DE SEGURIDAD (BS) | F38: 226488 | G38: SÁNCHEZ GARCÍA ERNESTO | H38: 17 | I38: 45071 | J38: 45071 | K38: REYNOSA, TAMAULIPAS | L38: =MONTH(J38) -> 5 | M38: =IF(AND(J38>=$B$2,J38<=$C$2),1,0) -> 1 | N38: Realizado | O38: 16 | P38: 196157 | Q38: POSADAS RAMÍREZ LUCIO ALFONSO | S38: =IF(N38="Cancelado","◄ ◄ ◄ Favor de indicar la causa","-") -> - | U38: SPRN | V38: =COUNTIFS($L$14:$L$300,V$15,$C$14:$C$300,$U38,$N$14:$N$300,"Cancelado") -> 0 | W38: =COUNTIFS($L$14:$L$300,W$15,$C$14:$C$300,$U38,$N$14:$N$300,"Cancelado") -> 0 | X38: =COUNTIFS($L$14:$L$300,X$15,$C$14:$C$300,$U38,$N$14:$N$300,"Cancelado") -> 0 | Y38: =COUNTIFS($L$14:$L$300,Y$15,$C$14:$C$300,$U38,$N$14:$N$300,"Cancelado") -> 0 | Z38: =COUNTIFS($L$14:$L$300,Z$15,$C$14:$C$300,$U38,$N$14:$N$300,"Cancelado") -> 0 | AA38: =COUNTIFS($L$14:$L$300,AA$15,$C$14:$C$300,$U38,$N$14:$N$300,"Cancelado") -> 0 | AB38: =COUNTIFS($L$14:$L$300,AB$15,$C$14:$C$300,$U38,$N$14:$N$300,"Cancelado") -> 0 | AC38: =COUNTIFS($L$14:$L$300,AC$15,$C$14:$C$300,$U38,$N$14:$N$300,"Cancelado") -> 0 | ... AG38: =COUNTIFS($L$14:$L$300,AG$15,$C$14:$C$300,$U38,$N$14:$N$300,"Cancelado") -> 0 | AH38: =SUM(V38:AG38) -> 0
A39: 48028 | C39: SPRN | D39: ACTIVO DE PRODUCCIÓN REYNOSA | E39: MANEJO A LA DEFENSIVA (MD) | F39: 317251 | G39: ALEMAN GARCIA FELIX HORACIO | H39: 17 | I39: 45072 | J39: 45072 | K39: REYNOSA, TAMAULIPAS | L39: =MONTH(J39) -> 5 | M39: =IF(AND(J39>=$B$2,J39<=$C$2),1,0) -> 1 | N39: Realizado | O39: 16 | P39: 317251 | Q39: ALEMAN GARCIA FELIX HORACIO | S39: =IF(N39="Cancelado","◄ ◄ ◄ Favor de indicar la causa","-") -> - | U39: SPRS | V39: =COUNTIFS($L$14:$L$300,V$15,$C$14:$C$300,$U39,$N$14:$N$300,"Cancelado") -> 0 | W39: =COUNTIFS($L$14:$L$300,W$15,$C$14:$C$300,$U39,$N$14:$N$300,"Cancelado") -> 0 | X39: =COUNTIFS($L$14:$L$300,X$15,$C$14:$C$300,$U39,$N$14:$N$300,"Cancelado") -> 0 | Y39: =COUNTIFS($L$14:$L$300,Y$15,$C$14:$C$300,$U39,$N$14:$N$300,"Cancelado") -> 0 | Z39: =COUNTIFS($L$14:$L$300,Z$15,$C$14:$C$300,$U39,$N$14:$N$300,"Cancelado") -> 0 | AA39: =COUNTIFS($L$14:$L$300,AA$15,$C$14:$C$300,$U39,$N$14:$N$300,"Cancelado") -> 0 | AB39: =COUNTIFS($L$14:$L$300,AB$15,$C$14:$C$300,$U39,$N$14:$N$300,"Cancelado") -> 0 | AC39: =COUNTIFS($L$14:$L$300,AC$15,$C$14:$C$300,$U39,$N$14:$N$300,"Cancelado") -> 0 | ... AG39: =COUNTIFS($L$14:$L$300,AG$15,$C$14:$C$300,$U39,$N$14:$N$300,"Cancelado") -> 0 | AH39: =SUM(V39:AG39) -> 0
A40: 48245 | C40: SSSTPA | D40: GERENCIA DE SEGURIDAD, SALUD EN EL TRABAJO Y PROTECCIÓN AMBIENTAL REGIÓN NORTE | E40: VERIFICADOR DE GAS (VG) | F40: 226488 | G40: SÁNCHEZ GARCÍA ERNESTO | H40: 16 | I40: 45072 | J40: 45072 | K40: REYNOSA, TAMAULIPAS | L40: =MONTH(J40) -> 5 | M40: =IF(AND(J40>=$B$2,J40<=$C$2),1,0) -> 1 | N40: Realizado | O40: 15 | P40: 226488 | Q40: SÁNCHEZ GARCÍA ERNESTO | R40: OFICIO PEP-DG-SSSTPA-GSSTPARN-CSSTPA-APR-151-2023 (UN JUBILADO) | S40: =IF(N40="Cancelado","◄ ◄ ◄ Favor de indicar la causa","-") -> - | U40: SSSTPA | V40: =COUNTIFS($L$14:$L$300,V$15,$C$14:$C$300,$U40,$N$14:$N$300,"Cancelado") -> 0 | W40: =COUNTIFS($L$14:$L$300,W$15,$C$14:$C$300,$U40,$N$14:$N$300,"Cancelado") -> 0 | X40: =COUNTIFS($L$14:$L$300,X$15,$C$14:$C$300,$U40,$N$14:$N$300,"Cancelado") -> 0 | Y40: =COUNTIFS($L$14:$L$300,Y$15,$C$14:$C$300,$U40,$N$14:$N$300,"Cancelado") -> 0 | Z40: =COUNTIFS($L$14:$L$300,Z$15,$C$14:$C$300,$U40,$N$14:$N$300,"Cancelado") -> 0 | AA40: =COUNTIFS($L$14:$L$300,AA$15,$C$14:$C$300,$U40,$N$14:$N$300,"Cancelado") -> 0 | AB40: =COUNTIFS($L$14:$L$300,AB$15,$C$14:$C$300,$U40,$N$14:$N$300,"Cancelado") -> 0 | AC40: =COUNTIFS($L$14:$L$300,AC$15,$C$14:$C$300,$U40,$N$14:$N$300,"Cancelado") -> 0 | ... AG40: =COUNTIFS($L$14:$L$300,AG$15,$C$14:$C$300,$U40,$N$14:$N$300,"Cancelado") -> 0 | AH40: =SUM(V40:AG40) -> 0
A41: 52422 | C41: SPRN | D41: ACTIVO DE PRODUCCIÓN REYNOSA | E41: VERIFICADOR DE GAS (VG) | F41: 226488 | G41: SÁNCHEZ GARCÍA ERNESTO | H41: 16 | I41: 45075 | J41: 45075 | K41: REYNOSA, TAMAULIPAS | L41: =MONTH(J41) -> 5 | M41: =IF(AND(J41>=$B$2,J41<=$C$2),1,0) -> 1 | N41: Realizado | O41: 16 | P41: 226488 | Q41: SÁNCHEZ GARCÍA ERNESTO | S41: =IF(N41="Cancelado","◄ ◄ ◄ Favor de indicar la causa","-") -> - | U41: Total | V41: =SUM(V30:V40) -> 0 | W41: =SUM(W30:W40) -> 0 | X41: =SUM(X30:X40) -> 0 | Y41: =SUM(Y30:Y40) -> 0 | Z41: =SUM(Z30:Z40) -> 0 | AA41: =SUM(AA30:AA40) -> 0 | AB41: =SUM(AB30:AB40) -> 0 | AC41: =SUM(AC30:AC40) -> 0 | ... AH41: =SUM(AH30:AH40) -> 0
A42: 47125 | C42: SSSTPA | D42: GERENCIA DE SEGURIDAD, SALUD EN EL TRABAJO Y PROTECCIÓN AMBIENTAL REGIÓN NORTE | E42: BÁSICO DE SEGURIDAD (BS) | F42: 196157 | G42: POSADAS RAMÍREZ LUCIO ALFONSO | H42: 6 | I42: 45075 | J42: 45076 | K42: REYNOSA, TAMAULIPAS | L42: =MONTH(J42) -> 5 | M42: =IF(AND(J42>=$B$2,J42<=$C$2),1,0) -> 1 | N42: Realizado | O42: 4 | P42: 375324 | Q42: MADRIGAL ELISEO DAVID MICHAEL | R42: OFICIO PEP-DG-SSSTPA-GSSTPARN-CSSTPA-APR-152-2023 (DOS JUBILADO) | S42: =IF(N42="Cancelado","◄ ◄ ◄ Favor de indicar la causa","-") -> -
A43: 52430 | C43: SPRN | D43: ACTIVO DE PRODUCCIÓN REYNOSA | E43: MANEJO A LA DEFENSIVA (MD) | F43: 317251 | G43: ALEMAN GARCIA FELIX HORACIO | H43: 10 | I43: 45077 | J43: 45077 | K43: REYNOSA, TAMAULIPAS | L43: =MONTH(J43) -> 5 | M43: =IF(AND(J43>=$B$2,J43<=$C$2),1,0) -> 1 | N43: Realizado | O43: 8 | P43: 317251 | Q43: ALEMAN GARCIA FELIX HORACIO | R43: CAMBIO DE EPS Y SU NUEVO JEFE NO LE DIO LAS FACILIDADES EDNA DE LEON FLORES Y ROBERTO CARLOS ARTEAGA ORTA COMISIONADO EN BRAVO NUEVO LEÓN, POR TRÁFICO EN RETENES NO LLEGO A TIEMPO AL CURSO. | S43: =IF(N43="Cancelado","◄ ◄ ◄ Favor de indicar la causa","-") -> -
A44: 48024 | C44: SSSTPA | D44: GERENCIA DE SEGURIDAD, SALUD EN EL TRABAJO Y PROTECCIÓN AMBIENTAL REGIÓN NORTE | E44: PREVENCIÓN DE RIESGOS LABORALES (PRL) | F44: 375324 | G44: MADRIGAL ELISEO DAVID MICHAEL | H44: 11 | I44: 45077 | J44: 45078 | K44: REYNOSA, TAMAULIPAS | L44: =MONTH(J44) -> 6 | M44: =IF(AND(J44>=$B$2,J44<=$C$2),1,0) -> 1 | N44: Realizado | O44: 8 | P44: 375324 | Q44: =IFERROR((VLOOKUP(P44,Padrón[[Ficha]:[Nombre]],2,FALSE)),"-") -> DAVID MICHAEL MADRIGAL ELISEO | R44: PEP-DG-SSSTPA-GSSTPARN-CSSTPA-APR-153-2023 TRABAJADOR BARRERA GODINEZ JUBILADO Incapacidad 367844 OSCAR EDUARDO ORTIZ CAVAZOS. | S44: =IF(N44="Cancelado","◄ ◄ ◄ Favor de indicar la causa","-") -> -
A45: 48538 | C45: SSSTPA | D45: GERENCIA DE SEGURIDAD, SALUD EN EL TRABAJO Y PROTECCIÓN AMBIENTAL REGIÓN NORTE | E45: DISCIPLINA OPERATIVA (DO) | F45: 196157 | G45: POSADAS RAMÍREZ LUCIO ALFONSO | H45: 15 | I45: 45082 | J45: 45083 | K45: REYNOSA, TAMAULIPAS | L45: =MONTH(J45) -> 6 | M45: =IF(AND(J45>=$B$2,J45<=$C$2),1,0) -> 1 | N45: Realizado | O45: 10 | Q45: =IFERROR((VLOOKUP(P45,Padrón[[Ficha]:[Nombre]],2,FALSE)),"-") -> - | S45: =IF(N45="Cancelado","◄ ◄ ◄ Favor de indicar la causa","-") -> -
A46: 56319 | C46: SSSTPA | D46: GERENCIA DE SEGURIDAD, SALUD EN EL TRABAJO Y PROTECCIÓN AMBIENTAL REGIÓN NORTE | E46: ÁCIDO SULFHÍDRICO (H2S) | F46: 226488 | G46: SÁNCHEZ GARCÍA ERNESTO | H46: 8 | I46: 45082 | J46: 45082 | K46: REYNOSA, TAMAULIPAS | L46: =MONTH(J46) -> 6 | M46: =IF(AND(J46>=$B$2,J46<=$C$2),1,0) -> 1 | N46: Realizado | O46: 6 | P46: 226488 | Q46: =IFERROR((VLOOKUP(P46,Padrón[[Ficha]:[Nombre]],2,FALSE)),"-") -> ERNESTO SANCHEZ GARCIA | S46: =IF(N46="Cancelado","◄ ◄ ◄ Favor de indicar la causa","-") -> -
A47: 52440 | C47: SPRN | D47: ACTIVO DE PRODUCCIÓN REYNOSA | E47: BRIGADAS DE BÚSQUEDA Y RESCATE (BBR) | F47: 228486 | G47: HERNANDEZ GALVAN JORGE EDUARDO | H47: 10 | I47: 45083 | J47: 45085 | K47: REYNOSA, TAMAULIPAS | L47: =MONTH(J47) -> 6 | M47: =IF(AND(J47>=$B$2,J47<=$C$2),1,0) -> 1 | N47: Realizado | O47: 10 | P47: 228486 | Q47: =IFERROR((VLOOKUP(P47,Padrón[[Ficha]:[Nombre]],2,FALSE)),"-") -> JORGE EDUARDO HERNANDEZ GALVAN | S47: =IF(N47="Cancelado","◄ ◄ ◄ Favor de indicar la causa","-") -> -
A48: 56358 | C48: SSSTPA | D48: GERENCIA DE SEGURIDAD, SALUD EN EL TRABAJO Y PROTECCIÓN AMBIENTAL REGIÓN NORTE | E48: DISCIPLINA OPERATIVA (DO) | F48: 375324 | G48: MADRIGAL ELISEO DAVID MICHAEL | H48: 13 | I48: 45083 | J48: 45084 | K48: REYNOSA, TAMAULIPAS | L48: =MONTH(J48) -> 6 | M48: =IF(AND(J48>=$B$2,J48<=$C$2),1,0) -> 1 | N48: Realizado | O48: 13 | P48: 375324 | Q48: =IFERROR((VLOOKUP(P48,Padrón[[Ficha]:[Nombre]],2,FALSE)),"-") -> DAVID MICHAEL MADRIGAL ELISEO | S48: =IF(N48="Cancelado","◄ ◄ ◄ Favor de indicar la causa","-") -> -
A49: 48622 | C49: SSSTPA | D49: GERENCIA DE SEGURIDAD, SALUD EN EL TRABAJO Y PROTECCIÓN AMBIENTAL REGIÓN NORTE | E49: ÁCIDO SULFHÍDRICO (H2S) | F49: 226488 | G49: SÁNCHEZ GARCÍA ERNESTO | H49: 10 | I49: 45084 | J49: 45084 | K49: REYNOSA, TAMAULIPAS | L49: =MONTH(J49) -> 6 | M49: =IF(AND(J49>=$B$2,J49<=$C$2),1,0) -> 1 | N49: Realizado | O49: 9 | P49: 226488 | Q49: =IFERROR((VLOOKUP(P49,Padrón[[Ficha]:[Nombre]],2,FALSE)),"-") -> ERNESTO SANCHEZ GARCIA | S49: =IF(N49="Cancelado","◄ ◄ ◄ Favor de indicar la causa","-") -> -
A50: 48244 | C50: SMLIC | D50: GERENCIA DE SERVICIOS DE LOGÍSTICA TERRESTRE | E50: REVALIDACIÓN BÁSICO DE SEGURIDAD (BS) | F50: 408659 | G50: ROJAS DIAZ JUAN | H50: 15 | I50: 45084 | J50: 45084 | K50: REYNOSA, TAMAULIPAS | L50: =MONTH(J50) -> 6 | M50: =IF(AND(J50>=$B$2,J50<=$C$2),1,0) -> 1 | N50: Realizado | O50: 15 | P50: 408659 | Q50: =IFERROR((VLOOKUP(P50,Padrón[[Ficha]:[Nombre]],2,FALSE)),"-") -> JUAN ROJAS DIAZ | S50: =IF(N50="Cancelado","◄ ◄ ◄ Favor de indicar la causa","-") -> -
A51: 53920 | C51: SPRN | D51: ACTIVO DE PRODUCCIÓN REYNOSA | E51: BRIGADAS CONTRAINCENDIOS (BCI) | F51: 228486 | G51: HERNANDEZ GALVAN JORGE EDUARDO | H51: 11 | I51: 45090 | J51: 45092 | K51: REYNOSA, TAMAULIPAS | L51: =MONTH(J51) -> 6 | M51: =IF(AND(J51>=$B$2,J51<=$C$2),1,0) -> 1 | N51: Realizado | O51: 11 | P51: 228486 | Q51: =IFERROR((VLOOKUP(P51,Padrón[[Ficha]:[Nombre]],2,FALSE)),"-") -> JORGE EDUARDO HERNANDEZ GALVAN | S51: =IF(N51="Cancelado","◄ ◄ ◄ Favor de indicar la causa","-") -> -
A52: 48994 | C52: SMLIC | D52: GERENCIA DE SERVICIOS DE LOGÍSTICA TERRESTRE | E52: REVALIDACIÓN BÁSICO DE SEGURIDAD (BS) | F52: 408659 | G52: ROJAS DIAZ JUAN | H52: 13 | I52: 45091 | J52: 45091 | K52: REYNOSA, TAMAULIPAS | L52: =MONTH(J52) -> 6 | M52: =IF(AND(J52>=$B$2,J52<=$C$2),1,0) -> 1 | N52: Realizado | O52: 11 | P52: 408659 | Q52: =IFERROR((VLOOKUP(P52,Padrón[[Ficha]:[Nombre]],2,FALSE)),"-") -> JUAN ROJAS DIAZ | S52: =IF(N52="Cancelado","◄ ◄ ◄ Favor de indicar la causa","-") -> -
A53: 47978 | C53: SPRN | D53: ACTIVO DE PRODUCCIÓN REYNOSA | E53: DISCIPLINA OPERATIVA (DO) | F53: 243544 | G53: ARCE FLORES JOSE ALBERTO | H53: 17 | I53: 45092 | J53: 45093 | K53: REYNOSA, TAMAULIPAS | L53: =MONTH(J53) -> 6 | M53: =IF(AND(J53>=$B$2,J53<=$C$2),1,0) -> 1 | N53: Realizado | O53: 15 | P53: 226488 | Q53: =IFERROR((VLOOKUP(P53,Padrón[[Ficha]:[Nombre]],2,FALSE)),"-") -> ERNESTO SANCHEZ GARCIA | S53: =IF(N53="Cancelado","◄ ◄ ◄ Favor de indicar la causa","-") -> -
A54: 49212 | C54: SMLIC | D54: GERENCIA DE SERVICIOS DE LOGÍSTICA TERRESTRE | E54: PROCEDIMIENTOS CRÍTICOS (PC) | F54: 408659 | G54: ROJAS DIAZ JUAN | H54: 11 | I54: 45092 | J54: 45093 | K54: REYNOSA, TAMAULIPAS | L54: =MONTH(J54) -> 6 | M54: =IF(AND(J54>=$B$2,J54<=$C$2),1,0) -> 1 | N54: Realizado | O54: 10 | P54: 408659 | Q54: =IFERROR((VLOOKUP(P54,Padrón[[Ficha]:[Nombre]],2,FALSE)),"-") -> JUAN ROJAS DIAZ | S54: =IF(N54="Cancelado","◄ ◄ ◄ Favor de indicar la causa","-") -> -
A55: 47696 | C55: SPRN | D55: ACTIVO DE PRODUCCIÓN REYNOSA | E55: SISTEMA DE PERMISOS PARA TRABAJOS CON RIESGO (SPTR) | F55: 196157 | G55: POSADAS RAMÍREZ LUCIO ALFONSO | H55: 17 | I55: 45096 | J55: 45098 | K55: REYNOSA, TAMAULIPAS | L55: =MONTH(J55) -> 6 | M55: =IF(AND(J55>=$B$2,J55<=$C$2),1,0) -> 1 | N55: Realizado | O55: 17 | P55: 196157 | Q55: =IFERROR((VLOOKUP(P55,Padrón[[Ficha]:[Nombre]],2,FALSE)),"-") -> LUCIO ALFONSO POSADAS RAMIREZ | S55: =IF(N55="Cancelado","◄ ◄ ◄ Favor de indicar la causa","-") -> -
A56: 53913 | C56: SPRN | D56: ACTIVO DE PRODUCCIÓN REYNOSA | E56: BRIGADAS CONTRAINCENDIOS (BCI) | F56: 228486 | G56: HERNANDEZ GALVAN JORGE EDUARDO | H56: 10 | I56: 45097 | J56: 45099 | K56: REYNOSA, TAMAULIPAS | L56: =MONTH(J56) -> 6 | M56: =IF(AND(J56>=$B$2,J56<=$C$2),1,0) -> 1 | N56: Realizado | O56: 10 | Q56: =IFERROR((VLOOKUP(P56,Padrón[[Ficha]:[Nombre]],2,FALSE)),"-") -> - | S56: =IF(N56="Cancelado","◄ ◄ ◄ Favor de indicar la causa","-") -> -
A57: 47050 | C57: SPRN | D57: GERENCIA DE MANTENIMIENTO, CONFIABILIDAD Y CONSTRUCCIÓN | E57: REACREDITACIÓN DE SIGNATARIOS DEL SPPTR (RSPTR) | F57: 196157 | G57: POSADAS RAMÍREZ LUCIO ALFONSO | H57: 16 | I57: 45103 | J57: 45103 | K57: REYNOSA, TAMAULIPAS | L57: =MONTH(J57) -> 6 | M57: =IF(AND(J57>=$B$2,J57<=$C$2),1,0) -> 1 | N57: Realizado | O57: 11 | P57: 196157 | Q57: =IFERROR((VLOOKUP(P57,Padrón[[Ficha]:[Nombre]],2,FALSE)),"-") -> LUCIO ALFONSO POSADAS RAMIREZ | S57: =IF(N57="Cancelado","◄ ◄ ◄ Favor de indicar la causa","-") -> -
A58: 47049 | C58: SPRN | D58: GERENCIA DE MANTENIMIENTO, CONFIABILIDAD Y CONSTRUCCIÓN | E58: REACREDITACIÓN DE SIGNATARIOS DEL SPPTR (RSPTR) | F58: 196157 | G58: POSADAS RAMÍREZ LUCIO ALFONSO | H58: 14 | I58: 45104 | J58: 45104 | K58: REYNOSA, TAMAULIPAS | L58: =MONTH(J58) -> 6 | M58: =IF(AND(J58>=$B$2,J58<=$C$2),1,0) -> 1 | N58: Realizado | O58: 10 | P58: 196157 | Q58: =IFERROR((VLOOKUP(P58,Padrón[[Ficha]:[Nombre]],2,FALSE)),"-") -> LUCIO ALFONSO POSADAS RAMIREZ | S58: =IF(N58="Cancelado","◄ ◄ ◄ Favor de indicar la causa","-") -> -
A59: 47048 | C59: SPRN | D59: GERENCIA DE MANTENIMIENTO, CONFIABILIDAD Y CONSTRUCCIÓN | E59: REACREDITACIÓN DE SIGNATARIOS DEL SPPTR (RSPTR) | F59: 196157 | G59: POSADAS RAMÍREZ LUCIO ALFONSO | H59: 14 | I59: 45105 | J59: 45105 | K59: REYNOSA, TAMAULIPAS | L59: =MONTH(J59) -> 6 | M59: =IF(AND(J59>=$B$2,J59<=$C$2),1,0) -> 1 | N59: Realizado | O59: 12 | P59: 196157 | Q59: =IFERROR((VLOOKUP(P59,Padrón[[Ficha]:[Nombre]],2,FALSE)),"-") -> LUCIO ALFONSO POSADAS RAMIREZ | S59: =IF(N59="Cancelado","◄ ◄ ◄ Favor de indicar la causa","-") -> -
A60: 49311 | C60: SMLIC | D60: GERENCIA DE SERVICIOS DE LOGÍSTICA TERRESTRE | E60: MANEJO A LA DEFENSIVA (MD) | F60: 408659 | G60: ROJAS DIAZ JUAN | H60: 12 | I60: 45105 | J60: 45105 | K60: REYNOSA, TAMAULIPAS | L60: =MONTH(J60) -> 6 | M60: =IF(AND(J60>=$B$2,J60<=$C$2),1,0) -> 1 | N60: Realizado | O60: 12 | P60: 408659 | Q60: =IFERROR((VLOOKUP(P60,Padrón[[Ficha]:[Nombre]],2,FALSE)),"-") -> JUAN ROJAS DIAZ | S60: =IF(N60="Cancelado","◄ ◄ ◄ Favor de indicar la causa","-") -> -
A61: 57397 | C61: SPRN | D61: ACTIVO DE PRODUCCIÓN REYNOSA | E61: AUDITORÍAS EFECTIVAS (AE) | F61: 196157 | G61: POSADAS RAMÍREZ LUCIO ALFONSO | H61: 4 | I61: 45106 | J61: 45106 | K61: REYNOSA, TAMAULIPAS | L61: =MONTH(J61) -> 6 | M61: =IF(AND(J61>=$B$2,J61<=$C$2),1,0) -> 1 | N61: Realizado | O61: 4 | P61: 196157 | Q61: =IFERROR((VLOOKUP(P61,Padrón[[Ficha]:[Nombre]],2,FALSE)),"-") -> LUCIO ALFONSO POSADAS RAMIREZ | S61: =IF(N61="Cancelado","◄ ◄ ◄ Favor de indicar la causa","-") -> -
A62: 49739 | C62: SMLIC | D62: GERENCIA DE SERVICIOS DE LOGÍSTICA TERRESTRE | E62: PREVENCIÓN DE RIESGOS LABORALES (PRL) | F62: 408659 | G62: ROJAS DIAZ JUAN | H62: 14 | I62: 45106 | J62: 45107 | K62: REYNOSA, TAMAULIPAS | L62: =MONTH(J62) -> 6 | M62: =IF(AND(J62>=$B$2,J62<=$C$2),1,0) -> 1 | N62: Realizado | O62: 13 | P62: 408659 | Q62: =IFERROR((VLOOKUP(P62,Padrón[[Ficha]:[Nombre]],2,FALSE)),"-") -> JUAN ROJAS DIAZ | S62: =IF(N62="Cancelado","◄ ◄ ◄ Favor de indicar la causa","-") -> -
A63: 60345 | C63: SPRN | D63: ACTIVO DE PRODUCCIÓN REYNOSA | E63: DISCIPLINA OPERATIVA (DO) | F63: 243544 | G63: ARCE FLORES JOSE ALBERTO | H63: 8 | I63: 45148 | J63: 45149 | K63: REYNOSA, TAMAULIPAS | L63: =MONTH(J63) -> 8 | M63: =IF(AND(J63>=$B$2,J63<=$C$2),1,0) -> 1 | N63: Realizado | O63: 5 | P63: 196157 | Q63: =IFERROR((VLOOKUP(P63,Padrón[[Ficha]:[Nombre]],2,FALSE)),"-") -> LUCIO ALFONSO POSADAS RAMIREZ | S63: =IF(N63="Cancelado","◄ ◄ ◄ Favor de indicar la causa","-") -> -
A64: 47052 | C64: SPRN | D64: GERENCIA DE MANTENIMIENTO, CONFIABILIDAD Y CONSTRUCCIÓN | E64: PREVENCIÓN DE RIESGOS LABORALES (PRL) | F64: 196157 | G64: POSADAS RAMÍREZ LUCIO ALFONSO | H64: 12 | I64: 45173 | J64: 45174 | K64: REYNOSA, TAMAULIPAS | L64: =MONTH(J64) -> 9 | M64: =IF(AND(J64>=$B$2,J64<=$C$2),1,0) -> 1 | N64: Realizado | O64: 12 | P64: 196157 | Q64: =IFERROR((VLOOKUP(P64,Padrón[[Ficha]:[Nombre]],2,FALSE)),"-") -> LUCIO ALFONSO POSADAS RAMIREZ | S64: =IF(N64="Cancelado","◄ ◄ ◄ Favor de indicar la causa","-") -> -
A65: 47914 | C65: SPRN | D65: ACTIVO DE PRODUCCIÓN REYNOSA | E65: SISTEMA DE PERMISOS PARA TRABAJOS CON RIESGO (SPTR) | F65: 196157 | G65: POSADAS RAMÍREZ LUCIO ALFONSO | H65: 16 | I65: 45175 | J65: 45177 | K65: REYNOSA, TAMAULIPAS | L65: =MONTH(J65) -> 9 | M65: =IF(AND(J65>=$B$2,J65<=$C$2),1,0) -> 1 | N65: Realizado | O65: 18 | P65: 196157 | Q65: =IFERROR((VLOOKUP(P65,Padrón[[Ficha]:[Nombre]],2,FALSE)),"-") -> LUCIO ALFONSO POSADAS RAMIREZ | S65: =IF(N65="Cancelado","◄ ◄ ◄ Favor de indicar la causa","-") -> -
A66: 51355 | C66: SMLIC | D66: GERENCIA DE SERVICIOS DE LOGÍSTICA TERRESTRE | E66: SISTEMA DE PERMISOS PARA TRABAJOS CON RIESGO (SPTR) | F66: 196157 | G66: POSADAS RAMÍREZ LUCIO ALFONSO | H66: 11 | I66: 45181 | J66: 45183 | K66: REYNOSA, TAMAULIPAS | L66: =MONTH(J66) -> 9 | M66: =IF(AND(J66>=$B$2,J66<=$C$2),1,0) -> 1 | N66: Realizado | O66: 8 | P66: 196157 | Q66: =IFERROR((VLOOKUP(P66,Padrón[[Ficha]:[Nombre]],2,FALSE)),"-") -> LUCIO ALFONSO POSADAS RAMIREZ | S66: =IF(N66="Cancelado","◄ ◄ ◄ Favor de indicar la causa","-") -> -
A67: 54032 | C67: SPRN | D67: ACTIVO DE PRODUCCIÓN REYNOSA | E67: LIDERAZGO EN SSPA | F67: 196157 | G67: POSADAS RAMÍREZ LUCIO ALFONSO | H67: 15 | I67: 45187 | J67: 45188 | K67: REYNOSA, TAMAULIPAS | L67: =MONTH(J67) -> 9 | M67: =IF(AND(J67>=$B$2,J67<=$C$2),1,0) -> 1 | N67: Realizado | O67: 10 | P67: 196157 | Q67: =IFERROR((VLOOKUP(P67,Padrón[[Ficha]:[Nombre]],2,FALSE)),"-") -> LUCIO ALFONSO POSADAS RAMIREZ | S67: =IF(N67="Cancelado","◄ ◄ ◄ Favor de indicar la causa","-") -> -
A68: 47703 | C68: SPRN | D68: ACTIVO DE PRODUCCIÓN REYNOSA | E68: SISTEMA DE PERMISOS PARA TRABAJOS CON RIESGO (SPTR) | F68: 196157 | G68: POSADAS RAMÍREZ LUCIO ALFONSO | H68: 17 | I68: 45189 | J68: 45191 | K68: REYNOSA, TAMAULIPAS | L68: =MONTH(J68) -> 9 | M68: =IF(AND(J68>=$B$2,J68<=$C$2),1,0) -> 1 | N68: Realizado | O68: 20 | P68: 196157 | Q68: =IFERROR((VLOOKUP(P68,Padrón[[Ficha]:[Nombre]],2,FALSE)),"-") -> LUCIO ALFONSO POSADAS RAMIREZ | S68: =IF(N68="Cancelado","◄ ◄ ◄ Favor de indicar la causa","-") -> -
... A70: 57859 | C70: SPRN | D70: ACTIVO DE PRODUCCIÓN REYNOSA | E70: MANEJO A LA DEFENSIVA (MD) | F70: 317251 | G70: ALEMAN GARCIA FELIX HORACIO | H70: 16 | I70: 45195 | J70: 45196 | K70: REYNOSA, TAMAULIPAS | L70: =MONTH(J70) -> 9 | M70: =IF(AND(J70>=$B$2,J70<=$C$2),1,0) -> 1 | N70: Realizado | O70: 20 | P70: 317251 | Q70: =IFERROR((VLOOKUP(P70,Padrón[[Ficha]:[Nombre]],2,FALSE)),"-") -> FELIX HORACIO ALEMAN GARCIA | S70: =IF(N70="Cancelado","◄ ◄ ◄ Favor de indicar la causa","-") -> -
A71: 52036 | C71: SPRN | D71: ACTIVO DE PRODUCCIÓN REYNOSA | E71: BRIGADAS DE PRIMEROS AUXILIOS (BPA) | F71: 228486 | G71: HERNANDEZ GALVAN JORGE EDUARDO | H71: 12 | I71: 45195 | J71: 45196 | K71: REYNOSA, TAMAULIPAS | L71: =MONTH(J71) -> 9 | M71: =IF(AND(J71>=$B$2,J71<=$C$2),1,0) -> 1 | N71: Realizado | O71: 12 | Q71: =IFERROR((VLOOKUP(P71,Padrón[[Ficha]:[Nombre]],2,FALSE)),"-") -> - | S71: =IF(N71="Cancelado","◄ ◄ ◄ Favor de indicar la causa","-") -> -
A72: 54020 | C72: SPRN | D72: ACTIVO DE PRODUCCIÓN REYNOSA | E72: LIDERAZGO EN SSPA | F72: 196157 | G72: POSADAS RAMÍREZ LUCIO ALFONSO | H72: 13 | I72: 45201 | J72: 45202 | K72: REYNOSA, TAMAULIPAS | L72: =MONTH(J72) -> 10 | M72: =IF(AND(J72>=$B$2,J72<=$C$2),1,0) -> 1 | N72: Realizado | O72: 8 | P72: 348492 | Q72: =IFERROR((VLOOKUP(P72,Padrón[[Ficha]:[Nombre]],2,FALSE)),"-") -> CLAUDIA CONSUELO CUELLAR BURELA | R72: REEPROGRAMADO DEL 30 AL 31 DE OCTUBRE DEL 2023 | S72: =IF(N72="Cancelado","◄ ◄ ◄ Favor de indicar la causa","-") -> -
A73: 47998 | C73: SPRN | D73: ACTIVO DE PRODUCCIÓN REYNOSA | E73: BÁSICO DE SEGURIDAD (BS) | F73: 196157 | G73: POSADAS RAMÍREZ LUCIO ALFONSO | H73: 15 | I73: 45204 | J73: 45205 | K73: REYNOSA, TAMAULIPAS | L73: =MONTH(J73) -> 10 | M73: =IF(AND(J73>=$B$2,J73<=$C$2),1,0) -> 1 | N73: Realizado | O73: 20 | P73: 196157 | Q73: =IFERROR((VLOOKUP(P73,Padrón[[Ficha]:[Nombre]],2,FALSE)),"-") -> LUCIO ALFONSO POSADAS RAMIREZ | S73: =IF(N73="Cancelado","◄ ◄ ◄ Favor de indicar la causa","-") -> -
A74: 51360 | C74: SMLIC | D74: GERENCIA DE SERVICIOS DE LOGÍSTICA TERRESTRE | E74: VERIFICADOR DE GAS (VG) | F74: 196157 | G74: POSADAS RAMÍREZ LUCIO ALFONSO | H74: 7 | I74: 45216 | J74: 45216 | K74: REYNOSA, TAMAULIPAS | L74: =MONTH(J74) -> 10 | M74: =IF(AND(J74>=$B$2,J74<=$C$2),1,0) -> 1 | N74: Realizado | O74: 15 | P74: 226488 | Q74: =IFERROR((VLOOKUP(P74,Padrón[[Ficha]:[Nombre]],2,FALSE)),"-") -> ERNESTO SANCHEZ GARCIA | S74: =IF(N74="Cancelado","◄ ◄ ◄ Favor de indicar la causa","-") -> -
A75: 48045 | C75: SPRN | D75: ACTIVO DE PRODUCCIÓN REYNOSA | E75: PREVENCIÓN DE RIESGOS LABORALES (PRL) | F75: 196157 | G75: POSADAS RAMÍREZ LUCIO ALFONSO | H75: 18 | I75: 45218 | J75: 45219 | K75: REYNOSA, TAMAULIPAS | L75: =MONTH(J75) -> 10 | M75: =IF(AND(J75>=$B$2,J75<=$C$2),1,0) -> 1 | N75: Realizado | O75: 17 | P75: 196157 | Q75: =IFERROR((VLOOKUP(P75,Padrón[[Ficha]:[Nombre]],2,FALSE)),"-") -> LUCIO ALFONSO POSADAS RAMIREZ | S75: =IF(N75="Cancelado","◄ ◄ ◄ Favor de indicar la causa","-") -> -
A76: 53994 | C76: SPRN | D76: ACTIVO DE PRODUCCIÓN REYNOSA | E76: LIDERAZGO EN SSPA | F76: 196157 | G76: POSADAS RAMÍREZ LUCIO ALFONSO | H76: 13 | I76: 45222 | J76: 45223 | K76: REYNOSA, TAMAULIPAS | L76: =MONTH(J76) -> 10 | M76: =IF(AND(J76>=$B$2,J76<=$C$2),1,0) -> 1 | N76: Realizado | O76: 9 | P76: 196157 | Q76: =IFERROR((VLOOKUP(P76,Padrón[[Ficha]:[Nombre]],2,FALSE)),"-") -> LUCIO ALFONSO POSADAS RAMIREZ | S76: =IF(N76="Cancelado","◄ ◄ ◄ Favor de indicar la causa","-") -> -
A77: 48051 | C77: SPRN | D77: ACTIVO DE PRODUCCIÓN REYNOSA | E77: PREVENCIÓN DE RIESGOS LABORALES (PRL) | F77: 196157 | G77: POSADAS RAMÍREZ LUCIO ALFONSO | H77: 19 | I77: 45225 | J77: 45226 | K77: REYNOSA, TAMAULIPAS | L77: =MONTH(J77) -> 10 | M77: =IF(AND(J77>=$B$2,J77<=$C$2),1,0) -> 1 | N77: Realizado | O77: 17 | P77: 196157 | Q77: =IFERROR((VLOOKUP(P77,Padrón[[Ficha]:[Nombre]],2,FALSE)),"-") -> LUCIO ALFONSO POSADAS RAMIREZ | S77: =IF(N77="Cancelado","◄ ◄ ◄ Favor de indicar la causa","-") -> -
A78: 60124 | C78: SPRN | D78: ACTIVO DE PRODUCCIÓN REYNOSA | E78: SISTEMA DE PERMISOS PARA TRABAJOS CON RIESGO (SPTR) | F78: 196157 | G78: POSADAS RAMÍREZ LUCIO ALFONSO | H78: 8 | I78: 45229 | J78: 45231 | K78: REYNOSA, TAMAULIPAS | L78: =MONTH(J78) -> 11 | M78: =IF(AND(J78>=$B$2,J78<=$C$2),1,0) -> 1 | N78: Realizado | O78: 11 | P78: 196157 | Q78: =IFERROR((VLOOKUP(P78,Padrón[[Ficha]:[Nombre]],2,FALSE)),"-") -> LUCIO ALFONSO POSADAS RAMIREZ | R78: REPROGRAMADO DEL 13 AL 15 DE NOVIEMBRE DEL 2023 | S78: =IF(N78="Cancelado","◄ ◄ ◄ Favor de indicar la causa","-") -> -
A79: 58027 | C79: SPRN | D79: ACTIVO DE PRODUCCIÓN REYNOSA | E79: PREVENCIÓN DE RIESGOS LABORALES (PRL) | F79: 196157 | G79: POSADAS RAMÍREZ LUCIO ALFONSO | H79: 16 | I79: 45251 | J79: 45254 | K79: REYNOSA, TAMAULIPAS | L79: =MONTH(J79) -> 11 | M79: =IF(AND(J79>=$B$2,J79<=$C$2),1,0) -> 1 | N79: Realizado | O79: 15 | P79: 196157 | Q79: =IFERROR((VLOOKUP(P79,Padrón[[Ficha]:[Nombre]],2,FALSE)),"-") -> LUCIO ALFONSO POSADAS RAMIREZ | S79: =IF(N79="Cancelado","◄ ◄ ◄ Favor de indicar la causa","-") -> -
Q80: =IFERROR((VLOOKUP(P80,Padrón[[Ficha]:[Nombre]],2,FALSE)),"-") -> -
Q81: =IFERROR((VLOOKUP(P81,Padrón[[Ficha]:[Nombre]],2,FALSE)),"-") -> -
Q82: =IFERROR((VLOOKUP(P82,Padrón[[Ficha]:[Nombre]],2,FALSE)),"-") -> -
Q83: =IFERROR((VLOOKUP(P83,Padrón[[Ficha]:[Nombre]],2,FALSE)),"-") -> -
Q84: =IFERROR((VLOOKUP(P84,Padrón[[Ficha]:[Nombre]],2,FALSE)),"-") -> -
Q85: =IFERROR((VLOOKUP(P85,Padrón[[Ficha]:[Nombre]],2,FALSE)),"-") -> -
Q86: =IFERROR((VLOOKUP(P86,Padrón[[Ficha]:[Nombre]],2,FALSE)),"-") -> -
Q87: =IFERROR((VLOOKUP(P87,Padrón[[Ficha]:[Nombre]],2,FALSE)),"-") -> -
Q88: =IFERROR((VLOOKUP(P88,Padrón[[Ficha]:[Nombre]],2,FALSE)),"-") -> -
Q89: =IFERROR((VLOOKUP(P89,Padrón[[Ficha]:[Nombre]],2,FALSE)),"-") -> -
Q90: =IFERROR((VLOOKUP(P90,Padrón[[Ficha]:[Nombre]],2,FALSE)),"-") -> -
Q91: =IFERROR((VLOOKUP(P91,Padrón[[Ficha]:[Nombre]],2,FALSE)),"-") -> -
... Q160: =IFERROR((VLOOKUP(P160,Padrón[[Ficha]:[Nombre]],2,FALSE)),"-") -> -

Sheet Cerro_Azul
B1: Fecha inicial | C1: Fecha final | U1: Programa | V1: 1 | W1: 2 | X1: 3 | Y1: 4 | Z1: 5 | AA1: 6 | AB1: 7 | AC1: 8 | AD1: 9 | AE1: 10 | AF1: 11 | AG1: 12 | AH1: Total
B2: =Seguimiento!$E$6 -> 44927 | C2: =Seguimiento!$J$6 -> 45291 | U2: SCOC | V2: =COUNTIFS($L$14:$L$300,V$1,$C$14:$C$300,$U2) -> 0 | W2: =COUNTIFS($L$14:$L$300,W$1,$C$14:$C$300,$U2) -> 0 | X2: =COUNTIFS($L$14:$L$300,X$1,$C$14:$C$300,$U2) -> 0 | Y2: =COUNTIFS($L$14:$L$300,Y$1,$C$14:$C$300,$U2) -> 0 | Z2: =COUNTIFS($L$14:$L$300,Z$1,$C$14:$C$300,$U2) -> 0 | AA2: =COUNTIFS($L$14:$L$300,AA$1,$C$14:$C$300,$U2) -> 0 | AB2: =COUNTIFS($L$14:$L$300,AB$1,$C$14:$C$300,$U2) -> 0 | AC2: =COUNTIFS($L$14:$L$300,AC$1,$C$14:$C$300,$U2) -> 0 | ... AG2: =COUNTIFS($L$14:$L$300,AG$1,$C$14:$C$300,$U2) -> 0 | AH2: =SUM(V2:AG2) -> 0
H3: PICADE | U3: SE | V3: =COUNTIFS($L$14:$L$300,V$1,$C$14:$C$300,$U3) -> 0 | W3: =COUNTIFS($L$14:$L$300,W$1,$C$14:$C$300,$U3) -> 0 | X3: =COUNTIFS($L$14:$L$300,X$1,$C$14:$C$300,$U3) -> 0 | Y3: =COUNTIFS($L$14:$L$300,Y$1,$C$14:$C$300,$U3) -> 0 | Z3: =COUNTIFS($L$14:$L$300,Z$1,$C$14:$C$300,$U3) -> 0 | AA3: =COUNTIFS($L$14:$L$300,AA$1,$C$14:$C$300,$U3) -> 0 | AB3: =COUNTIFS($L$14:$L$300,AB$1,$C$14:$C$300,$U3) -> 0 | AC3: =COUNTIFS($L$14:$L$300,AC$1,$C$14:$C$300,$U3) -> 0 | ... AG3: =COUNTIFS($L$14:$L$300,AG$1,$C$14:$C$300,$U3) -> 0 | AH3: =SUM(V3:AG3) -> 0
H4: Cursos | I4: Capacitandos | J4: Programados | K4: Realizados en prog. | L4: Cancelados | N4: Capacitandos programados | O4: Capacitandos | U4: SEPCA | V4: =COUNTIFS($L$14:$L$300,V$1,$C$14:$C$300,$U4) -> 0 | W4: =COUNTIFS($L$14:$L$300,W$1,$C$14:$C$300,$U4) -> 0 | X4: =COUNTIFS($L$14:$L$300,X$1,$C$14:$C$300,$U4) -> 0 | Y4: =COUNTIFS($L$14:$L$300,Y$1,$C$14:$C$300,$U4) -> 0 | Z4: =COUNTIFS($L$14:$L$300,Z$1,$C$14:$C$300,$U4) -> 0 | AA4: =COUNTIFS($L$14:$L$300,AA$1,$C$14:$C$300,$U4) -> 0 | AB4: =COUNTIFS($L$14:$L$300,AB$1,$C$14:$C$300,$U4) -> 0 | AC4: =COUNTIFS($L$14:$L$300,AC$1,$C$14:$C$300,$U4) -> 0 | ... AG4: =COUNTIFS($L$14:$L$300,AG$1,$C$14:$C$300,$U4) -> 0 | AH4: =SUM(V4:AG4) -> 0
H5: =COUNT(A14:A300) -> 33 | I5: =SUM(H14:H300) -> 440 | J5: =COUNTIF($M$14:$M$300,1) -> 33 | K5: =COUNTIFS($M$14:$M$300,1,$N$14:$N$300,"Realizado") -> 33 | L5: =COUNTIFS($M$14:$M$300,1,$N$14:$N$300,"Cancelado") -> 0 | N5: =+SUMIF($M$14:$M$300,1,$H$14:$H$300) -> 440 | O5: =+SUMIF($M$14:$M$300,1,$O$14:$O$300) -> 360 | U5: SMLIC | V5: =COUNTIFS($L$14:$L$300,V$1,$C$14:$C$300,$U5) -> 0 | W5: =COUNTIFS($L$14:$L$300,W$1,$C$14:$C$300,$U5) -> 0 | X5: =COUNTIFS($L$14:$L$300,X$1,$C$14:$C$300,$U5) -> 0 | Y5: =COUNTIFS($L$14:$L$300,Y$1,$C$14:$C$300,$U5) -> 1 | Z5: =COUNTIFS($L$14:$L$300,Z$1,$C$14:$C$300,$U5) -> 0 | AA5: =COUNTIFS($L$14:$L$300,AA$1,$C$14:$C$300,$U5) -> 0 | AB5: =COUNTIFS($L$14:$L$300,AB$1,$C$14:$C$300,$U5) -> 0 | AC5: =COUNTIFS($L$14:$L$300,AC$1,$C$14:$C$300,$U5) -> 0 | ... AG5: =COUNTIFS($L$14:$L$300,AG$1,$C$14:$C$300,$U5) -> 0 | AH5: =SUM(V5:AG5) -> 2
U6: SPEE | V6: =COUNTIFS($L$14:$L$300,V$1,$C$14:$C$300,$U6) -> 0 | W6: =COUNTIFS($L$14:$L$300,W$1,$C$14:$C$300,$U6) -> 0 | X6: =COUNTIFS($L$14:$L$300,X$1,$C$14:$C$300,$U6) -> 0 | Y6: =COUNTIFS($L$14:$L$300,Y$1,$C$14:$C$300,$U6) -> 0 | Z6: =COUNTIFS($L$14:$L$300,Z$1,$C$14:$C$300,$U6) -> 0 | AA6: =COUNTIFS($L$14:$L$300,AA$1,$C$14:$C$300,$U6) -> 0 | AB6: =COUNTIFS($L$14:$L$300,AB$1,$C$14:$C$300,$U6) -> 0 | AC6: =COUNTIFS($L$14:$L$300,AC$1,$C$14:$C$300,$U6) -> 0 | ... AG6: =COUNTIFS($L$14:$L$300,AG$1,$C$14:$C$300,$U6) -> 0 | AH6: =SUM(V6:AG6) -> 0
U7: SPMP | V7: =COUNTIFS($L$14:$L$300,V$1,$C$14:$C$300,$U7) -> 0 | W7: =COUNTIFS($L$14:$L$300,W$1,$C$14:$C$300,$U7) -> 0 | X7: =COUNTIFS($L$14:$L$300,X$1,$C$14:$C$300,$U7) -> 0 | Y7: =COUNTIFS($L$14:$L$300,Y$1,$C$14:$C$300,$U7) -> 0 | Z7: =COUNTIFS($L$14:$L$300,Z$1,$C$14:$C$300,$U7) -> 0 | AA7: =COUNTIFS($L$14:$L$300,AA$1,$C$14:$C$300,$U7) -> 0 | AB7: =COUNTIFS($L$14:$L$300,AB$1,$C$14:$C$300,$U7) -> 0 | AC7: =COUNTIFS($L$14:$L$300,AC$1,$C$14:$C$300,$U7) -> 0 | ... AG7: =COUNTIFS($L$14:$L$300,AG$1,$C$14:$C$300,$U7) -> 0 | AH7: =SUM(V7:AG7) -> 0
U8: SPRMNE | V8: =COUNTIFS($L$14:$L$300,V$1,$C$14:$C$300,$U8) -> 0 | W8: =COUNTIFS($L$14:$L$300,W$1,$C$14:$C$300,$U8) -> 0 | X8: =COUNTIFS($L$14:$L$300,X$1,$C$14:$C$300,$U8) -> 0 | Y8: =COUNTIFS($L$14:$L$300,Y$1,$C$14:$C$300,$U8) -> 0 | Z8: =COUNTIFS($L$14:$L$300,Z$1,$C$14:$C$300,$U8) -> 0 | AA8: =COUNTIFS($L$14:$L$300,AA$1,$C$14:$C$300,$U8) -> 0 | AB8: =COUNTIFS($L$14:$L$300,AB$1,$C$14:$C$300,$U8) -> 0 | AC8: =COUNTIFS($L$14:$L$300,AC$1,$C$14:$C$300,$U8) -> 0 | ... AG8: =COUNTIFS($L$14:$L$300,AG$1,$C$14:$C$300,$U8) -> 0 | AH8: =SUM(V8:AG8) -> 0
U9: SPRMSO | V9: =COUNTIFS($L$14:$L$300,V$1,$C$14:$C$300,$U9) -> 0 | W9: =COUNTIFS($L$14:$L$300,W$1,$C$14:$C$300,$U9) -> 0 | X9: =COUNTIFS($L$14:$L$300,X$1,$C$14:$C$300,$U9) -> 0 | Y9: =COUNTIFS($L$14:$L$300,Y$1,$C$14:$C$300,$U9) -> 0 | Z9: =COUNTIFS($L$14:$L$300,Z$1,$C$14:$C$300,$U9) -> 0 | AA9: =COUNTIFS($L$14:$L$300,AA$1,$C$14:$C$300,$U9) -> 0 | AB9: =COUNTIFS($L$14:$L$300,AB$1,$C$14:$C$300,$U9) -> 0 | AC9: =COUNTIFS($L$14:$L$300,AC$1,$C$14:$C$300,$U9) -> 0 | ... AG9: =COUNTIFS($L$14:$L$300,AG$1,$C$14:$C$300,$U9) -> 0 | AH9: =SUM(V9:AG9) -> 0
U10: SPRN | V10: =COUNTIFS($L$14:$L$300,V$1,$C$14:$C$300,$U10) -> 0 | W10: =COUNTIFS($L$14:$L$300,W$1,$C$14:$C$300,$U10) -> 3 | X10: =COUNTIFS($L$14:$L$300,X$1,$C$14:$C$300,$U10) -> 4 | Y10: =COUNTIFS($L$14:$L$300,Y$1,$C$14:$C$300,$U10) -> 4 | Z10: =COUNTIFS($L$14:$L$300,Z$1,$C$14:$C$300,$U10) -> 3 | AA10: =COUNTIFS($L$14:$L$300,AA$1,$C$14:$C$300,$U10) -> 4 | AB10: =COUNTIFS($L$14:$L$300,AB$1,$C$14:$C$300,$U10) -> 2 | AC10: =COUNTIFS($L$14:$L$300,AC$1,$C$14:$C$300,$U10) -> 1 | ... AG10: =COUNTIFS($L$14:$L$300,AG$1,$C$14:$C$300,$U10) -> 0 | AH10: =SUM(V10:AG10) -> 25
U11: SPRS | V11: =COUNTIFS($L$14:$L$300,V$1,$C$14:$C$300,$U11) -> 0 | W11: =COUNTIFS($L$14:$L$300,W$1,$C$14:$C$300,$U11) -> 0 | X11: =COUNTIFS($L$14:$L$300,X$1,$C$14:$C$300,$U11) -> 0 | Y11: =COUNTIFS($L$14:$L$300,Y$1,$C$14:$C$300,$U11) -> 0 | Z11: =COUNTIFS($L$14:$L$300,Z$1,$C$14:$C$300,$U11) -> 0 | AA11: =COUNTIFS($L$14:$L$300,AA$1,$C$14:$C$300,$U11) -> 0 | AB11: =COUNTIFS($L$14:$L$300,AB$1,$C$14:$C$300,$U11) -> 0 | AC11: =COUNTIFS($L$14:$L$300,AC$1,$C$14:$C$300,$U11) -> 0 | ... AG11: =COUNTIFS($L$14:$L$300,AG$1,$C$14:$C$300,$U11) -> 0 | AH11: =SUM(V11:AG11) -> 0
U12: SSSTPA | V12: =COUNTIFS($L$14:$L$300,V$1,$C$14:$C$300,$U12) -> 0 | W12: =COUNTIFS($L$14:$L$300,W$1,$C$14:$C$300,$U12) -> 1 | X12: =COUNTIFS($L$14:$L$300,X$1,$C$14:$C$300,$U12) -> 3 | Y12: =COUNTIFS($L$14:$L$300,Y$1,$C$14:$C$300,$U12) -> 0 | Z12: =COUNTIFS($L$14:$L$300,Z$1,$C$14:$C$300,$U12) -> 2 | AA12: =COUNTIFS($L$14:$L$300,AA$1,$C$14:$C$300,$U12) -> 0 | AB12: =COUNTIFS($L$14:$L$300,AB$1,$C$14:$C$300,$U12) -> 0 | AC12: =COUNTIFS($L$14:$L$300,AC$1,$C$14:$C$300,$U12) -> 0 | ... AG12: =COUNTIFS($L$14:$L$300,AG$1,$C$14:$C$300,$U12) -> 0 | AH12: =SUM(V12:AG12) -> 6
A13: IDSDNCA | B13: IDSAP | C13: Subdirección | D13: Gerencia/Activo | E13: Nombre Evento Original | F13: Ficha Instructor | G13: Nombre Instructor | H13: Asistentes Programados | I13: Fecha de Inicio | J13: Fecha de Termino | K13: Sede | L13: Mes | M13: Periodo | N13: Estatus curso | O13: Capacitandos | P13: Ficha Inst | Q13: Instructor | R13: Observaciones | U13: Total | V13: =SUM(V2:V12) -> 0 | W13: =SUM(W2:W12) -> 4 | X13: =SUM(X2:X12) -> 7 | Y13: =SUM(Y2:Y12) -> 5 | Z13: =SUM(Z2:Z12) -> 5 | AA13: =SUM(AA2:AA12) -> 4 | AB13: =SUM(AB2:AB12) -> 2 | AC13: =SUM(AC2:AC12) -> 1 | ... AH13: =SUM(AH2:AH12) -> 33
A14: 51742 | C14: SSSTPA | D14: GERENCIA DE SEGURIDAD, SALUD EN EL TRABAJO Y PROTECCIÓN AMBIENTAL REGIÓN NORTE | E14: PROCEDIMIENTOS CRÍTICOS (PC) | F14: 196853 | G14: DEL ANGEL DEL ANGEL JUSTO JESUS | H14: 10 | I14: 44973 | J14: 44974 | K14: CERRO AZUL,VERACRUZ | L14: =MONTH(J14) -> 2 | M14: =IF(AND(J14>=$B$2,J14<=$C$2),1,0) -> 1 | N14: Realizado | O14: 10 | P14: 196853 | Q14: =IFERROR((VLOOKUP(P14,Padrón[[Ficha]:[Nombre]],2,FALSE)),"-") -> JUSTO JESUS DEL ANGEL DEL ANGEL | S14: =IF(N14="Cancelado","◄ ◄ ◄ Favor de indicar la causa","-") -> -
A15: 48902 | C15: SPRN | D15: GERENCIA DE MANTENIMIENTO, CONFIABILIDAD Y CONSTRUCCIÓN | E15: BÁSICO DE SEGURIDAD (BS) | F15: 372624 | G15: CARRILLO CABELLO JAIR DE JESUS | H15: 17 | I15: 44977 | J15: 44978 | K15: CERRO AZUL,VERACRUZ | L15: =MONTH(J15) -> 2 | M15: =IF(AND(J15>=$B$2,J15<=$C$2),1,0) -> 1 | N15: Realizado | O15: 14 | P15: 372624 | Q15: =IFERROR((VLOOKUP(P15,Padrón[[Ficha]:[Nombre]],2,FALSE)),"-") -> JAIR DE JESUS CARRILLO CABELLO | S15: =IF(N15="Cancelado","◄ ◄ ◄ Favor de indicar la causa","-") -> - | U15: Realizados | V15: 1 | W15: 2 | X15: 3 | Y15: 4 | Z15: 5 | AA15: 6 | AB15: 7 | AC15: 8 | AD15: 9 | AE15: 10 | AF15: 11 | AG15: 12 | AH15: Total
A16: 49110 | C16: SPRN | D16: GERENCIA DE MANTENIMIENTO, CONFIABILIDAD Y CONSTRUCCIÓN | E16: ÁCIDO SULFHÍDRICO (H2S) | F16: 196853 | G16: DEL ANGEL DEL ANGEL JUSTO JESUS | H16: 9 | I16: 44981 | J16: 44981 | K16: CERRO AZUL,VERACRUZ | L16: =MONTH(J16) -> 2 | M16: =IF(AND(J16>=$B$2,J16<=$C$2),1,0) -> 1 | N16: Realizado | O16: 9 | P16: 196853 | Q16: =IFERROR((VLOOKUP(P16,Padrón[[Ficha]:[Nombre]],2,FALSE)),"-") -> JUSTO JESUS DEL ANGEL DEL ANGEL | S16: =IF(N16="Cancelado","◄ ◄ ◄ Favor de indicar la causa","-") -> - | U16: SCOC | V16: =COUNTIFS($L$14:$L$300,V$15,$C$14:$C$300,$U16,$N$14:$N$300,"Realizado") -> 0 | W16: =COUNTIFS($L$14:$L$300,W$15,$C$14:$C$300,$U16,$N$14:$N$300,"Realizado") -> 0 | X16: =COUNTIFS($L$14:$L$300,X$15,$C$14:$C$300,$U16,$N$14:$N$300,"Realizado") -> 0 | Y16: =COUNTIFS($L$14:$L$300,Y$15,$C$14:$C$300,$U16,$N$14:$N$300,"Realizado") -> 0 | Z16: =COUNTIFS($L$14:$L$300,Z$15,$C$14:$C$300,$U16,$N$14:$N$300,"Realizado") -> 0 | AA16: =COUNTIFS($L$14:$L$300,AA$15,$C$14:$C$300,$U16,$N$14:$N$300,"Realizado") -> 0 | AB16: =COUNTIFS($L$14:$L$300,AB$15,$C$14:$C$300,$U16,$N$14:$N$300,"Realizado") -> 0 | AC16: =COUNTIFS($L$14:$L$300,AC$15,$C$14:$C$300,$U16,$N$14:$N$300,"Realizado") -> 0 | ... AG16: =COUNTIFS($L$14:$L$300,AG$15,$C$14:$C$300,$U16,$N$14:$N$300,"Realizado") -> 0 | AH16: =SUM(V16:AG16) -> 0
A17: 50159 | C17: SPRN | D17: GERENCIA DE MANTENIMIENTO, CONFIABILIDAD Y CONSTRUCCIÓN | E17: AUDITORÍAS EFECTIVAS (AE) | F17: 196853 | G17: DEL ANGEL DEL ANGEL JUSTO JESUS | H17: 12 | I17: 44985 | J17: 44985 | K17: CERRO AZUL,VERACRUZ | L17: =MONTH(J17) -> 2 | M17: =IF(AND(J17>=$B$2,J17<=$C$2),1,0) -> 1 | N17: Realizado | O17: 11 | P17: 196853 | Q17: =IFERROR((VLOOKUP(P17,Padrón[[Ficha]:[Nombre]],2,FALSE)),"-") -> JUSTO JESUS DEL ANGEL DEL ANGEL | S17: =IF(N17="Cancelado","◄ ◄ ◄ Favor de indicar la causa","-") -> - | U17: SE | V17: =COUNTIFS($L$14:$L$300,V$15,$C$14:$C$300,$U17,$N$14:$N$300,"Realizado") -> 0 | W17: =COUNTIFS($L$14:$L$300,W$15,$C$14:$C$300,$U17,$N$14:$N$300,"Realizado") -> 0 | X17: =COUNTIFS($L$14:$L$300,X$15,$C$14:$C$300,$U17,$N$14:$N$300,"Realizado") -> 0 | Y17: =COUNTIFS($L$14:$L$300,Y$15,$C$14:$C$300,$U17,$N$14:$N$300,"Realizado") -> 0 | Z17: =COUNTIFS($L$14:$L$300,Z$15,$C$14:$C$300,$U17,$N$14:$N$300,"Realizado") -> 0 | AA17: =COUNTIFS($L$14:$L$300,AA$15,$C$14:$C$300,$U17,$N$14:$N$300,"Realizado") -> 0 | AB17: =COUNTIFS($L$14:$L$300,AB$15,$C$14:$C$300,$U17,$N$14:$N$300,"Realizado") -> 0 | AC17: =COUNTIFS($L$14:$L$300,AC$15,$C$14:$C$300,$U17,$N$14:$N$300,"Realizado") -> 0 | ... AG17: =COUNTIFS($L$14:$L$300,AG$15,$C$14:$C$300,$U17,$N$14:$N$300,"Realizado") -> 0 | AH17: =SUM(V17:AG17) -> 0
A18: 51099 | C18: SSSTPA | D18: GERENCIA DE SEGURIDAD, SALUD EN EL TRABAJO Y PROTECCIÓN AMBIENTAL REGIÓN NORTE | E18: SEGURIDAD EN CENTROS ADMINISTRATIVOS (SCA) | F18: 196853 | G18: DEL ANGEL DEL ANGEL JUSTO JESUS | H18: 12 | I18: 44988 | J18: 44988 | K18: CERRO AZUL,VERACRUZ | L18: =MONTH(J18) -> 3 | M18: =IF(AND(J18>=$B$2,J18<=$C$2),1,0) -> 1 | N18: Realizado | O18: 9 | P18: 196853 | Q18: =IFERROR((VLOOKUP(P18,Padrón[[Ficha]:[Nombre]],2,FALSE)),"-") -> JUSTO JESUS DEL ANGEL DEL ANGEL | S18: =IF(N18="Cancelado","◄ ◄ ◄ Favor de indicar la causa","-") -> - | U18: SEPCA | V18: =COUNTIFS($L$14:$L$300,V$15,$C$14:$C$300,$U18,$N$14:$N$300,"Realizado") -> 0 | W18: =COUNTIFS($L$14:$L$300,W$15,$C$14:$C$300,$U18,$N$14:$N$300,"Realizado") -> 0 | X18: =COUNTIFS($L$14:$L$300,X$15,$C$14:$C$300,$U18,$N$14:$N$300,"Realizado") -> 0 | Y18: =COUNTIFS($L$14:$L$300,Y$15,$C$14:$C$300,$U18,$N$14:$N$300,"Realizado") -> 0 | Z18: =COUNTIFS($L$14:$L$300,Z$15,$C$14:$C$300,$U18,$N$14:$N$300,"Realizado") -> 0 | AA18: =COUNTIFS($L$14:$L$300,AA$15,$C$14:$C$300,$U18,$N$14:$N$300,"Realizado") -> 0 | AB18: =COUNTIFS($L$14:$L$300,AB$15,$C$14:$C$300,$U18,$N$14:$N$300,"Realizado") -> 0 | AC18: =COUNTIFS($L$14:$L$300,AC$15,$C$14:$C$300,$U18,$N$14:$N$300,"Realizado") -> 0 | ... AG18: =COUNTIFS($L$14:$L$300,AG$15,$C$14:$C$300,$U18,$N$14:$N$300,"Realizado") -> 0 | AH18: =SUM(V18:AG18) -> 0
A19: 49853 | C19: SSSTPA | D19: GERENCIA DE SEGURIDAD, SALUD EN EL TRABAJO Y PROTECCIÓN AMBIENTAL REGIÓN NORTE | E19: BÁSICO DE SEGURIDAD (BS) | F19: 372624 | G19: CARRILLO CABELLO JAIR DE JESUS | H19: 8 | I19: 44998 | J19: 44999 | K19: CERRO AZUL,VERACRUZ | L19: =MONTH(J19) -> 3 | M19: =IF(AND(J19>=$B$2,J19<=$C$2),1,0) -> 1 | N19: Realizado | O19: 6 | P19: 372624 | Q19: =IFERROR((VLOOKUP(P19,Padrón[[Ficha]:[Nombre]],2,FALSE)),"-") -> JAIR DE JESUS CARRILLO CABELLO | S19: =IF(N19="Cancelado","◄ ◄ ◄ Favor de indicar la causa","-") -> - | U19: SMLIC | V19: =COUNTIFS($L$14:$L$300,V$15,$C$14:$C$300,$U19,$N$14:$N$300,"Realizado") -> 0 | W19: =COUNTIFS($L$14:$L$300,W$15,$C$14:$C$300,$U19,$N$14:$N$300,"Realizado") -> 0 | X19: =COUNTIFS($L$14:$L$300,X$15,$C$14:$C$300,$U19,$N$14:$N$300,"Realizado") -> 0 | Y19: =COUNTIFS($L$14:$L$300,Y$15,$C$14:$C$300,$U19,$N$14:$N$300,"Realizado") -> 1 | Z19: =COUNTIFS($L$14:$L$300,Z$15,$C$14:$C$300,$U19,$N$14:$N$300,"Realizado") -> 0 | AA19: =COUNTIFS($L$14:$L$300,AA$15,$C$14:$C$300,$U19,$N$14:$N$300,"Realizado") -> 0 | AB19: =COUNTIFS($L$14:$L$300,AB$15,$C$14:$C$300,$U19,$N$14:$N$300,"Realizado") -> 0 | AC19: =COUNTIFS($L$14:$L$300,AC$15,$C$14:$C$300,$U19,$N$14:$N$300,"Realizado") -> 0 | ... AG19: =COUNTIFS($L$14:$L$300,AG$15,$C$14:$C$300,$U19,$N$14:$N$300,"Realizado") -> 0 | AH19: =SUM(V19:AG19) -> 2
A20: 50426 | C20: SSSTPA | D20: GERENCIA DE SEGURIDAD, SALUD EN EL TRABAJO Y PROTECCIÓN AMBIENTAL REGIÓN NORTE | E20: PREVENCIÓN DE RIESGOS LABORALES (PRL) | F20: 372624 | G20: CARRILLO CABELLO JAIR DE JESUS | H20: 12 | I20: 45000 | J20: 45001 | K20: CERRO AZUL,VERACRUZ | L20: =MONTH(J20) -> 3 | M20: =IF(AND(J20>=$B$2,J20<=$C$2),1,0) -> 1 | N20: Realizado | O20: 12 | P20: 372624 | Q20: =IFERROR((VLOOKUP(P20,Padrón[[Ficha]:[Nombre]],2,FALSE)),"-") -> JAIR DE JESUS CARRILLO CABELLO | S20: =IF(N20="Cancelado","◄ ◄ ◄ Favor de indicar la causa","-") -> - | U20: SPEE | V20: =COUNTIFS($L$14:$L$300,V$15,$C$14:$C$300,$U20,$N$14:$N$300,"Realizado") -> 0 | W20: =COUNTIFS($L$14:$L$300,W$15,$C$14:$C$300,$U20,$N$14:$N$300,"Realizado") -> 0 | X20: =COUNTIFS($L$14:$L$300,X$15,$C$14:$C$300,$U20,$N$14:$N$300,"Realizado") -> 0 | Y20: =COUNTIFS($L$14:$L$300,Y$15,$C$14:$C$300,$U20,$N$14:$N$300,"Realizado") -> 0 | Z20: =COUNTIFS($L$14:$L$300,Z$15,$C$14:$C$300,$U20,$N$14:$N$300,"Realizado") -> 0 | AA20: =COUNTIFS($L$14:$L$300,AA$15,$C$14:$C$300,$U20,$N$14:$N$300,"Realizado") -> 0 | AB20: =COUNTIFS($L$14:$L$300,AB$15,$C$14:$C$300,$U20,$N$14:$N$300,"Realizado") -> 0 | AC20: =COUNTIFS($L$14:$L$300,AC$15,$C$14:$C$300,$U20,$N$14:$N$300,"Realizado") -> 0 | ... AG20: =COUNTIFS($L$14:$L$300,AG$15,$C$14:$C$300,$U20,$N$14:$N$300,"Realizado") -> 0 | AH20: =SUM(V20:AG20) -> 0
A21: 49442 | C21: SPRN | D21: GERENCIA DE MANTENIMIENTO, CONFIABILIDAD Y CONSTRUCCIÓN | E21: VERIFICADOR DE GAS (VG) | F21: 352720 | G21: ROSAS HERNANDEZ ROBERTO AUGUSTO | H21: 15 | I21: 45001 | J21: 45001 | K21: CERRO AZUL,VERACRUZ | L21: =MONTH(J21) -> 3 | M21: =IF(AND(J21>=$B$2,J21<=$C$2),1,0) -> 1 | N21: Realizado | O21: 14 | P21: 352720 | Q21: =IFERROR((VLOOKUP(P21,Padrón[[Ficha]:[Nombre]],2,FALSE)),"-") -> ROBERTO AUGUSTO ROSAS HERNANDEZ | R21: REPROGRAMADO AL 6 DE MARZO DEL 2023, POR DISPONIBILIDAD DEL INSTRUCTOR | S21: =IF(N21="Cancelado","◄ ◄ ◄ Favor de indicar la causa","-") -> - | U21: SPMP | V21: =COUNTIFS($L$14:$L$300,V$15,$C$14:$C$300,$U21,$N$14:$N$300,"Realizado") -> 0 | W21: =COUNTIFS($L$14:$L$300,W$15,$C$14:$C$300,$U21,$N$14:$N$300,"Realizado") -> 0 | X21: =COUNTIFS($L$14:$L$300,X$15,$C$14:$C$300,$U21,$N$14:$N$300,"Realizado") -> 0 | Y21: =COUNTIFS($L$14:$L$300,Y$15,$C$14:$C$300,$U21,$N$14:$N$300,"Realizado") -> 0 | Z21: =COUNTIFS($L$14:$L$300,Z$15,$C$14:$C$300,$U21,$N$14:$N$300,"Realizado") -> 0 | AA21: =COUNTIFS($L$14:$L$300,AA$15,$C$14:$C$300,$U21,$N$14:$N$300,"Realizado") -> 0 | AB21: =COUNTIFS($L$14:$L$300,AB$15,$C$14:$C$300,$U21,$N$14:$N$300,"Realizado") -> 0 | AC21: =COUNTIFS($L$14:$L$300,AC$15,$C$14:$C$300,$U21,$N$14:$N$300,"Realizado") -> 0 | ... AG21: =COUNTIFS($L$14:$L$300,AG$15,$C$14:$C$300,$U21,$N$14:$N$300,"Realizado") -> 0 | AH21: =SUM(V21:AG21) -> 0
A22: 49423 | C22: SPRN | D22: GERENCIA DE MANTENIMIENTO, CONFIABILIDAD Y CONSTRUCCIÓN | E22: REACREDITACIÓN DE SIGNATARIOS DEL SPPTR (RSPTR) | F22: 352720 | G22: ROSAS HERNANDEZ ROBERTO AUGUSTO | H22: 10 | I22: 45006 | J22: 45006 | K22: CERRO AZUL,VERACRUZ | L22: =MONTH(J22) -> 3 | M22: =IF(AND(J22>=$B$2,J22<=$C$2),1,0) -> 1 | N22: Realizado | O22: 8 | P22: 352720 | Q22: =IFERROR((VLOOKUP(P22,Padrón[[Ficha]:[Nombre]],2,FALSE)),"-") -> ROBERTO AUGUSTO ROSAS HERNANDEZ | R22: REPROGRAMADO AL 31 DE MARZO DEL 2023, POR DISPONIBILIDAD DEL INSTRUCTOR | S22: =IF(N22="Cancelado","◄ ◄ ◄ Favor de indicar la causa","-") -> - | U22: SPRMNE | V22: =COUNTIFS($L$14:$L$300,V$15,$C$14:$C$300,$U22,$N$14:$N$300,"Realizado") -> 0 | W22: =COUNTIFS($L$14:$L$300,W$15,$C$14:$C$300,$U22,$N$14:$N$300,"Realizado") -> 0 | X22: =COUNTIFS($L$14:$L$300,X$15,$C$14:$C$300,$U22,$N$14:$N$300,"Realizado") -> 0 | Y22: =COUNTIFS($L$14:$L$300,Y$15,$C$14:$C$300,$U22,$N$14:$N$300,"Realizado") -> 0 | Z22: =COUNTIFS($L$14:$L$300,Z$15,$C$14:$C$300,$U22,$N$14:$N$300,"Realizado") -> 0 | AA22: =COUNTIFS($L$14:$L$300,AA$15,$C$14:$C$300,$U22,$N$14:$N$300,"Realizado") -> 0 | AB22: =COUNTIFS($L$14:$L$300,AB$15,$C$14:$C$300,$U22,$N$14:$N$300,"Realizado") -> 0 | AC22: =COUNTIFS($L$14:$L$300,AC$15,$C$14:$C$300,$U22,$N$14:$N$300,"Realizado") -> 0 | ... AG22: =COUNTIFS($L$14:$L$300,AG$15,$C$14:$C$300,$U22,$N$14:$N$300,"Realizado") -> 0 | AH22: =SUM(V22:AG22) -> 0
A23: 55060 | C23: SPRN | D23: ACTIVO DE PRODUCCIÓN POZA RICA - ALTAMIRA | E23: PROCEDIMIENTOS CRÍTICOS (PC) | F23: 196853 | G23: DEL ANGEL DEL ANGEL JUSTO JESUS | H23: 12 | I23: 45012 | J23: 45013 | K23: CERRO AZUL,VERACRUZ | L23: =MONTH(J23) -> 3 | M23: =IF(AND(J23>=$B$2,J23<=$C$2),1,0) -> 1 | N23: Realizado | O23: 9 | Q23: =IFERROR((VLOOKUP(P23,Padrón[[Ficha]:[Nombre]],2,FALSE)),"-") -> - | S23: =IF(N23="Cancelado","◄ ◄ ◄ Favor de indicar la causa","-") -> - | U23: SPRMSO | V23: =COUNTIFS($L$14:$L$300,V$15,$C$14:$C$300,$U23,$N$14:$N$300,"Realizado") -> 0 | W23: =COUNTIFS($L$14:$L$300,W$15,$C$14:$C$300,$U23,$N$14:$N$300,"Realizado") -> 0 | X23: =COUNTIFS($L$14:$L$300,X$15,$C$14:$C$300,$U23,$N$14:$N$300,"Realizado") -> 0 | Y23: =COUNTIFS($L$14:$L$300,Y$15,$C$14:$C$300,$U23,$N$14:$N$300,"Realizado") -> 0 | Z23: =COUNTIFS($L$14:$L$300,Z$15,$C$14:$C$300,$U23,$N$14:$N$300,"Realizado") -> 0 | AA23: =COUNTIFS($L$14:$L$300,AA$15,$C$14:$C$300,$U23,$N$14:$N$300,"Realizado") -> 0 | AB23: =COUNTIFS($L$14:$L$300,AB$15,$C$14:$C$300,$U23,$N$14:$N$300,"Realizado") -> 0 | AC23: =COUNTIFS($L$14:$L$300,AC$15,$C$14:$C$300,$U23,$N$14:$N$300,"Realizado") -> 0 | ... AG23: =COUNTIFS($L$14:$L$300,AG$15,$C$14:$C$300,$U23,$N$14:$N$300,"Realizado") -> 0 | AH23: =SUM(V23:AG23) -> 0
A24: 48904 | C24: SPRN | D24: GERENCIA DE MANTENIMIENTO, CONFIABILIDAD Y CONSTRUCCIÓN | E24: BÁSICO DE SEGURIDAD (BS) | F24: 372624 | G24: CARRILLO CABELLO JAIR DE JESUS | H24: 15 | I24: 45012 | J24: 45013 | K24: CERRO AZUL,VERACRUZ | L24: =MONTH(J24) -> 3 | M24: =IF(AND(J24>=$B$2,J24<=$C$2),1,0) -> 1 | N24: Realizado | O24: 16 | P24: 372624 | Q24: =IFERROR((VLOOKUP(P24,Padrón[[Ficha]:[Nombre]],2,FALSE)),"-") -> JAIR DE JESUS CARRILLO CABELLO | S24: =IF(N24="Cancelado","◄ ◄ ◄ Favor de indicar la causa","-") -> - | U24: SPRN | V24: =COUNTIFS($L$14:$L$300,V$15,$C$14:$C$300,$U24,$N$14:$N$300,"Realizado") -> 0 | W24: =COUNTIFS($L$14:$L$300,W$15,$C$14:$C$300,$U24,$N$14:$N$300,"Realizado") -> 3 | X24: =COUNTIFS($L$14:$L$300,X$15,$C$14:$C$300,$U24,$N$14:$N$300,"Realizado") -> 4 | Y24: =COUNTIFS($L$14:$L$300,Y$15,$C$14:$C$300,$U24,$N$14:$N$300,"Realizado") -> 4 | Z24: =COUNTIFS($L$14:$L$300,Z$15,$C$14:$C$300,$U24,$N$14:$N$300,"Realizado") -> 3 | AA24: =COUNTIFS($L$14:$L$300,AA$15,$C$14:$C$300,$U24,$N$14:$N$300,"Realizado") -> 4 | AB24: =COUNTIFS($L$14:$L$300,AB$15,$C$14:$C$300,$U24,$N$14:$N$300,"Realizado") -> 2 | AC24: =COUNTIFS($L$14:$L$300,AC$15,$C$14:$C$300,$U24,$N$14:$N$300,"Realizado") -> 1 | ... AG24: =COUNTIFS($L$14:$L$300,AG$15,$C$14:$C$300,$U24,$N$14:$N$300,"Realizado") -> 0 | AH24: =SUM(V24:AG24) -> 25
A25: 47957 | C25: SMLIC | D25: GERENCIA DE SERVICIOS DE LOGÍSTICA TERRESTRE | E25: MANEJO A LA DEFENSIVA (MD) | F25: 372624 | G25: CARRILLO CABELLO JAIR DE JESUS | H25: 12 | I25: 45020 | J25: 45020 | K25: CERRO AZUL,VERACRUZ | L25: =MONTH(J25) -> 4 | M25: =IF(AND(J25>=$B$2,J25<=$C$2),1,0) -> 1 | N25: Realizado | O25: 7 | P25: 372624 | Q25: =IFERROR((VLOOKUP(P25,Padrón[[Ficha]:[Nombre]],2,FALSE)),"-") -> JAIR DE JESUS CARRILLO CABELLO | S25: =IF(N25="Cancelado","◄ ◄ ◄ Favor de indicar la causa","-") -> - | U25: SPRS | V25: =COUNTIFS($L$14:$L$300,V$15,$C$14:$C$300,$U25,$N$14:$N$300,"Realizado") -> 0 | W25: =COUNTIFS($L$14:$L$300,W$15,$C$14:$C$300,$U25,$N$14:$N$300,"Realizado") -> 0 | X25: =COUNTIFS($L$14:$L$300,X$15,$C$14:$C$300,$U25,$N$14:$N$300,"Realizado") -> 0 | Y25: =COUNTIFS($L$14:$L$300,Y$15,$C$14:$C$300,$U25,$N$14:$N$300,"Realizado") -> 0 | Z25: =COUNTIFS($L$14:$L$300,Z$15,$C$14:$C$300,$U25,$N$14:$N$300,"Realizado") -> 0 | AA25: =COUNTIFS($L$14:$L$300,AA$15,$C$14:$C$300,$U25,$N$14:$N$300,"Realizado") -> 0 | AB25: =COUNTIFS($L$14:$L$300,AB$15,$C$14:$C$300,$U25,$N$14:$N$300,"Realizado") -> 0 | AC25: =COUNTIFS($L$14:$L$300,AC$15,$C$14:$C$300,$U25,$N$14:$N$300,"Realizado") -> 0 | ... AG25: =COUNTIFS($L$14:$L$300,AG$15,$C$14:$C$300,$U25,$N$14:$N$300,"Realizado") -> 0 | AH25: =SUM(V25:AG25) -> 0
A26: 59167 | C26: SPRN | D26: ACTIVO DE PRODUCCIÓN POZA RICA - ALTAMIRA | E26: PROCEDIMIENTOS CRÍTICOS (PC) | F26: 372624 | G26: CARRILLO CABELLO JAIR DE JESUS | H26: 11 | I26: 45026 | J26: 45027 | K26: CERRO AZUL,VERACRUZ | L26: =MONTH(J26) -> 4 | M26: =IF(AND(J26>=$B$2,J26<=$C$2),1,0) -> 1 | N26: Realizado | O26: 11 | P26: 372624 | Q26: =IFERROR((VLOOKUP(P26,Padrón[[Ficha]:[Nombre]],2,FALSE)),"-") -> JAIR DE JESUS CARRILLO CABELLO | S26: =IF(N26="Cancelado","◄ ◄ ◄ Favor de indicar la causa","-") -> - | U26: SSSTPA | V26: =COUNTIFS($L$14:$L$300,V$15,$C$14:$C$300,$U26,$N$14:$N$300,"Realizado") -> 0 | W26: =COUNTIFS($L$14:$L$300,W$15,$C$14:$C$300,$U26,$N$14:$N$300,"Realizado") -> 1 | X26: =COUNTIFS($L$14:$L$300,X$15,$C$14:$C$300,$U26,$N$14:$N$300,"Realizado") -> 3 | Y26: =COUNTIFS($L$14:$L$300,Y$15,$C$14:$C$300,$U26,$N$14:$N$300,"Realizado") -> 0 | Z26: =COUNTIFS($L$14:$L$300,Z$15,$C$14:$C$300,$U26,$N$14:$N$300,"Realizado") -> 2 | AA26: =COUNTIFS($L$14:$L$300,AA$15,$C$14:$C$300,$U26,$N$14:$N$300,"Realizado") -> 0 | AB26: =COUNTIFS($L$14:$L$300,AB$15,$C$14:$C$300,$U26,$N$14:$N$300,"Realizado") -> 0 | AC26: =COUNTIFS($L$14:$L$300,AC$15,$C$14:$C$300,$U26,$N$14:$N$300,"Realizado") -> 0 | ... AG26: =COUNTIFS($L$14:$L$300,AG$15,$C$14:$C$300,$U26,$N$14:$N$300,"Realizado") -> 0 | AH26: =SUM(V26:AG26) -> 6
A27: 48081 | C27: SPRN | D27: ACTIVO DE PRODUCCIÓN POZA RICA - ALTAMIRA | E27: PLANEACIÓN Y SUPERVISIÓN SEGURA DE LOS TRABAJOS (PSST) | F27: 372624 | G27: CARRILLO CABELLO JAIR DE JESUS | H27: 11 | I27: 45033 | J27: 45034 | K27: CERRO AZUL,VERACRUZ | L27: =MONTH(J27) -> 4 | M27: =IF(AND(J27>=$B$2,J27<=$C$2),1,0) -> 1 | N27: Realizado | O27: 10 | P27: 372624 | Q27: =IFERROR((VLOOKUP(P27,Padrón[[Ficha]:[Nombre]],2,FALSE)),"-") -> JAIR DE JESUS CARRILLO CABELLO | S27: =IF(N27="Cancelado","◄ ◄ ◄ Favor de indicar la causa","-") -> - | U27: Total | V27: =SUM(V16:V26) -> 0 | W27: =SUM(W16:W26) -> 4 | X27: =SUM(X16:X26) -> 7 | Y27: =SUM(Y16:Y26) -> 5 | Z27: =SUM(Z16:Z26) -> 5 | AA27: =SUM(AA16:AA26) -> 4 | AB27: =SUM(AB16:AB26) -> 2 | AC27: =SUM(AC16:AC26) -> 1 | ... AH27: =SUM(AH16:AH26) -> 33
A28: 48168 | C28: SPRN | D28: ACTIVO DE PRODUCCIÓN POZA RICA - ALTAMIRA | E28: REACREDITACIÓN DE SIGNATARIOS DEL SPPTR (RSPTR) | F28: 352720 | G28: ROSAS HERNANDEZ ROBERTO AUGUSTO | H28: 14 | I28: 45037 | J28: 45037 | K28: CERRO AZUL,VERACRUZ | L28: =MONTH(J28) -> 4 | M28: =IF(AND(J28>=$B$2,J28<=$C$2),1,0) -> 1 | N28: Realizado | O28: 7 | P28: 352720 | Q28: =IFERROR((VLOOKUP(P28,Padrón[[Ficha]:[Nombre]],2,FALSE)),"-") -> ROBERTO AUGUSTO ROSAS HERNANDEZ | S28: =IF(N28="Cancelado","◄ ◄ ◄ Favor de indicar la causa","-") -> -
A29: 56773 | C29: SPRN | D29: ACTIVO DE PRODUCCIÓN POZA RICA - ALTAMIRA | E29: ÁCIDO SULFHÍDRICO (H2S) | F29: 372624 | G29: CARRILLO CABELLO JAIR DE JESUS | H29: 10 | I29: 45041 | J29: 45041 | K29: CERRO AZUL,VERACRUZ | L29: =MONTH(J29) -> 4 | M29: =IF(AND(J29>=$B$2,J29<=$C$2),1,0) -> 1 | N29: Realizado | O29: 8 | P29: 372624 | Q29: =IFERROR((VLOOKUP(P29,Padrón[[Ficha]:[Nombre]],2,FALSE)),"-") -> JAIR DE JESUS CARRILLO CABELLO | S29: =IF(N29="Cancelado","◄ ◄ ◄ Favor de indicar la causa","-") -> - | U29: Cancelados | V29: 1 | W29: 2 | X29: 3 | Y29: 4 | Z29: 5 | AA29: 6 | AB29: 7 | AC29: 8 | AD29: 9 | AE29: 10 | AF29: 11 | AG29: 12 | AH29: Total
A30: 50326 | C30: SPRN | D30: GERENCIA DE MANTENIMIENTO, CONFIABILIDAD Y CONSTRUCCIÓN | E30: MANEJO A LA DEFENSIVA (MD) | F30: 372624 | G30: CARRILLO CABELLO JAIR DE JESUS | H30: 12 | I30: 45062 | J30: 45062 | K30: CERRO AZUL,VERACRUZ | L30: =MONTH(J30) -> 5 | M30: =IF(AND(J30>=$B$2,J30<=$C$2),1,0) -> 1 | N30: Realizado | O30: 11 | P30: 372624 | Q30: =IFERROR((VLOOKUP(P30,Padrón[[Ficha]:[Nombre]],2,FALSE)),"-") -> JAIR DE JESUS CARRILLO CABELLO | S30: =IF(N30="Cancelado","◄ ◄ ◄ Favor de indicar la causa","-") -> - | U30: SCOC | V30: =COUNTIFS($L$14:$L$300,V$15,$C$14:$C$300,$U30,$N$14:$N$300,"Cancelado") -> 0 | W30: =COUNTIFS($L$14:$L$300,W$15,$C$14:$C$300,$U30,$N$14:$N$300,"Cancelado") -> 0 | X30: =COUNTIFS($L$14:$L$300,X$15,$C$14:$C$300,$U30,$N$14:$N$300,"Cancelado") -> 0 | Y30: =COUNTIFS($L$14:$L$300,Y$15,$C$14:$C$300,$U30,$N$14:$N$300,"Cancelado") -> 0 | Z30: =COUNTIFS($L$14:$L$300,Z$15,$C$14:$C$300,$U30,$N$14:$N$300,"Cancelado") -> 0 | AA30: =COUNTIFS($L$14:$L$300,AA$15,$C$14:$C$300,$U30,$N$14:$N$300,"Cancelado") -> 0 | AB30: =COUNTIFS($L$14:$L$300,AB$15,$C$14:$C$300,$U30,$N$14:$N$300,"Cancelado") -> 0 | AC30: =COUNTIFS($L$14:$L$300,AC$15,$C$14:$C$300,$U30,$N$14:$N$300,"Cancelado") -> 0 | ... AG30: =COUNTIFS($L$14:$L$300,AG$15,$C$14:$C$300,$U30,$N$14:$N$300,"Cancelado") -> 0 | AH30: =SUM(V30:AG30) -> 0
A31: 52404 | C31: SSSTPA | D31: GERENCIA DE SEGURIDAD, SALUD EN EL TRABAJO Y PROTECCIÓN AMBIENTAL REGIÓN NORTE | E31: AUDITORÍAS EFECTIVAS (AE) | F31: 196853 | G31: DEL ANGEL DEL ANGEL JUSTO JESUS | H31: 7 | I31: 45063 | J31: 45063 | K31: CERRO AZUL,VERACRUZ | L31: =MONTH(J31) -> 5 | M31: =IF(AND(J31>=$B$2,J31<=$C$2),1,0) -> 1 | N31: Realizado | O31: 7 | P31: 331056 | Q31: =IFERROR((VLOOKUP(P31,Padrón[[Ficha]:[Nombre]],2,FALSE)),"-") -> JOSE MANUEL HERNANDEZ DE LEON | S31: =IF(N31="Cancelado","◄ ◄ ◄ Favor de indicar la causa","-") -> - | U31: SE | V31: =COUNTIFS($L$14:$L$300,V$15,$C$14:$C$300,$U31,$N$14:$N$300,"Cancelado") -> 0 | W31: =COUNTIFS($L$14:$L$300,W$15,$C$14:$C$300,$U31,$N$14:$N$300,"Cancelado") -> 0 | X31: =COUNTIFS($L$14:$L$300,X$15,$C$14:$C$300,$U31,$N$14:$N$300,"Cancelado") -> 0 | Y31: =COUNTIFS($L$14:$L$300,Y$15,$C$14:$C$300,$U31,$N$14:$N$300,"Cancelado") -> 0 | Z31: =COUNTIFS($L$14:$L$300,Z$15,$C$14:$C$300,$U31,$N$14:$N$300,"Cancelado") -> 0 | AA31: =COUNTIFS($L$14:$L$300,AA$15,$C$14:$C$300,$U31,$N$14:$N$300,"Cancelado") -> 0 | AB31: =COUNTIFS($L$14:$L$300,AB$15,$C$14:$C$300,$U31,$N$14:$N$300,"Cancelado") -> 0 | AC31: =COUNTIFS($L$14:$L$300,AC$15,$C$14:$C$300,$U31,$N$14:$N$300,"Cancelado") -> 0 | ... AG31: =COUNTIFS($L$14:$L$300,AG$15,$C$14:$C$300,$U31,$N$14:$N$300,"Cancelado") -> 0 | AH31: =SUM(V31:AG31) -> 0
A32: 55768 | C32: SPRN | D32: ACTIVO DE PRODUCCIÓN POZA RICA - ALTAMIRA | E32: SEGURIDAD EN CENTROS ADMINISTRATIVOS (SCA) | F32: 372624 | G32: CARRILLO CABELLO JAIR DE JESUS | H32: 18 | I32: 45064 | J32: 45064 | K32: CERRO AZUL,VERACRUZ | L32: =MONTH(J32) -> 5 | M32: =IF(AND(J32>=$B$2,J32<=$C$2),1,0) -> 1 | N32: Realizado | O32: 17 | P32: 372624 | Q32: =IFERROR((VLOOKUP(P32,Padrón[[Ficha]:[Nombre]],2,FALSE)),"-") -> JAIR DE JESUS CARRILLO CABELLO | S32: =IF(N32="Cancelado","◄ ◄ ◄ Favor de indicar la causa","-") -> - | U32: SEPCA | V32: =COUNTIFS($L$14:$L$300,V$15,$C$14:$C$300,$U32,$N$14:$N$300,"Cancelado") -> 0 | W32: =COUNTIFS($L$14:$L$300,W$15,$C$14:$C$300,$U32,$N$14:$N$300,"Cancelado") -> 0 | X32: =COUNTIFS($L$14:$L$300,X$15,$C$14:$C$300,$U32,$N$14:$N$300,"Cancelado") -> 0 | Y32: =COUNTIFS($L$14:$L$300,Y$15,$C$14:$C$300,$U32,$N$14:$N$300,"Cancelado") -> 0 | Z32: =COUNTIFS($L$14:$L$300,Z$15,$C$14:$C$300,$U32,$N$14:$N$300,"Cancelado") -> 0 | AA32: =COUNTIFS($L$14:$L$300,AA$15,$C$14:$C$300,$U32,$N$14:$N$300,"Cancelado") -> 0 | AB32: =COUNTIFS($L$14:$L$300,AB$15,$C$14:$C$300,$U32,$N$14:$N$300,"Cancelado") -> 0 | AC32: =COUNTIFS($L$14:$L$300,AC$15,$C$14:$C$300,$U32,$N$14:$N$300,"Cancelado") -> 0 | ... AG32: =COUNTIFS($L$14:$L$300,AG$15,$C$14:$C$300,$U32,$N$14:$N$300,"Cancelado") -> 0 | AH32: =SUM(V32:AG32) -> 0
A33: 48191 | C33: SPRN | D33: ACTIVO DE PRODUCCIÓN POZA RICA - ALTAMIRA | E33: PREVENCIÓN DE RIESGOS LABORALES (PRL) | F33: 352720 | G33: ROSAS HERNANDEZ ROBERTO AUGUSTO | H33: 17 | I33: 45075 | J33: 45076 | K33: CERRO AZUL,VERACRUZ | L33: =MONTH(J33) -> 5 | M33: =IF(AND(J33>=$B$2,J33<=$C$2),1,0) -> 1 | N33: Realizado | O33: 15 | P33: 352720 | Q33: =IFERROR((VLOOKUP(P33,Padrón[[Ficha]:[Nombre]],2,FALSE)),"-") -> ROBERTO AUGUSTO ROSAS HERNANDEZ | S33: =IF(N33="Cancelado","◄ ◄ ◄ Favor de indicar la causa","-") -> - | U33: SMLIC | V33: =COUNTIFS($L$14:$L$300,V$15,$C$14:$C$300,$U33,$N$14:$N$300,"Cancelado") -> 0 | W33: =COUNTIFS($L$14:$L$300,W$15,$C$14:$C$300,$U33,$N$14:$N$300,"Cancelado") -> 0 | X33: =COUNTIFS($L$14:$L$300,X$15,$C$14:$C$300,$U33,$N$14:$N$300,"Cancelado") -> 0 | Y33: =COUNTIFS($L$14:$L$300,Y$15,$C$14:$C$300,$U33,$N$14:$N$300,"Cancelado") -> 0 | Z33: =COUNTIFS($L$14:$L$300,Z$15,$C$14:$C$300,$U33,$N$14:$N$300,"Cancelado") -> 0 | AA33: =COUNTIFS($L$14:$L$300,AA$15,$C$14:$C$300,$U33,$N$14:$N$300,"Cancelado") -> 0 | AB33: =COUNTIFS($L$14:$L$300,AB$15,$C$14:$C$300,$U33,$N$14:$N$300,"Cancelado") -> 0 | AC33: =COUNTIFS($L$14:$L$300,AC$15,$C$14:$C$300,$U33,$N$14:$N$300,"Cancelado") -> 0 | ... AG33: =COUNTIFS($L$14:$L$300,AG$15,$C$14:$C$300,$U33,$N$14:$N$300,"Cancelado") -> 0 | AH33: =SUM(V33:AG33) -> 0
A34: 51840 | C34: SSSTPA | D34: GERENCIA DE SEGURIDAD, SALUD EN EL TRABAJO Y PROTECCIÓN AMBIENTAL REGIÓN NORTE | E34: DISCIPLINA OPERATIVA (DO) | F34: 372624 | G34: CARRILLO CABELLO JAIR DE JESUS | H34: 12 | I34: 45076 | J34: 45077 | K34: CERRO AZUL,VERACRUZ | L34: =MONTH(J34) -> 5 | M34: =IF(AND(J34>=$B$2,J34<=$C$2),1,0) -> 1 | N34: Realizado | O34: 12 | P34: 372624 | Q34: =IFERROR((VLOOKUP(P34,Padrón[[Ficha]:[Nombre]],2,FALSE)),"-") -> JAIR DE JESUS CARRILLO CABELLO | S34: =IF(N34="Cancelado","◄ ◄ ◄ Favor de indicar la causa","-") -> - | U34: SPEE | V34: =COUNTIFS($L$14:$L$300,V$15,$C$14:$C$300,$U34,$N$14:$N$300,"Cancelado") -> 0 | W34: =COUNTIFS($L$14:$L$300,W$15,$C$14:$C$300,$U34,$N$14:$N$300,"Cancelado") -> 0 | X34: =COUNTIFS($L$14:$L$300,X$15,$C$14:$C$300,$U34,$N$14:$N$300,"Cancelado") -> 0 | Y34: =COUNTIFS($L$14:$L$300,Y$15,$C$14:$C$300,$U34,$N$14:$N$300,"Cancelado") -> 0 | Z34: =COUNTIFS($L$14:$L$300,Z$15,$C$14:$C$300,$U34,$N$14:$N$300,"Cancelado") -> 0 | AA34: =COUNTIFS($L$14:$L$300,AA$15,$C$14:$C$300,$U34,$N$14:$N$300,"Cancelado") -> 0 | AB34: =COUNTIFS($L$14:$L$300,AB$15,$C$14:$C$300,$U34,$N$14:$N$300,"Cancelado") -> 0 | AC34: =COUNTIFS($L$14:$L$300,AC$15,$C$14:$C$300,$U34,$N$14:$N$300,"Cancelado") -> 0 | ... AG34: =COUNTIFS($L$14:$L$300,AG$15,$C$14:$C$300,$U34,$N$14:$N$300,"Cancelado") -> 0 | AH34: =SUM(V34:AG34) -> 0
A35: 49491 | C35: SPRN | D35: GERENCIA DE MANTENIMIENTO, CONFIABILIDAD Y CONSTRUCCIÓN | E35: PREVENCIÓN DE RIESGOS LABORALES (PRL) | F35: 372624 | G35: CARRILLO CABELLO JAIR DE JESUS | H35: 14 | I35: 45082 | J35: 45083 | K35: CERRO AZUL,VERACRUZ | L35: =MONTH(J35) -> 6 | M35: =IF(AND(J35>=$B$2,J35<=$C$2),1,0) -> 1 | N35: Realizado | O35: 13 | P35: 372624 | Q35: =IFERROR((VLOOKUP(P35,Padrón[[Ficha]:[Nombre]],2,FALSE)),"-") -> JAIR DE JESUS CARRILLO CABELLO | S35: =IF(N35="Cancelado","◄ ◄ ◄ Favor de indicar la causa","-") -> - | U35: SPMP | V35: =COUNTIFS($L$14:$L$300,V$15,$C$14:$C$300,$U35,$N$14:$N$300,"Cancelado") -> 0 | W35: =COUNTIFS($L$14:$L$300,W$15,$C$14:$C$300,$U35,$N$14:$N$300,"Cancelado") -> 0 | X35: =COUNTIFS($L$14:$L$300,X$15,$C$14:$C$300,$U35,$N$14:$N$300,"Cancelado") -> 0 | Y35: =COUNTIFS($L$14:$L$300,Y$15,$C$14:$C$300,$U35,$N$14:$N$300,"Cancelado") -> 0 | Z35: =COUNTIFS($L$14:$L$300,Z$15,$C$14:$C$300,$U35,$N$14:$N$300,"Cancelado") -> 0 | AA35: =COUNTIFS($L$14:$L$300,AA$15,$C$14:$C$300,$U35,$N$14:$N$300,"Cancelado") -> 0 | AB35: =COUNTIFS($L$14:$L$300,AB$15,$C$14:$C$300,$U35,$N$14:$N$300,"Cancelado") -> 0 | AC35: =COUNTIFS($L$14:$L$300,AC$15,$C$14:$C$300,$U35,$N$14:$N$300,"Cancelado") -> 0 | ... AG35: =COUNTIFS($L$14:$L$300,AG$15,$C$14:$C$300,$U35,$N$14:$N$300,"Cancelado") -> 0 | AH35: =SUM(V35:AG35) -> 0
A36: 55782 | C36: SPRN | D36: ACTIVO DE PRODUCCIÓN POZA RICA - ALTAMIRA | E36: SEGURIDAD EN CENTROS ADMINISTRATIVOS (SCA) | F36: 372624 | G36: CARRILLO CABELLO JAIR DE JESUS | H36: 18 | I36: 45091 | J36: 45091 | K36: CERRO AZUL,VERACRUZ | L36: =MONTH(J36) -> 6 | M36: =IF(AND(J36>=$B$2,J36<=$C$2),1,0) -> 1 | N36: Realizado | O36: 13 | P36: 372624 | Q36: =IFERROR((VLOOKUP(P36,Padrón[[Ficha]:[Nombre]],2,FALSE)),"-") -> JAIR DE JESUS CARRILLO CABELLO | S36: =IF(N36="Cancelado","◄ ◄ ◄ Favor de indicar la causa","-") -> - | U36: SPRMNE | V36: =COUNTIFS($L$14:$L$300,V$15,$C$14:$C$300,$U36,$N$14:$N$300,"Cancelado") -> 0 | W36: =COUNTIFS($L$14:$L$300,W$15,$C$14:$C$300,$U36,$N$14:$N$300,"Cancelado") -> 0 | X36: =COUNTIFS($L$14:$L$300,X$15,$C$14:$C$300,$U36,$N$14:$N$300,"Cancelado") -> 0 | Y36: =COUNTIFS($L$14:$L$300,Y$15,$C$14:$C$300,$U36,$N$14:$N$300,"Cancelado") -> 0 | Z36: =COUNTIFS($L$14:$L$300,Z$15,$C$14:$C$300,$U36,$N$14:$N$300,"Cancelado") -> 0 | AA36: =COUNTIFS($L$14:$L$300,AA$15,$C$14:$C$300,$U36,$N$14:$N$300,"Cancelado") -> 0 | AB36: =COUNTIFS($L$14:$L$300,AB$15,$C$14:$C$300,$U36,$N$14:$N$300,"Cancelado") -> 0 | AC36: =COUNTIFS($L$14:$L$300,AC$15,$C$14:$C$300,$U36,$N$14:$N$300,"Cancelado") -> 0 | ... AG36: =COUNTIFS($L$14:$L$300,AG$15,$C$14:$C$300,$U36,$N$14:$N$300,"Cancelado") -> 0 | AH36: =SUM(V36:AG36) -> 0
A37: 50613 | C37: SPRN | D37: GERENCIA DE MANTENIMIENTO, CONFIABILIDAD Y CONSTRUCCIÓN | E37: DISCIPLINA OPERATIVA (DO) | F37: 196853 | G37: DEL ANGEL DEL ANGEL JUSTO JESUS | H37: 11 | I37: 45091 | J37: 45092 | K37: CERRO AZUL,VERACRUZ | L37: =MONTH(J37) -> 6 | M37: =IF(AND(J37>=$B$2,J37<=$C$2),1,0) -> 1 | N37: Realizado | O37: 9 | P37: 196853 | Q37: =IFERROR((VLOOKUP(P37,Padrón[[Ficha]:[Nombre]],2,FALSE)),"-") -> JUSTO JESUS DEL ANGEL DEL ANGEL | R37: REPROGRAMADO PARA EL 22 DE JUNIO DEL 2023 | S37: =IF(N37="Cancelado","◄ ◄ ◄ Favor de indicar la causa","-") -> - | U37: SPRMSO | V37: =COUNTIFS($L$14:$L$300,V$15,$C$14:$C$300,$U37,$N$14:$N$300,"Cancelado") -> 0 | W37: =COUNTIFS($L$14:$L$300,W$15,$C$14:$C$300,$U37,$N$14:$N$300,"Cancelado") -> 0 | X37: =COUNTIFS($L$14:$L$300,X$15,$C$14:$C$300,$U37,$N$14:$N$300,"Cancelado") -> 0 | Y37: =COUNTIFS($L$14:$L$300,Y$15,$C$14:$C$300,$U37,$N$14:$N$300,"Cancelado") -> 0 | Z37: =COUNTIFS($L$14:$L$300,Z$15,$C$14:$C$300,$U37,$N$14:$N$300,"Cancelado") -> 0 | AA37: =COUNTIFS($L$14:$L$300,AA$15,$C$14:$C$300,$U37,$N$14:$N$300,"Cancelado") -> 0 | AB37: =COUNTIFS($L$14:$L$300,AB$15,$C$14:$C$300,$U37,$N$14:$N$300,"Cancelado") -> 0 | AC37: =COUNTIFS($L$14:$L$300,AC$15,$C$14:$C$300,$U37,$N$14:$N$300,"Cancelado") -> 0 | ... AG37: =COUNTIFS($L$14:$L$300,AG$15,$C$14:$C$300,$U37,$N$14:$N$300,"Cancelado") -> 0 | AH37: =SUM(V37:AG37) -> 0
A38: 55762 | C38: SPRN | D38: ACTIVO DE PRODUCCIÓN POZA RICA - ALTAMIRA | E38: REVALIDACIÓN BÁSICO DE SEGURIDAD (BS) | F38: 196853 | G38: DEL ANGEL DEL ANGEL JUSTO JESUS | H38: 16 | I38: 45093 | J38: 45093 | K38: CERRO AZUL,VERACRUZ | L38: =MONTH(J38) -> 6 | M38: =IF(AND(J38>=$B$2,J38<=$C$2),1,0) -> 1 | N38: Realizado | O38: 12 | P38: 196853 | Q38: =IFERROR((VLOOKUP(P38,Padrón[[Ficha]:[Nombre]],2,FALSE)),"-") -> JUSTO JESUS DEL ANGEL DEL ANGEL | R38: REPROGRAMADO PARA EL 28 DE JUNIO DEL 2023 | S38: =IF(N38="Cancelado","◄ ◄ ◄ Favor de indicar la causa","-") -> - | U38: SPRN | V38: =COUNTIFS($L$14:$L$300,V$15,$C$14:$C$300,$U38,$N$14:$N$300,"Cancelado") -> 0 | W38: =COUNTIFS($L$14:$L$300,W$15,$C$14:$C$300,$U38,$N$14:$N$300,"Cancelado") -> 0 | X38: =COUNTIFS($L$14:$L$300,X$15,$C$14:$C$300,$U38,$N$14:$N$300,"Cancelado") -> 0 | Y38: =COUNTIFS($L$14:$L$300,Y$15,$C$14:$C$300,$U38,$N$14:$N$300,"Cancelado") -> 0 | Z38: =COUNTIFS($L$14:$L$300,Z$15,$C$14:$C$300,$U38,$N$14:$N$300,"Cancelado") -> 0 | AA38: =COUNTIFS($L$14:$L$300,AA$15,$C$14:$C$300,$U38,$N$14:$N$300,"Cancelado") -> 0 | AB38: =COUNTIFS($L$14:$L$300,AB$15,$C$14:$C$300,$U38,$N$14:$N$300,"Cancelado") -> 0 | AC38: =COUNTIFS($L$14:$L$300,AC$15,$C$14:$C$300,$U38,$N$14:$N$300,"Cancelado") -> 0 | ... AG38: =COUNTIFS($L$14:$L$300,AG$15,$C$14:$C$300,$U38,$N$14:$N$300,"Cancelado") -> 0 | AH38: =SUM(V38:AG38) -> 0
A39: 56291 | C39: SPRN | D39: ACTIVO DE PRODUCCIÓN POZA RICA - ALTAMIRA | E39: PREVENCIÓN DE RIESGOS LABORALES (PRL) | F39: 196853 | G39: DEL ANGEL DEL ANGEL JUSTO JESUS | H39: 18 | I39: 45125 | J39: 45126 | K39: CERRO AZUL,VERACRUZ | L39: =MONTH(J39) -> 7 | M39: =IF(AND(J39>=$B$2,J39<=$C$2),1,0) -> 1 | N39: Realizado | O39: 12 | P39: 196853 | Q39: =IFERROR((VLOOKUP(P39,Padrón[[Ficha]:[Nombre]],2,FALSE)),"-") -> JUSTO JESUS DEL ANGEL DEL ANGEL | S39: =IF(N39="Cancelado","◄ ◄ ◄ Favor de indicar la causa","-") -> - | U39: SPRS | V39: =COUNTIFS($L$14:$L$300,V$15,$C$14:$C$300,$U39,$N$14:$N$300,"Cancelado") -> 0 | W39: =COUNTIFS($L$14:$L$300,W$15,$C$14:$C$300,$U39,$N$14:$N$300,"Cancelado") -> 0 | X39: =COUNTIFS($L$14:$L$300,X$15,$C$14:$C$300,$U39,$N$14:$N$300,"Cancelado") -> 0 | Y39: =COUNTIFS($L$14:$L$300,Y$15,$C$14:$C$300,$U39,$N$14:$N$300,"Cancelado") -> 0 | Z39: =COUNTIFS($L$14:$L$300,Z$15,$C$14:$C$300,$U39,$N$14:$N$300,"Cancelado") -> 0 | AA39: =COUNTIFS($L$14:$L$300,AA$15,$C$14:$C$300,$U39,$N$14:$N$300,"Cancelado") -> 0 | AB39: =COUNTIFS($L$14:$L$300,AB$15,$C$14:$C$300,$U39,$N$14:$N$300,"Cancelado") -> 0 | AC39: =COUNTIFS($L$14:$L$300,AC$15,$C$14:$C$300,$U39,$N$14:$N$300,"Cancelado") -> 0 | ... AG39: =COUNTIFS($L$14:$L$300,AG$15,$C$14:$C$300,$U39,$N$14:$N$300,"Cancelado") -> 0 | AH39: =SUM(V39:AG39) -> 0
A40: 56340 | C40: SPRN | D40: ACTIVO DE PRODUCCIÓN POZA RICA - ALTAMIRA | E40: SISTEMA DE PERMISOS PARA TRABAJOS CON RIESGO (SPTR) | F40: 352720 | G40: ROSAS HERNANDEZ ROBERTO AUGUSTO | H40: 15 | I40: 45132 | J40: 45134 | K40: CERRO AZUL,VERACRUZ | L40: =MONTH(J40) -> 7 | M40: =IF(AND(J40>=$B$2,J40<=$C$2),1,0) -> 1 | N40: Realizado | O40: 11 | P40: 352720 | Q40: =IFERROR((VLOOKUP(P40,Padrón[[Ficha]:[Nombre]],2,FALSE)),"-") -> ROBERTO AUGUSTO ROSAS HERNANDEZ | S40: =IF(N40="Cancelado","◄ ◄ ◄ Favor de indicar la causa","-") -> - | U40: SSSTPA | V40: =COUNTIFS($L$14:$L$300,V$15,$C$14:$C$300,$U40,$N$14:$N$300,"Cancelado") -> 0 | W40: =COUNTIFS($L$14:$L$300,W$15,$C$14:$C$300,$U40,$N$14:$N$300,"Cancelado") -> 0 | X40: =COUNTIFS($L$14:$L$300,X$15,$C$14:$C$300,$U40,$N$14:$N$300,"Cancelado") -> 0 | Y40: =COUNTIFS($L$14:$L$300,Y$15,$C$14:$C$300,$U40,$N$14:$N$300,"Cancelado") -> 0 | Z40: =COUNTIFS($L$14:$L$300,Z$15,$C$14:$C$300,$U40,$N$14:$N$300,"Cancelado") -> 0 | AA40: =COUNTIFS($L$14:$L$300,AA$15,$C$14:$C$300,$U40,$N$14:$N$300,"Cancelado") -> 0 | AB40: =COUNTIFS($L$14:$L$300,AB$15,$C$14:$C$300,$U40,$N$14:$N$300,"Cancelado") -> 0 | AC40: =COUNTIFS($L$14:$L$300,AC$15,$C$14:$C$300,$U40,$N$14:$N$300,"Cancelado") -> 0 | ... AG40: =COUNTIFS($L$14:$L$300,AG$15,$C$14:$C$300,$U40,$N$14:$N$300,"Cancelado") -> 0 | AH40: =SUM(V40:AG40) -> 0
A41: 56317 | C41: SPRN | D41: ACTIVO DE PRODUCCIÓN POZA RICA - ALTAMIRA | E41: SISTEMA DE PERMISOS PARA TRABAJOS CON RIESGO (SPTR) | F41: 352720 | G41: ROSAS HERNANDEZ ROBERTO AUGUSTO | H41: 14 | I41: 45167 | J41: 45169 | K41: CERRO AZUL,VERACRUZ | L41: =MONTH(J41) -> 8 | M41: =IF(AND(J41>=$B$2,J41<=$C$2),1,0) -> 1 | N41: Realizado | O41: 13 | P41: 352720 | Q41: =IFERROR((VLOOKUP(P41,Padrón[[Ficha]:[Nombre]],2,FALSE)),"-") -> ROBERTO AUGUSTO ROSAS HERNANDEZ | S41: =IF(N41="Cancelado","◄ ◄ ◄ Favor de indicar la causa","-") -> - | U41: Total | V41: =SUM(V30:V40) -> 0 | W41: =SUM(W30:W40) -> 0 | X41: =SUM(X30:X40) -> 0 | Y41: =SUM(Y30:Y40) -> 0 | Z41: =SUM(Z30:Z40) -> 0 | AA41: =SUM(AA30:AA40) -> 0 | AB41: =SUM(AB30:AB40) -> 0 | AC41: =SUM(AC30:AC40) -> 0 | ... AH41: =SUM(AH30:AH40) -> 0
A42: 49456 | C42: SMLIC | D42: GERENCIA DE SERVICIOS DE LOGÍSTICA TERRESTRE | E42: BÁSICO DE SEGURIDAD (BS) | F42: 372624 | G42: CARRILLO CABELLO JAIR DE JESUS | H42: 11 | I42: 45174 | J42: 45175 | K42: CERRO AZUL,VERACRUZ | L42: =MONTH(J42) -> 9 | M42: =IF(AND(J42>=$B$2,J42<=$C$2),1,0) -> 1 | N42: Realizado | O42: 12 | P42: 372624 | Q42: =IFERROR((VLOOKUP(P42,Padrón[[Ficha]:[Nombre]],2,FALSE)),"-") -> JAIR DE JESUS CARRILLO CABELLO | S42: =IF(N42="Cancelado","◄ ◄ ◄ Favor de indicar la causa","-") -> -
A43: 49641 | C43: SPRN | D43: ACTIVO DE PRODUCCIÓN POZA RICA - ALTAMIRA | E43: LIDERAZGO EN SSPA | F43: 449433 | G43: MORAL JORDAN GONZALO | H43: 15 | I43: 45183 | J43: 45184 | K43: CERRO AZUL,VERACRUZ | L43: =MONTH(J43) -> 9 | M43: =IF(AND(J43>=$B$2,J43<=$C$2),1,0) -> 1 | N43: Realizado | O43: 15 | P43: 352720 | Q43: =IFERROR((VLOOKUP(P43,Padrón[[Ficha]:[Nombre]],2,FALSE)),"-") -> ROBERTO AUGUSTO ROSAS HERNANDEZ | R43: REEPROGRAMADO PARA EL 21 Y 22 DE SEPTIEMBRE DEL 2023 | S43: =IF(N43="Cancelado","◄ ◄ ◄ Favor de indicar la causa","-") -> -
A44: 56236 | C44: SPRN | D44: ACTIVO DE PRODUCCIÓN POZA RICA - ALTAMIRA | E44: VERIFICADOR DE GAS (VG) | F44: 352720 | G44: ROSAS HERNANDEZ ROBERTO AUGUSTO | H44: 18 | I44: 45196 | J44: 45196 | K44: CERRO AZUL,VERACRUZ | L44: =MONTH(J44) -> 9 | M44: =IF(AND(J44>=$B$2,J44<=$C$2),1,0) -> 1 | N44: Realizado | O44: 12 | P44: 352720 | Q44: =IFERROR((VLOOKUP(P44,Padrón[[Ficha]:[Nombre]],2,FALSE)),"-") -> ROBERTO AUGUSTO ROSAS HERNANDEZ | S44: =IF(N44="Cancelado","◄ ◄ ◄ Favor de indicar la causa","-") -> -
A45: 56262 | C45: SPRN | D45: ACTIVO DE PRODUCCIÓN POZA RICA - ALTAMIRA | E45: PREVENCIÓN DE RIESGOS LABORALES (PRL) | F45: 196853 | G45: DEL ANGEL DEL ANGEL JUSTO JESUS | H45: 18 | I45: 45218 | J45: 45219 | K45: CERRO AZUL,VERACRUZ | L45: =MONTH(J45) -> 10 | M45: =IF(AND(J45>=$B$2,J45<=$C$2),1,0) -> 1 | N45: Realizado | O45: 3 | P45: 196853 | Q45: =IFERROR((VLOOKUP(P45,Padrón[[Ficha]:[Nombre]],2,FALSE)),"-") -> JUSTO JESUS DEL ANGEL DEL ANGEL | S45: =IF(N45="Cancelado","◄ ◄ ◄ Favor de indicar la causa","-") -> -
A46: 56328 | C46: SPRN | D46: ACTIVO DE PRODUCCIÓN POZA RICA - ALTAMIRA | E46: SISTEMA DE PERMISOS PARA TRABAJOS CON RIESGO (SPTR) | F46: 352720 | G46: ROSAS HERNANDEZ ROBERTO AUGUSTO | H46: 16 | I46: 45258 | J46: 45260 | K46: CERRO AZUL,VERACRUZ | L46: =MONTH(J46) -> 11 | M46: =IF(AND(J46>=$B$2,J46<=$C$2),1,0) -> 1 | N46: Realizado | O46: 12 | P46: 196853 | Q46: =IFERROR((VLOOKUP(P46,Padrón[[Ficha]:[Nombre]],2,FALSE)),"-") -> JUSTO JESUS DEL ANGEL DEL ANGEL | S46: =IF(N46="Cancelado","◄ ◄ ◄ Favor de indicar la causa","-") -> -
M47: =IF(AND(J47>=$B$2,J47<=$C$2),1,0) -> 0 | Q47: =IFERROR((VLOOKUP(P47,Padrón[[Ficha]:[Nombre]],2,FALSE)),"-") -> -
M48: =IF(AND(J48>=$B$2,J48<=$C$2),1,0) -> 0 | Q48: =IFERROR((VLOOKUP(P48,Padrón[[Ficha]:[Nombre]],2,FALSE)),"-") -> -
M49: =IF(AND(J49>=$B$2,J49<=$C$2),1,0) -> 0 | Q49: =IFERROR((VLOOKUP(P49,Padrón[[Ficha]:[Nombre]],2,FALSE)),"-") -> -
M50: =IF(AND(J50>=$B$2,J50<=$C$2),1,0) -> 0 | Q50: =IFERROR((VLOOKUP(P50,Padrón[[Ficha]:[Nombre]],2,FALSE)),"-") -> -
M51: =IF(AND(J51>=$B$2,J51<=$C$2),1,0) -> 0 | Q51: =IFERROR((VLOOKUP(P51,Padrón[[Ficha]:[Nombre]],2,FALSE)),"-") -> -
M52: =IF(AND(J52>=$B$2,J52<=$C$2),1,0) -> 0 | Q52: =IFERROR((VLOOKUP(P52,Padrón[[Ficha]:[Nombre]],2,FALSE)),"-") -> -
M53: =IF(AND(J53>=$B$2,J53<=$C$2),1,0) -> 0 | Q53: =IFERROR((VLOOKUP(P53,Padrón[[Ficha]:[Nombre]],2,FALSE)),"-") -> -
M54: =IF(AND(J54>=$B$2,J54<=$C$2),1,0) -> 0 | Q54: =IFERROR((VLOOKUP(P54,Padrón[[Ficha]:[Nombre]],2,FALSE)),"-") -> -
M55: =IF(AND(J55>=$B$2,J55<=$C$2),1,0) -> 0 | Q55: =IFERROR((VLOOKUP(P55,Padrón[[Ficha]:[Nombre]],2,FALSE)),"-") -> -
M56: =IF(AND(J56>=$B$2,J56<=$C$2),1,0) -> 0 | Q56: =IFERROR((VLOOKUP(P56,Padrón[[Ficha]:[Nombre]],2,FALSE)),"-") -> -
M57: =IF(AND(J57>=$B$2,J57<=$C$2),1,0) -> 0 | Q57: =IFERROR((VLOOKUP(P57,Padrón[[Ficha]:[Nombre]],2,FALSE)),"-") -> -
M58: =IF(AND(J58>=$B$2,J58<=$C$2),1,0) -> 0 | Q58: =IFERROR((VLOOKUP(P58,Padrón[[Ficha]:[Nombre]],2,FALSE)),"-") -> -
... M68: =IF(AND(J68>=$B$2,J68<=$C$2),1,0) -> 0 | Q68: =IFERROR((VLOOKUP(P68,Padrón[[Ficha]:[Nombre]],2,FALSE)),"-") -> -
Q69: =IFERROR((VLOOKUP(P69,Padrón[[Ficha]:[Nombre]],2,FALSE)),"-") -> -
Q70: =IFERROR((VLOOKUP(P70,Padrón[[Ficha]:[Nombre]],2,FALSE)),"-") -> -
Q71: =IFERROR((VLOOKUP(P71,Padrón[[Ficha]:[Nombre]],2,FALSE)),"-") -> -
Q72: =IFERROR((VLOOKUP(P72,Padrón[[Ficha]:[Nombre]],2,FALSE)),"-") -> -
Q73: =IFERROR((VLOOKUP(P73,Padrón[[Ficha]:[Nombre]],2,FALSE)),"-") -> -
Q74: =IFERROR((VLOOKUP(P74,Padrón[[Ficha]:[Nombre]],2,FALSE)),"-") -> -
Q75: =IFERROR((VLOOKUP(P75,Padrón[[Ficha]:[Nombre]],2,FALSE)),"-") -> -
Q76: =IFERROR((VLOOKUP(P76,Padrón[[Ficha]:[Nombre]],2,FALSE)),"-") -> -
Q77: =IFERROR((VLOOKUP(P77,Padrón[[Ficha]:[Nombre]],2,FALSE)),"-") -> -
Q78: =IFERROR((VLOOKUP(P78,Padrón[[Ficha]:[Nombre]],2,FALSE)),"-") -> -
Q79: =IFERROR((VLOOKUP(P79,Padrón[[Ficha]:[Nombre]],2,FALSE)),"-") -> -
Q80: =IFERROR((VLOOKUP(P80,Padrón[[Ficha]:[Nombre]],2,FALSE)),"-") -> -
... Q160: =IFERROR((VLOOKUP(P160,Padrón[[Ficha]:[Nombre]],2,FALSE)),"-") -> -

Sheet Altamira
B1: Fecha inicial | C1: Fecha final | U1: Programa | V1: 1 | W1: 2 | X1: 3 | Y1: 4 | Z1: 5 | AA1: 6 | AB1: 7 | AC1: 8 | AD1: 9 | AE1: 10 | AF1: 11 | AG1: 12 | AH1: Total
B2: =Seguimiento!$E$6 -> 44927 | C2: =Seguimiento!$J$6 -> 45291 | U2: SCOC | V2: =COUNTIFS($L$14:$L$300,V$1,$C$14:$C$300,$U2) -> 0 | W2: =COUNTIFS($L$14:$L$300,W$1,$C$14:$C$300,$U2) -> 0 | X2: =COUNTIFS($L$14:$L$300,X$1,$C$14:$C$300,$U2) -> 0 | Y2: =COUNTIFS($L$14:$L$300,Y$1,$C$14:$C$300,$U2) -> 0 | Z2: =COUNTIFS($L$14:$L$300,Z$1,$C$14:$C$300,$U2) -> 0 | AA2: =COUNTIFS($L$14:$L$300,AA$1,$C$14:$C$300,$U2) -> 0 | AB2: =COUNTIFS($L$14:$L$300,AB$1,$C$14:$C$300,$U2) -> 0 | AC2: =COUNTIFS($L$14:$L$300,AC$1,$C$14:$C$300,$U2) -> 0 | ... AG2: =COUNTIFS($L$14:$L$300,AG$1,$C$14:$C$300,$U2) -> 0 | AH2: =SUM(V2:AG2) -> 0
H3: PICADE | U3: SE | V3: =COUNTIFS($L$14:$L$300,V$1,$C$14:$C$300,$U3) -> 0 | W3: =COUNTIFS($L$14:$L$300,W$1,$C$14:$C$300,$U3) -> 0 | X3: =COUNTIFS($L$14:$L$300,X$1,$C$14:$C$300,$U3) -> 0 | Y3: =COUNTIFS($L$14:$L$300,Y$1,$C$14:$C$300,$U3) -> 0 | Z3: =COUNTIFS($L$14:$L$300,Z$1,$C$14:$C$300,$U3) -> 0 | AA3: =COUNTIFS($L$14:$L$300,AA$1,$C$14:$C$300,$U3) -> 0 | AB3: =COUNTIFS($L$14:$L$300,AB$1,$C$14:$C$300,$U3) -> 0 | AC3: =COUNTIFS($L$14:$L$300,AC$1,$C$14:$C$300,$U3) -> 0 | ... AG3: =COUNTIFS($L$14:$L$300,AG$1,$C$14:$C$300,$U3) -> 0 | AH3: =SUM(V3:AG3) -> 0
H4: Cursos | I4: Capacitandos | J4: Programados | K4: Realizados en prog. | L4: Cancelados | N4: Capacitandos programados | O4: Capacitandos | U4: SEPCA | V4: =COUNTIFS($L$14:$L$300,V$1,$C$14:$C$300,$U4) -> 0 | W4: =COUNTIFS($L$14:$L$300,W$1,$C$14:$C$300,$U4) -> 0 | X4: =COUNTIFS($L$14:$L$300,X$1,$C$14:$C$300,$U4) -> 0 | Y4: =COUNTIFS($L$14:$L$300,Y$1,$C$14:$C$300,$U4) -> 0 | Z4: =COUNTIFS($L$14:$L$300,Z$1,$C$14:$C$300,$U4) -> 0 | AA4: =COUNTIFS($L$14:$L$300,AA$1,$C$14:$C$300,$U4) -> 0 | AB4: =COUNTIFS($L$14:$L$300,AB$1,$C$14:$C$300,$U4) -> 0 | AC4: =COUNTIFS($L$14:$L$300,AC$1,$C$14:$C$300,$U4) -> 0 | ... AG4: =COUNTIFS($L$14:$L$300,AG$1,$C$14:$C$300,$U4) -> 0 | AH4: =SUM(V4:AG4) -> 0
H5: =COUNT(A14:A300) -> 55 | I5: =SUM(H14:H300) -> 635 | J5: =COUNTIF($M$14:$M$300,1) -> 55 | K5: =COUNTIFS($M$14:$M$300,1,$N$14:$N$300,"Realizado") -> 55 | L5: =COUNTIFS($M$14:$M$300,1,$N$14:$N$300,"Cancelado") -> 0 | N5: =+SUMIF($M$14:$M$300,1,$H$14:$H$300) -> 635 | O5: =+SUMIF($M$14:$M$300,1,$O$14:$O$300) -> 546 | U5: SMLIC | V5: =COUNTIFS($L$14:$L$300,V$1,$C$14:$C$300,$U5) -> 0 | W5: =COUNTIFS($L$14:$L$300,W$1,$C$14:$C$300,$U5) -> 0 | X5: =COUNTIFS($L$14:$L$300,X$1,$C$14:$C$300,$U5) -> 0 | Y5: =COUNTIFS($L$14:$L$300,Y$1,$C$14:$C$300,$U5) -> 0 | Z5: =COUNTIFS($L$14:$L$300,Z$1,$C$14:$C$300,$U5) -> 3 | AA5: =COUNTIFS($L$14:$L$300,AA$1,$C$14:$C$300,$U5) -> 3 | AB5: =COUNTIFS($L$14:$L$300,AB$1,$C$14:$C$300,$U5) -> 1 | AC5: =COUNTIFS($L$14:$L$300,AC$1,$C$14:$C$300,$U5) -> 0 | ... AG5: =COUNTIFS($L$14:$L$300,AG$1,$C$14:$C$300,$U5) -> 0 | AH5: =SUM(V5:AG5) -> 9
U6: SPEE | V6: =COUNTIFS($L$14:$L$300,V$1,$C$14:$C$300,$U6) -> 0 | W6: =COUNTIFS($L$14:$L$300,W$1,$C$14:$C$300,$U6) -> 0 | X6: =COUNTIFS($L$14:$L$300,X$1,$C$14:$C$300,$U6) -> 0 | Y6: =COUNTIFS($L$14:$L$300,Y$1,$C$14:$C$300,$U6) -> 0 | Z6: =COUNTIFS($L$14:$L$300,Z$1,$C$14:$C$300,$U6) -> 0 | AA6: =COUNTIFS($L$14:$L$300,AA$1,$C$14:$C$300,$U6) -> 0 | AB6: =COUNTIFS($L$14:$L$300,AB$1,$C$14:$C$300,$U6) -> 0 | AC6: =COUNTIFS($L$14:$L$300,AC$1,$C$14:$C$300,$U6) -> 0 | ... AG6: =COUNTIFS($L$14:$L$300,AG$1,$C$14:$C$300,$U6) -> 0 | AH6: =SUM(V6:AG6) -> 0
U7: SPMP | V7: =COUNTIFS($L$14:$L$300,V$1,$C$14:$C$300,$U7) -> 0 | W7: =COUNTIFS($L$14:$L$300,W$1,$C$14:$C$300,$U7) -> 0 | X7: =COUNTIFS($L$14:$L$300,X$1,$C$14:$C$300,$U7) -> 0 | Y7: =COUNTIFS($L$14:$L$300,Y$1,$C$14:$C$300,$U7) -> 0 | Z7: =COUNTIFS($L$14:$L$300,Z$1,$C$14:$C$300,$U7) -> 0 | AA7: =COUNTIFS($L$14:$L$300,AA$1,$C$14:$C$300,$U7) -> 0 | AB7: =COUNTIFS($L$14:$L$300,AB$1,$C$14:$C$300,$U7) -> 0 | AC7: =COUNTIFS($L$14:$L$300,AC$1,$C$14:$C$300,$U7) -> 0 | ... AG7: =COUNTIFS($L$14:$L$300,AG$1,$C$14:$C$300,$U7) -> 0 | AH7: =SUM(V7:AG7) -> 0
U8: SPRMNE | V8: =COUNTIFS($L$14:$L$300,V$1,$C$14:$C$300,$U8) -> 0 | W8: =COUNTIFS($L$14:$L$300,W$1,$C$14:$C$300,$U8) -> 0 | X8: =COUNTIFS($L$14:$L$300,X$1,$C$14:$C$300,$U8) -> 0 | Y8: =COUNTIFS($L$14:$L$300,Y$1,$C$14:$C$300,$U8) -> 0 | Z8: =COUNTIFS($L$14:$L$300,Z$1,$C$14:$C$300,$U8) -> 0 | AA8: =COUNTIFS($L$14:$L$300,AA$1,$C$14:$C$300,$U8) -> 0 | AB8: =COUNTIFS($L$14:$L$300,AB$1,$C$14:$C$300,$U8) -> 0 | AC8: =COUNTIFS($L$14:$L$300,AC$1,$C$14:$C$300,$U8) -> 0 | ... AG8: =COUNTIFS($L$14:$L$300,AG$1,$C$14:$C$300,$U8) -> 0 | AH8: =SUM(V8:AG8) -> 0
U9: SPRMSO | V9: =COUNTIFS($L$14:$L$300,V$1,$C$14:$C$300,$U9) -> 0 | W9: =COUNTIFS($L$14:$L$300,W$1,$C$14:$C$300,$U9) -> 0 | X9: =COUNTIFS($L$14:$L$300,X$1,$C$14:$C$300,$U9) -> 0 | Y9: =COUNTIFS($L$14:$L$300,Y$1,$C$14:$C$300,$U9) -> 0 | Z9: =COUNTIFS($L$14:$L$300,Z$1,$C$14:$C$300,$U9) -> 0 | AA9: =COUNTIFS($L$14:$L$300,AA$1,$C$14:$C$300,$U9) -> 0 | AB9: =COUNTIFS($L$14:$L$300,AB$1,$C$14:$C$300,$U9) -> 0 | AC9: =COUNTIFS($L$14:$L$300,AC$1,$C$14:$C$300,$U9) -> 0 | ... AG9: =COUNTIFS($L$14:$L$300,AG$1,$C$14:$C$300,$U9) -> 0 | AH9: =SUM(V9:AG9) -> 0
U10: SPRN | V10: =COUNTIFS($L$14:$L$300,V$1,$C$14:$C$300,$U10) -> 0 | W10: =COUNTIFS($L$14:$L$300,W$1,$C$14:$C$300,$U10) -> 0 | X10: =COUNTIFS($L$14:$L$300,X$1,$C$14:$C$300,$U10) -> 2 | Y10: =COUNTIFS($L$14:$L$300,Y$1,$C$14:$C$300,$U10) -> 0 | Z10: =COUNTIFS($L$14:$L$300,Z$1,$C$14:$C$300,$U10) -> 9 | AA10: =COUNTIFS($L$14:$L$300,AA$1,$C$14:$C$300,$U10) -> 8 | AB10: =COUNTIFS($L$14:$L$300,AB$1,$C$14:$C$300,$U10) -> 5 | AC10: =COUNTIFS($L$14:$L$300,AC$1,$C$14:$C$300,$U10) -> 2 | ... AG10: =COUNTIFS($L$14:$L$300,AG$1,$C$14:$C$300,$U10) -> 0 | AH10: =SUM(V10:AG10) -> 39
U11: SPRS | V11: =COUNTIFS($L$14:$L$300,V$1,$C$14:$C$300,$U11) -> 0 | W11: =COUNTIFS($L$14:$L$300,W$1,$C$14:$C$300,$U11) -> 0 | X11: =COUNTIFS($L$14:$L$300,X$1,$C$14:$C$300,$U11) -> 0 | Y11: =COUNTIFS($L$14:$L$300,Y$1,$C$14:$C$300,$U11) -> 0 | Z11: =COUNTIFS($L$14:$L$300,Z$1,$C$14:$C$300,$U11) -> 0 | AA11: =COUNTIFS($L$14:$L$300,AA$1,$C$14:$C$300,$U11) -> 0 | AB11: =COUNTIFS($L$14:$L$300,AB$1,$C$14:$C$300,$U11) -> 0 | AC11: =COUNTIFS($L$14:$L$300,AC$1,$C$14:$C$300,$U11) -> 0 | ... AG11: =COUNTIFS($L$14:$L$300,AG$1,$C$14:$C$300,$U11) -> 0 | AH11: =SUM(V11:AG11) -> 0
U12: SSSTPA | V12: =COUNTIFS($L$14:$L$300,V$1,$C$14:$C$300,$U12) -> 0 | W12: =COUNTIFS($L$14:$L$300,W$1,$C$14:$C$300,$U12) -> 0 | X12: =COUNTIFS($L$14:$L$300,X$1,$C$14:$C$300,$U12) -> 4 | Y12: =COUNTIFS($L$14:$L$300,Y$1,$C$14:$C$300,$U12) -> 2 | Z12: =COUNTIFS($L$14:$L$300,Z$1,$C$14:$C$300,$U12) -> 1 | AA12: =COUNTIFS($L$14:$L$300,AA$1,$C$14:$C$300,$U12) -> 0 | AB12: =COUNTIFS($L$14:$L$300,AB$1,$C$14:$C$300,$U12) -> 0 | AC12: =COUNTIFS($L$14:$L$300,AC$1,$C$14:$C$300,$U12) -> 0 | ... AG12: =COUNTIFS($L$14:$L$300,AG$1,$C$14:$C$300,$U12) -> 0 | AH12: =SUM(V12:AG12) -> 7
A13: IDSDNCA | B13: IDSAP | C13: Subdirección | D13: Gerencia/Activo | E13: Nombre Evento Original | F13: Ficha Instructor | G13: Nombre Instructor | H13: Asistentes Programados | I13: Fecha de Inicio | J13: Fecha de Termino | K13: Sede | L13: Mes | M13: Periodo | N13: Estatus curso | O13: Capacitandos | P13: Ficha Inst | Q13: Instructor | R13: Observaciones | U13: Total | V13: =SUM(V2:V12) -> 0 | W13: =SUM(W2:W12) -> 0 | X13: =SUM(X2:X12) -> 6 | Y13: =SUM(Y2:Y12) -> 2 | Z13: =SUM(Z2:Z12) -> 13 | AA13: =SUM(AA2:AA12) -> 11 | AB13: =SUM(AB2:AB12) -> 6 | AC13: =SUM(AC2:AC12) -> 2 | ... AH13: =SUM(AH2:AH12) -> 55
A14: 48169 | C14: SSSTPA | D14: GERENCIA DE SEGURIDAD, SALUD EN EL TRABAJO Y PROTECCIÓN AMBIENTAL REGIÓN NORTE | E14: VERIFICADOR DE GAS (VG) | F14: 352720 | G14: ROSAS HERNANDEZ ROBERTO AUGUSTO | H14: 13 | I14: 44988 | J14: 44988 | K14: ALTAMIRA, TAMAULIPAS | L14: =MONTH(J14) -> 3 | M14: =IF(AND(J14>=$B$2,J14<=$C$2),1,0) -> 1 | N14: Realizado | O14: 11 | P14: 352720 | Q14: =IFERROR((VLOOKUP(P14,Padrón[[Ficha]:[Nombre]],2,FALSE)),"-") -> ROBERTO AUGUSTO ROSAS HERNANDEZ | S14: =IF(N14="Cancelado","◄ ◄ ◄ Favor de indicar la causa","-") -> -
A15: 48763 | C15: SSSTPA | D15: GERENCIA DE SEGURIDAD, SALUD EN EL TRABAJO Y PROTECCIÓN AMBIENTAL REGIÓN NORTE | E15: SISTEMA DE PERMISOS PARA TRABAJOS CON RIESGO (SPTR) | F15: 352720 | G15: ROSAS HERNANDEZ ROBERTO AUGUSTO | H15: 12 | I15: 44993 | J15: 44995 | K15: ALTAMIRA, TAMAULIPAS | L15: =MONTH(J15) -> 3 | M15: =IF(AND(J15>=$B$2,J15<=$C$2),1,0) -> 1 | N15: Realizado | O15: 11 | P15: 352720 | Q15: =IFERROR((VLOOKUP(P15,Padrón[[Ficha]:[Nombre]],2,FALSE)),"-") -> ROBERTO AUGUSTO ROSAS HERNANDEZ | S15: =IF(N15="Cancelado","◄ ◄ ◄ Favor de indicar la causa","-") -> - | U15: Realizados | V15: 1 | W15: 2 | X15: 3 | Y15: 4 | Z15: 5 | AA15: 6 | AB15: 7 | AC15: 8 | AD15: 9 | AE15: 10 | AF15: 11 | AG15: 12 | AH15: Total
A16: 48478 | C16: SSSTPA | D16: GERENCIA DE SEGURIDAD, SALUD EN EL TRABAJO Y PROTECCIÓN AMBIENTAL REGIÓN NORTE | E16: MANEJO A LA DEFENSIVA (MD) | F16: 315766 | G16: RANGEL RIVAS ROCIO | H16: 13 | I16: 45002 | J16: 45002 | K16: ALTAMIRA, TAMAULIPAS | L16: =MONTH(J16) -> 3 | M16: =IF(AND(J16>=$B$2,J16<=$C$2),1,0) -> 1 | N16: Realizado | O16: 13 | P16: 315766 | Q16: =IFERROR((VLOOKUP(P16,Padrón[[Ficha]:[Nombre]],2,FALSE)),"-") -> ROCIO RANGEL RIVAS | S16: =IF(N16="Cancelado","◄ ◄ ◄ Favor de indicar la causa","-") -> - | U16: SCOC | V16: =COUNTIFS($L$14:$L$300,V$15,$C$14:$C$300,$U16,$N$14:$N$300,"Realizado") -> 0 | W16: =COUNTIFS($L$14:$L$300,W$15,$C$14:$C$300,$U16,$N$14:$N$300,"Realizado") -> 0 | X16: =COUNTIFS($L$14:$L$300,X$15,$C$14:$C$300,$U16,$N$14:$N$300,"Realizado") -> 0 | Y16: =COUNTIFS($L$14:$L$300,Y$15,$C$14:$C$300,$U16,$N$14:$N$300,"Realizado") -> 0 | Z16: =COUNTIFS($L$14:$L$300,Z$15,$C$14:$C$300,$U16,$N$14:$N$300,"Realizado") -> 0 | AA16: =COUNTIFS($L$14:$L$300,AA$15,$C$14:$C$300,$U16,$N$14:$N$300,"Realizado") -> 0 | AB16: =COUNTIFS($L$14:$L$300,AB$15,$C$14:$C$300,$U16,$N$14:$N$300,"Realizado") -> 0 | AC16: =COUNTIFS($L$14:$L$300,AC$15,$C$14:$C$300,$U16,$N$14:$N$300,"Realizado") -> 0 | ... AG16: =COUNTIFS($L$14:$L$300,AG$15,$C$14:$C$300,$U16,$N$14:$N$300,"Realizado") -> 0 | AH16: =SUM(V16:AG16) -> 0
A17: 48266 | C17: SPRN | D17: GERENCIA DE MANTENIMIENTO, CONFIABILIDAD Y CONSTRUCCIÓN | E17: PREVENCIÓN DE RIESGOS LABORALES (PRL) | F17: 457409 | G17: SAVINO COMSILLE MARIA GUADALUPE | H17: 7 | I17: 45007 | J17: 45008 | K17: ALTAMIRA, TAMAULIPAS | L17: =MONTH(J17) -> 3 | M17: =IF(AND(J17>=$B$2,J17<=$C$2),1,0) -> 1 | N17: Realizado | O17: 7 | P17: 457409 | Q17: =IFERROR((VLOOKUP(P17,Padrón[[Ficha]:[Nombre]],2,FALSE)),"-") -> MARIA GUADALUPE SAVINO COMSILLE | S17: =IF(N17="Cancelado","◄ ◄ ◄ Favor de indicar la causa","-") -> - | U17: SE | V17: =COUNTIFS($L$14:$L$300,V$15,$C$14:$C$300,$U17,$N$14:$N$300,"Realizado") -> 0 | W17: =COUNTIFS($L$14:$L$300,W$15,$C$14:$C$300,$U17,$N$14:$N$300,"Realizado") -> 0 | X17: =COUNTIFS($L$14:$L$300,X$15,$C$14:$C$300,$U17,$N$14:$N$300,"Realizado") -> 0 | Y17: =COUNTIFS($L$14:$L$300,Y$15,$C$14:$C$300,$U17,$N$14:$N$300,"Realizado") -> 0 | Z17: =COUNTIFS($L$14:$L$300,Z$15,$C$14:$C$300,$U17,$N$14:$N$300,"Realizado") -> 0 | AA17: =COUNTIFS($L$14:$L$300,AA$15,$C$14:$C$300,$U17,$N$14:$N$300,"Realizado") -> 0 | AB17: =COUNTIFS($L$14:$L$300,AB$15,$C$14:$C$300,$U17,$N$14:$N$300,"Realizado") -> 0 | AC17: =COUNTIFS($L$14:$L$300,AC$15,$C$14:$C$300,$U17,$N$14:$N$300,"Realizado") -> 0 | ... AG17: =COUNTIFS($L$14:$L$300,AG$15,$C$14:$C$300,$U17,$N$14:$N$300,"Realizado") -> 0 | AH17: =SUM(V17:AG17) -> 0
A18: 48768 | C18: SSSTPA | D18: GERENCIA DE SEGURIDAD, SALUD EN EL TRABAJO Y PROTECCIÓN AMBIENTAL REGIÓN NORTE | E18: SISTEMA DE PERMISOS PARA TRABAJOS CON RIESGO (SPTR) | F18: 352720 | G18: ROSAS HERNANDEZ ROBERTO AUGUSTO | H18: 12 | I18: 45007 | J18: 45009 | K18: ALTAMIRA, TAMAULIPAS | L18: =MONTH(J18) -> 3 | M18: =IF(AND(J18>=$B$2,J18<=$C$2),1,0) -> 1 | N18: Realizado | O18: 12 | Q18: =IFERROR((VLOOKUP(P18,Padrón[[Ficha]:[Nombre]],2,FALSE)),"-") -> - | S18: =IF(N18="Cancelado","◄ ◄ ◄ Favor de indicar la causa","-") -> - | U18: SEPCA | V18: =COUNTIFS($L$14:$L$300,V$15,$C$14:$C$300,$U18,$N$14:$N$300,"Realizado") -> 0 | W18: =COUNTIFS($L$14:$L$300,W$15,$C$14:$C$300,$U18,$N$14:$N$300,"Realizado") -> 0 | X18: =COUNTIFS($L$14:$L$300,X$15,$C$14:$C$300,$U18,$N$14:$N$300,"Realizado") -> 0 | Y18: =COUNTIFS($L$14:$L$300,Y$15,$C$14:$C$300,$U18,$N$14:$N$300,"Realizado") -> 0 | Z18: =COUNTIFS($L$14:$L$300,Z$15,$C$14:$C$300,$U18,$N$14:$N$300,"Realizado") -> 0 | AA18: =COUNTIFS($L$14:$L$300,AA$15,$C$14:$C$300,$U18,$N$14:$N$300,"Realizado") -> 0 | AB18: =COUNTIFS($L$14:$L$300,AB$15,$C$14:$C$300,$U18,$N$14:$N$300,"Realizado") -> 0 | AC18: =COUNTIFS($L$14:$L$300,AC$15,$C$14:$C$300,$U18,$N$14:$N$300,"Realizado") -> 0 | ... AG18: =COUNTIFS($L$14:$L$300,AG$15,$C$14:$C$300,$U18,$N$14:$N$300,"Realizado") -> 0 | AH18: =SUM(V18:AG18) -> 0
A19: 48261 | C19: SPRN | D19: GERENCIA DE MANTENIMIENTO, CONFIABILIDAD Y CONSTRUCCIÓN | E19: PREVENCIÓN DE RIESGOS LABORALES (PRL) | F19: 457409 | G19: SAVINO COMSILLE MARIA GUADALUPE | H19: 6 | I19: 45013 | J19: 45014 | K19: ALTAMIRA, TAMAULIPAS | L19: =MONTH(J19) -> 3 | M19: =IF(AND(J19>=$B$2,J19<=$C$2),1,0) -> 1 | N19: Realizado | O19: 5 | P19: 457409 | Q19: =IFERROR((VLOOKUP(P19,Padrón[[Ficha]:[Nombre]],2,FALSE)),"-") -> MARIA GUADALUPE SAVINO COMSILLE | S19: =IF(N19="Cancelado","◄ ◄ ◄ Favor de indicar la causa","-") -> - | U19: SMLIC | V19: =COUNTIFS($L$14:$L$300,V$15,$C$14:$C$300,$U19,$N$14:$N$300,"Realizado") -> 0 | W19: =COUNTIFS($L$14:$L$300,W$15,$C$14:$C$300,$U19,$N$14:$N$300,"Realizado") -> 0 | X19: =COUNTIFS($L$14:$L$300,X$15,$C$14:$C$300,$U19,$N$14:$N$300,"Realizado") -> 0 | Y19: =COUNTIFS($L$14:$L$300,Y$15,$C$14:$C$300,$U19,$N$14:$N$300,"Realizado") -> 0 | Z19: =COUNTIFS($L$14:$L$300,Z$15,$C$14:$C$300,$U19,$N$14:$N$300,"Realizado") -> 3 | AA19: =COUNTIFS($L$14:$L$300,AA$15,$C$14:$C$300,$U19,$N$14:$N$300,"Realizado") -> 3 | AB19: =COUNTIFS($L$14:$L$300,AB$15,$C$14:$C$300,$U19,$N$14:$N$300,"Realizado") -> 1 | AC19: =COUNTIFS($L$14:$L$300,AC$15,$C$14:$C$300,$U19,$N$14:$N$300,"Realizado") -> 0 | ... AG19: =COUNTIFS($L$14:$L$300,AG$15,$C$14:$C$300,$U19,$N$14:$N$300,"Realizado") -> 0 | AH19: =SUM(V19:AG19) -> 9
A20: 48201 | C20: SSSTPA | D20: GERENCIA DE SEGURIDAD, SALUD EN EL TRABAJO Y PROTECCIÓN AMBIENTAL REGIÓN NORTE | E20: PREVENCIÓN DE RIESGOS LABORALES (PRL) | F20: 457409 | G20: SAVINO COMSILLE MARIA GUADALUPE | H20: 8 | I20: 45019 | J20: 45020 | K20: ALTAMIRA, TAMAULIPAS | L20: =MONTH(J20) -> 4 | M20: =IF(AND(J20>=$B$2,J20<=$C$2),1,0) -> 1 | N20: Realizado | O20: 5 | P20: 457409 | Q20: =IFERROR((VLOOKUP(P20,Padrón[[Ficha]:[Nombre]],2,FALSE)),"-") -> MARIA GUADALUPE SAVINO COMSILLE | S20: =IF(N20="Cancelado","◄ ◄ ◄ Favor de indicar la causa","-") -> - | U20: SPEE | V20: =COUNTIFS($L$14:$L$300,V$15,$C$14:$C$300,$U20,$N$14:$N$300,"Realizado") -> 0 | W20: =COUNTIFS($L$14:$L$300,W$15,$C$14:$C$300,$U20,$N$14:$N$300,"Realizado") -> 0 | X20: =COUNTIFS($L$14:$L$300,X$15,$C$14:$C$300,$U20,$N$14:$N$300,"Realizado") -> 0 | Y20: =COUNTIFS($L$14:$L$300,Y$15,$C$14:$C$300,$U20,$N$14:$N$300,"Realizado") -> 0 | Z20: =COUNTIFS($L$14:$L$300,Z$15,$C$14:$C$300,$U20,$N$14:$N$300,"Realizado") -> 0 | AA20: =COUNTIFS($L$14:$L$300,AA$15,$C$14:$C$300,$U20,$N$14:$N$300,"Realizado") -> 0 | AB20: =COUNTIFS($L$14:$L$300,AB$15,$C$14:$C$300,$U20,$N$14:$N$300,"Realizado") -> 0 | AC20: =COUNTIFS($L$14:$L$300,AC$15,$C$14:$C$300,$U20,$N$14:$N$300,"Realizado") -> 0 | ... AG20: =COUNTIFS($L$14:$L$300,AG$15,$C$14:$C$300,$U20,$N$14:$N$300,"Realizado") -> 0 | AH20: =SUM(V20:AG20) -> 0
A21: 48663 | C21: SSSTPA | D21: GERENCIA DE SEGURIDAD, SALUD EN EL TRABAJO Y PROTECCIÓN AMBIENTAL REGIÓN NORTE | E21: PLANEACIÓN Y SUPERVISIÓN SEGURA DE LOS TRABAJOS (PSST) | F21: 451509 | G21: BORJAS ENRIQUEZ PABLO JESUS | H21: 12 | I21: 45043 | J21: 45044 | K21: ALTAMIRA, TAMAULIPAS | L21: =MONTH(J21) -> 4 | M21: =IF(AND(J21>=$B$2,J21<=$C$2),1,0) -> 1 | N21: Realizado | O21: 12 | P21: 451509 | Q21: =IFERROR((VLOOKUP(P21,Padrón[[Ficha]:[Nombre]],2,FALSE)),"-") -> PABLO JESUS BORJAS ENRIQUEZ | S21: =IF(N21="Cancelado","◄ ◄ ◄ Favor de indicar la causa","-") -> - | U21: SPMP | V21: =COUNTIFS($L$14:$L$300,V$15,$C$14:$C$300,$U21,$N$14:$N$300,"Realizado") -> 0 | W21: =COUNTIFS($L$14:$L$300,W$15,$C$14:$C$300,$U21,$N$14:$N$300,"Realizado") -> 0 | X21: =COUNTIFS($L$14:$L$300,X$15,$C$14:$C$300,$U21,$N$14:$N$300,"Realizado") -> 0 | Y21: =COUNTIFS($L$14:$L$300,Y$15,$C$14:$C$300,$U21,$N$14:$N$300,"Realizado") -> 0 | Z21: =COUNTIFS($L$14:$L$300,Z$15,$C$14:$C$300,$U21,$N$14:$N$300,"Realizado") -> 0 | AA21: =COUNTIFS($L$14:$L$300,AA$15,$C$14:$C$300,$U21,$N$14:$N$300,"Realizado") -> 0 | AB21: =COUNTIFS($L$14:$L$300,AB$15,$C$14:$C$300,$U21,$N$14:$N$300,"Realizado") -> 0 | AC21: =COUNTIFS($L$14:$L$300,AC$15,$C$14:$C$300,$U21,$N$14:$N$300,"Realizado") -> 0 | ... AG21: =COUNTIFS($L$14:$L$300,AG$15,$C$14:$C$300,$U21,$N$14:$N$300,"Realizado") -> 0 | AH21: =SUM(V21:AG21) -> 0
A22: 49073 | C22: SMLIC | D22: GERENCIA DE SERVICIOS DE LOGÍSTICA TERRESTRE | E22: BÁSICO DE SEGURIDAD (BS) | F22: 449433 | G22: MORAL JORDAN GONZALO | H22: 5 | I22: 45048 | J22: 45049 | K22: ALTAMIRA, TAMAULIPAS | L22: =MONTH(J22) -> 5 | M22: =IF(AND(J22>=$B$2,J22<=$C$2),1,0) -> 1 | N22: Realizado | O22: 6 | P22: 449433 | Q22: =IFERROR((VLOOKUP(P22,Padrón[[Ficha]:[Nombre]],2,FALSE)),"-") -> GONZALO MORAL JORDAN | S22: =IF(N22="Cancelado","◄ ◄ ◄ Favor de indicar la causa","-") -> - | U22: SPRMNE | V22: =COUNTIFS($L$14:$L$300,V$15,$C$14:$C$300,$U22,$N$14:$N$300,"Realizado") -> 0 | W22: =COUNTIFS($L$14:$L$300,W$15,$C$14:$C$300,$U22,$N$14:$N$300,"Realizado") -> 0 | X22: =COUNTIFS($L$14:$L$300,X$15,$C$14:$C$300,$U22,$N$14:$N$300,"Realizado") -> 0 | Y22: =COUNTIFS($L$14:$L$300,Y$15,$C$14:$C$300,$U22,$N$14:$N$300,"Realizado") -> 0 | Z22: =COUNTIFS($L$14:$L$300,Z$15,$C$14:$C$300,$U22,$N$14:$N$300,"Realizado") -> 0 | AA22: =COUNTIFS($L$14:$L$300,AA$15,$C$14:$C$300,$U22,$N$14:$N$300,"Realizado") -> 0 | AB22: =COUNTIFS($L$14:$L$300,AB$15,$C$14:$C$300,$U22,$N$14:$N$300,"Realizado") -> 0 | AC22: =COUNTIFS($L$14:$L$300,AC$15,$C$14:$C$300,$U22,$N$14:$N$300,"Realizado") -> 0 | ... AG22: =COUNTIFS($L$14:$L$300,AG$15,$C$14:$C$300,$U22,$N$14:$N$300,"Realizado") -> 0 | AH22: =SUM(V22:AG22) -> 0
A23: 50466 | C23: SPRN | D23: ACTIVO DE PRODUCCIÓN POZA RICA - ALTAMIRA | E23: ÁCIDO SULFHÍDRICO (H2S) | F23: 449433 | G23: MORAL JORDAN GONZALO | H23: 14 | I23: 45054 | J23: 45054 | K23: ALTAMIRA, TAMAULIPAS | L23: =MONTH(J23) -> 5 | M23: =IF(AND(J23>=$B$2,J23<=$C$2),1,0) -> 1 | N23: Realizado | O23: 9 | Q23: =IFERROR((VLOOKUP(P23,Padrón[[Ficha]:[Nombre]],2,FALSE)),"-") -> - | S23: =IF(N23="Cancelado","◄ ◄ ◄ Favor de indicar la causa","-") -> - | U23: SPRMSO | V23: =COUNTIFS($L$14:$L$300,V$15,$C$14:$C$300,$U23,$N$14:$N$300,"Realizado") -> 0 | W23: =COUNTIFS($L$14:$L$300,W$15,$C$14:$C$300,$U23,$N$14:$N$300,"Realizado") -> 0 | X23: =COUNTIFS($L$14:$L$300,X$15,$C$14:$C$300,$U23,$N$14:$N$300,"Realizado") -> 0 | Y23: =COUNTIFS($L$14:$L$300,Y$15,$C$14:$C$300,$U23,$N$14:$N$300,"Realizado") -> 0 | Z23: =COUNTIFS($L$14:$L$300,Z$15,$C$14:$C$300,$U23,$N$14:$N$300,"Realizado") -> 0 | AA23: =COUNTIFS($L$14:$L$300,AA$15,$C$14:$C$300,$U23,$N$14:$N$300,"Realizado") -> 0 | AB23: =COUNTIFS($L$14:$L$300,AB$15,$C$14:$C$300,$U23,$N$14:$N$300,"Realizado") -> 0 | AC23: =COUNTIFS($L$14:$L$300,AC$15,$C$14:$C$300,$U23,$N$14:$N$300,"Realizado") -> 0 | ... AG23: =COUNTIFS($L$14:$L$300,AG$15,$C$14:$C$300,$U23,$N$14:$N$300,"Realizado") -> 0 | AH23: =SUM(V23:AG23) -> 0
A24: 50635 | C24: SPRN | D24: ACTIVO DE PRODUCCIÓN POZA RICA - ALTAMIRA | E24: ÁCIDO SULFHÍDRICO (H2S) | F24: 449433 | G24: MORAL JORDAN GONZALO | H24: 13 | I24: 45055 | J24: 45055 | K24: ALTAMIRA, TAMAULIPAS | L24: =MONTH(J24) -> 5 | M24: =IF(AND(J24>=$B$2,J24<=$C$2),1,0) -> 1 | N24: Realizado | O24: 11 | P24: 449433 | Q24: =IFERROR((VLOOKUP(P24,Padrón[[Ficha]:[Nombre]],2,FALSE)),"-") -> GONZALO MORAL JORDAN | S24: =IF(N24="Cancelado","◄ ◄ ◄ Favor de indicar la causa","-") -> - | U24: SPRN | V24: =COUNTIFS($L$14:$L$300,V$15,$C$14:$C$300,$U24,$N$14:$N$300,"Realizado") -> 0 | W24: =COUNTIFS($L$14:$L$300,W$15,$C$14:$C$300,$U24,$N$14:$N$300,"Realizado") -> 0 | X24: =COUNTIFS($L$14:$L$300,X$15,$C$14:$C$300,$U24,$N$14:$N$300,"Realizado") -> 2 | Y24: =COUNTIFS($L$14:$L$300,Y$15,$C$14:$C$300,$U24,$N$14:$N$300,"Realizado") -> 0 | Z24: =COUNTIFS($L$14:$L$300,Z$15,$C$14:$C$300,$U24,$N$14:$N$300,"Realizado") -> 9 | AA24: =COUNTIFS($L$14:$L$300,AA$15,$C$14:$C$300,$U24,$N$14:$N$300,"Realizado") -> 8 | AB24: =COUNTIFS($L$14:$L$300,AB$15,$C$14:$C$300,$U24,$N$14:$N$300,"Realizado") -> 5 | AC24: =COUNTIFS($L$14:$L$300,AC$15,$C$14:$C$300,$U24,$N$14:$N$300,"Realizado") -> 2 | ... AG24: =COUNTIFS($L$14:$L$300,AG$15,$C$14:$C$300,$U24,$N$14:$N$300,"Realizado") -> 0 | AH24: =SUM(V24:AG24) -> 39
A25: 50925 | C25: SPRN | D25: ACTIVO DE PRODUCCIÓN POZA RICA - ALTAMIRA | E25: PREVENCIÓN DE RIESGOS LABORALES (PRL) | F25: 449433 | G25: MORAL JORDAN GONZALO | H25: 12 | I25: 45057 | J25: 45058 | K25: ALTAMIRA, TAMAULIPAS | L25: =MONTH(J25) -> 5 | M25: =IF(AND(J25>=$B$2,J25<=$C$2),1,0) -> 1 | N25: Realizado | O25: 9 | P25: 449433 | Q25: =IFERROR((VLOOKUP(P25,Padrón[[Ficha]:[Nombre]],2,FALSE)),"-") -> GONZALO MORAL JORDAN | S25: =IF(N25="Cancelado","◄ ◄ ◄ Favor de indicar la causa","-") -> - | U25: SPRS | V25: =COUNTIFS($L$14:$L$300,V$15,$C$14:$C$300,$U25,$N$14:$N$300,"Realizado") -> 0 | W25: =COUNTIFS($L$14:$L$300,W$15,$C$14:$C$300,$U25,$N$14:$N$300,"Realizado") -> 0 | X25: =COUNTIFS($L$14:$L$300,X$15,$C$14:$C$300,$U25,$N$14:$N$300,"Realizado") -> 0 | Y25: =COUNTIFS($L$14:$L$300,Y$15,$C$14:$C$300,$U25,$N$14:$N$300,"Realizado") -> 0 | Z25: =COUNTIFS($L$14:$L$300,Z$15,$C$14:$C$300,$U25,$N$14:$N$300,"Realizado") -> 0 | AA25: =COUNTIFS($L$14:$L$300,AA$15,$C$14:$C$300,$U25,$N$14:$N$300,"Realizado") -> 0 | AB25: =COUNTIFS($L$14:$L$300,AB$15,$C$14:$C$300,$U25,$N$14:$N$300,"Realizado") -> 0 | AC25: =COUNTIFS($L$14:$L$300,AC$15,$C$14:$C$300,$U25,$N$14:$N$300,"Realizado") -> 0 | ... AG25: =COUNTIFS($L$14:$L$300,AG$15,$C$14:$C$300,$U25,$N$14:$N$300,"Realizado") -> 0 | AH25: =SUM(V25:AG25) -> 0
A26: 49292 | C26: SMLIC | D26: GERENCIA DE SERVICIOS DE LOGÍSTICA TERRESTRE | E26: RESPUESTA A EMERGENCIAS CON MATERIALES PELIGROSOS (REMP) | F26: 449433 | G26: MORAL JORDAN GONZALO | H26: 11 | I26: 45061 | J26: 45062 | K26: ALTAMIRA, TAMAULIPAS | L26: =MONTH(J26) -> 5 | M26: =IF(AND(J26>=$B$2,J26<=$C$2),1,0) -> 1 | N26: Realizado | O26: 10 | P26: 449433 | Q26: =IFERROR((VLOOKUP(P26,Padrón[[Ficha]:[Nombre]],2,FALSE)),"-") -> GONZALO MORAL JORDAN | S26: =IF(N26="Cancelado","◄ ◄ ◄ Favor de indicar la causa","-") -> - | U26: SSSTPA | V26: =COUNTIFS($L$14:$L$300,V$15,$C$14:$C$300,$U26,$N$14:$N$300,"Realizado") -> 0 | W26: =COUNTIFS($L$14:$L$300,W$15,$C$14:$C$300,$U26,$N$14:$N$300,"Realizado") -> 0 | X26: =COUNTIFS($L$14:$L$300,X$15,$C$14:$C$300,$U26,$N$14:$N$300,"Realizado") -> 4 | Y26: =COUNTIFS($L$14:$L$300,Y$15,$C$14:$C$300,$U26,$N$14:$N$300,"Realizado") -> 2 | Z26: =COUNTIFS($L$14:$L$300,Z$15,$C$14:$C$300,$U26,$N$14:$N$300,"Realizado") -> 1 | AA26: =COUNTIFS($L$14:$L$300,AA$15,$C$14:$C$300,$U26,$N$14:$N$300,"Realizado") -> 0 | AB26: =COUNTIFS($L$14:$L$300,AB$15,$C$14:$C$300,$U26,$N$14:$N$300,"Realizado") -> 0 | AC26: =COUNTIFS($L$14:$L$300,AC$15,$C$14:$C$300,$U26,$N$14:$N$300,"Realizado") -> 0 | ... AG26: =COUNTIFS($L$14:$L$300,AG$15,$C$14:$C$300,$U26,$N$14:$N$300,"Realizado") -> 0 | AH26: =SUM(V26:AG26) -> 7
A27: 49117 | C27: SPRN | D27: GERENCIA DE MANTENIMIENTO, CONFIABILIDAD Y CONSTRUCCIÓN | E27: SEGURIDAD EN CENTROS ADMINISTRATIVOS (SCA) | F27: 457409 | G27: SAVINO COMSILLE MARIA GUADALUPE | H27: 9 | I27: 45062 | J27: 45062 | K27: ALTAMIRA, TAMAULIPAS | L27: =MONTH(J27) -> 5 | M27: =IF(AND(J27>=$B$2,J27<=$C$2),1,0) -> 1 | N27: Realizado | O27: 5 | P27: 457409 | Q27: =IFERROR((VLOOKUP(P27,Padrón[[Ficha]:[Nombre]],2,FALSE)),"-") -> MARIA GUADALUPE SAVINO COMSILLE | S27: =IF(N27="Cancelado","◄ ◄ ◄ Favor de indicar la causa","-") -> - | U27: Total | V27: =SUM(V16:V26) -> 0 | W27: =SUM(W16:W26) -> 0 | X27: =SUM(X16:X26) -> 6 | Y27: =SUM(Y16:Y26) -> 2 | Z27: =SUM(Z16:Z26) -> 13 | AA27: =SUM(AA16:AA26) -> 11 | AB27: =SUM(AB16:AB26) -> 6 | AC27: =SUM(AC16:AC26) -> 2 | ... AH27: =SUM(AH16:AH26) -> 55
A28: 49299 | C28: SMLIC | D28: GERENCIA DE SERVICIOS DE LOGÍSTICA TERRESTRE | E28: RESPUESTA A EMERGENCIAS CON MATERIALES PELIGROSOS (REMP) | F28: 449433 | G28: MORAL JORDAN GONZALO | H28: 10 | I28: 45063 | J28: 45064 | K28: ALTAMIRA, TAMAULIPAS | L28: =MONTH(J28) -> 5 | M28: =IF(AND(J28>=$B$2,J28<=$C$2),1,0) -> 1 | N28: Realizado | O28: 9 | P28: 449433 | Q28: =IFERROR((VLOOKUP(P28,Padrón[[Ficha]:[Nombre]],2,FALSE)),"-") -> GONZALO MORAL JORDAN | S28: =IF(N28="Cancelado","◄ ◄ ◄ Favor de indicar la causa","-") -> -
A29: 47666 | C29: SSSTPA | D29: GERENCIA DE SEGURIDAD, SALUD EN EL TRABAJO Y PROTECCIÓN AMBIENTAL REGIÓN NORTE | E29: BÁSICO DE SEGURIDAD (BS) | F29: 451509 | G29: BORJAS ENRIQUEZ PABLO JESUS | H29: 10 | I29: 45064 | J29: 45065 | K29: ALTAMIRA, TAMAULIPAS | L29: =MONTH(J29) -> 5 | M29: =IF(AND(J29>=$B$2,J29<=$C$2),1,0) -> 1 | N29: Realizado | O29: 9 | P29: 451509 | Q29: =IFERROR((VLOOKUP(P29,Padrón[[Ficha]:[Nombre]],2,FALSE)),"-") -> PABLO JESUS BORJAS ENRIQUEZ | S29: =IF(N29="Cancelado","◄ ◄ ◄ Favor de indicar la causa","-") -> - | U29: Cancelados | V29: 1 | W29: 2 | X29: 3 | Y29: 4 | Z29: 5 | AA29: 6 | AB29: 7 | AC29: 8 | AD29: 9 | AE29: 10 | AF29: 11 | AG29: 12 | AH29: Total
A30: 47729 | C30: SPRN | D30: ACTIVO DE PRODUCCIÓN POZA RICA - ALTAMIRA | E30: ÁCIDO SULFHÍDRICO (H2S) | F30: 449433 | G30: MORAL JORDAN GONZALO | H30: 12 | I30: 45069 | J30: 45069 | K30: ALTAMIRA, TAMAULIPAS | L30: =MONTH(J30) -> 5 | M30: =IF(AND(J30>=$B$2,J30<=$C$2),1,0) -> 1 | N30: Realizado | O30: 11 | P30: 449433 | Q30: =IFERROR((VLOOKUP(P30,Padrón[[Ficha]:[Nombre]],2,FALSE)),"-") -> GONZALO MORAL JORDAN | S30: =IF(N30="Cancelado","◄ ◄ ◄ Favor de indicar la causa","-") -> - | U30: SCOC | V30: =COUNTIFS($L$14:$L$300,V$15,$C$14:$C$300,$U30,$N$14:$N$300,"Cancelado") -> 0 | W30: =COUNTIFS($L$14:$L$300,W$15,$C$14:$C$300,$U30,$N$14:$N$300,"Cancelado") -> 0 | X30: =COUNTIFS($L$14:$L$300,X$15,$C$14:$C$300,$U30,$N$14:$N$300,"Cancelado") -> 0 | Y30: =COUNTIFS($L$14:$L$300,Y$15,$C$14:$C$300,$U30,$N$14:$N$300,"Cancelado") -> 0 | Z30: =COUNTIFS($L$14:$L$300,Z$15,$C$14:$C$300,$U30,$N$14:$N$300,"Cancelado") -> 0 | AA30: =COUNTIFS($L$14:$L$300,AA$15,$C$14:$C$300,$U30,$N$14:$N$300,"Cancelado") -> 0 | AB30: =COUNTIFS($L$14:$L$300,AB$15,$C$14:$C$300,$U30,$N$14:$N$300,"Cancelado") -> 0 | AC30: =COUNTIFS($L$14:$L$300,AC$15,$C$14:$C$300,$U30,$N$14:$N$300,"Cancelado") -> 0 | ... AG30: =COUNTIFS($L$14:$L$300,AG$15,$C$14:$C$300,$U30,$N$14:$N$300,"Cancelado") -> 0 | AH30: =SUM(V30:AG30) -> 0
A31: 47714 | C31: SPRN | D31: ACTIVO DE PRODUCCIÓN POZA RICA - ALTAMIRA | E31: MANEJO A LA DEFENSIVA (MD) | F31: 315766 | G31: RANGEL RIVAS ROCIO | H31: 12 | I31: 45070 | J31: 45070 | K31: ALTAMIRA, TAMAULIPAS | L31: =MONTH(J31) -> 5 | M31: =IF(AND(J31>=$B$2,J31<=$C$2),1,0) -> 1 | N31: Realizado | O31: 12 | P31: 315766 | Q31: =IFERROR((VLOOKUP(P31,Padrón[[Ficha]:[Nombre]],2,FALSE)),"-") -> ROCIO RANGEL RIVAS | S31: =IF(N31="Cancelado","◄ ◄ ◄ Favor de indicar la causa","-") -> - | U31: SE | V31: =COUNTIFS($L$14:$L$300,V$15,$C$14:$C$300,$U31,$N$14:$N$300,"Cancelado") -> 0 | W31: =COUNTIFS($L$14:$L$300,W$15,$C$14:$C$300,$U31,$N$14:$N$300,"Cancelado") -> 0 | X31: =COUNTIFS($L$14:$L$300,X$15,$C$14:$C$300,$U31,$N$14:$N$300,"Cancelado") -> 0 | Y31: =COUNTIFS($L$14:$L$300,Y$15,$C$14:$C$300,$U31,$N$14:$N$300,"Cancelado") -> 0 | Z31: =COUNTIFS($L$14:$L$300,Z$15,$C$14:$C$300,$U31,$N$14:$N$300,"Cancelado") -> 0 | AA31: =COUNTIFS($L$14:$L$300,AA$15,$C$14:$C$300,$U31,$N$14:$N$300,"Cancelado") -> 0 | AB31: =COUNTIFS($L$14:$L$300,AB$15,$C$14:$C$300,$U31,$N$14:$N$300,"Cancelado") -> 0 | AC31: =COUNTIFS($L$14:$L$300,AC$15,$C$14:$C$300,$U31,$N$14:$N$300,"Cancelado") -> 0 | ... AG31: =COUNTIFS($L$14:$L$300,AG$15,$C$14:$C$300,$U31,$N$14:$N$300,"Cancelado") -> 0 | AH31: =SUM(V31:AG31) -> 0
A32: 47721 | C32: SPRN | D32: ACTIVO DE PRODUCCIÓN POZA RICA - ALTAMIRA | E32: MANEJO A LA DEFENSIVA (MD) | F32: 315766 | G32: RANGEL RIVAS ROCIO | H32: 13 | I32: 45071 | J32: 45071 | K32: ALTAMIRA, TAMAULIPAS | L32: =MONTH(J32) -> 5 | M32: =IF(AND(J32>=$B$2,J32<=$C$2),1,0) -> 1 | N32: Realizado | O32: 12 | P32: 315766 | Q32: =IFERROR((VLOOKUP(P32,Padrón[[Ficha]:[Nombre]],2,FALSE)),"-") -> ROCIO RANGEL RIVAS | S32: =IF(N32="Cancelado","◄ ◄ ◄ Favor de indicar la causa","-") -> - | U32: SEPCA | V32: =COUNTIFS($L$14:$L$300,V$15,$C$14:$C$300,$U32,$N$14:$N$300,"Cancelado") -> 0 | W32: =COUNTIFS($L$14:$L$300,W$15,$C$14:$C$300,$U32,$N$14:$N$300,"Cancelado") -> 0 | X32: =COUNTIFS($L$14:$L$300,X$15,$C$14:$C$300,$U32,$N$14:$N$300,"Cancelado") -> 0 | Y32: =COUNTIFS($L$14:$L$300,Y$15,$C$14:$C$300,$U32,$N$14:$N$300,"Cancelado") -> 0 | Z32: =COUNTIFS($L$14:$L$300,Z$15,$C$14:$C$300,$U32,$N$14:$N$300,"Cancelado") -> 0 | AA32: =COUNTIFS($L$14:$L$300,AA$15,$C$14:$C$300,$U32,$N$14:$N$300,"Cancelado") -> 0 | AB32: =COUNTIFS($L$14:$L$300,AB$15,$C$14:$C$300,$U32,$N$14:$N$300,"Cancelado") -> 0 | AC32: =COUNTIFS($L$14:$L$300,AC$15,$C$14:$C$300,$U32,$N$14:$N$300,"Cancelado") -> 0 | ... AG32: =COUNTIFS($L$14:$L$300,AG$15,$C$14:$C$300,$U32,$N$14:$N$300,"Cancelado") -> 0 | AH32: =SUM(V32:AG32) -> 0
A33: 47883 | C33: SPRN | D33: GERENCIA DE MANTENIMIENTO, CONFIABILIDAD Y CONSTRUCCIÓN | E33: ÁCIDO SULFHÍDRICO (H2S) | F33: 196853 | G33: DEL ANGEL DEL ANGEL JUSTO JESUS | H33: 8 | I33: 45076 | J33: 45076 | K33: ALTAMIRA, TAMAULIPAS | L33: =MONTH(J33) -> 5 | M33: =IF(AND(J33>=$B$2,J33<=$C$2),1,0) -> 1 | N33: Realizado | O33: 7 | P33: 457409 | Q33: =IFERROR((VLOOKUP(P33,Padrón[[Ficha]:[Nombre]],2,FALSE)),"-") -> MARIA GUADALUPE SAVINO COMSILLE | S33: =IF(N33="Cancelado","◄ ◄ ◄ Favor de indicar la causa","-") -> - | U33: SMLIC | V33: =COUNTIFS($L$14:$L$300,V$15,$C$14:$C$300,$U33,$N$14:$N$300,"Cancelado") -> 0 | W33: =COUNTIFS($L$14:$L$300,W$15,$C$14:$C$300,$U33,$N$14:$N$300,"Cancelado") -> 0 | X33: =COUNTIFS($L$14:$L$300,X$15,$C$14:$C$300,$U33,$N$14:$N$300,"Cancelado") -> 0 | Y33: =COUNTIFS($L$14:$L$300,Y$15,$C$14:$C$300,$U33,$N$14:$N$300,"Cancelado") -> 0 | Z33: =COUNTIFS($L$14:$L$300,Z$15,$C$14:$C$300,$U33,$N$14:$N$300,"Cancelado") -> 0 | AA33: =COUNTIFS($L$14:$L$300,AA$15,$C$14:$C$300,$U33,$N$14:$N$300,"Cancelado") -> 0 | AB33: =COUNTIFS($L$14:$L$300,AB$15,$C$14:$C$300,$U33,$N$14:$N$300,"Cancelado") -> 0 | AC33: =COUNTIFS($L$14:$L$300,AC$15,$C$14:$C$300,$U33,$N$14:$N$300,"Cancelado") -> 0 | ... AG33: =COUNTIFS($L$14:$L$300,AG$15,$C$14:$C$300,$U33,$N$14:$N$300,"Cancelado") -> 0 | AH33: =SUM(V33:AG33) -> 0
A34: 47667 | C34: SPRN | D34: GERENCIA DE MANTENIMIENTO, CONFIABILIDAD Y CONSTRUCCIÓN | E34: ÁCIDO SULFHÍDRICO (H2S) | F34: 196853 | G34: DEL ANGEL DEL ANGEL JUSTO JESUS | H34: 8 | I34: 45077 | J34: 45077 | K34: ALTAMIRA, TAMAULIPAS | L34: =MONTH(J34) -> 5 | M34: =IF(AND(J34>=$B$2,J34<=$C$2),1,0) -> 1 | N34: Realizado | O34: 6 | P34: 457409 | Q34: =IFERROR((VLOOKUP(P34,Padrón[[Ficha]:[Nombre]],2,FALSE)),"-") -> MARIA GUADALUPE SAVINO COMSILLE | S34: =IF(N34="Cancelado","◄ ◄ ◄ Favor de indicar la causa","-") -> - | U34: SPEE | V34: =COUNTIFS($L$14:$L$300,V$15,$C$14:$C$300,$U34,$N$14:$N$300,"Cancelado") -> 0 | W34: =COUNTIFS($L$14:$L$300,W$15,$C$14:$C$300,$U34,$N$14:$N$300,"Cancelado") -> 0 | X34: =COUNTIFS($L$14:$L$300,X$15,$C$14:$C$300,$U34,$N$14:$N$300,"Cancelado") -> 0 | Y34: =COUNTIFS($L$14:$L$300,Y$15,$C$14:$C$300,$U34,$N$14:$N$300,"Cancelado") -> 0 | Z34: =COUNTIFS($L$14:$L$300,Z$15,$C$14:$C$300,$U34,$N$14:$N$300,"Cancelado") -> 0 | AA34: =COUNTIFS($L$14:$L$300,AA$15,$C$14:$C$300,$U34,$N$14:$N$300,"Cancelado") -> 0 | AB34: =COUNTIFS($L$14:$L$300,AB$15,$C$14:$C$300,$U34,$N$14:$N$300,"Cancelado") -> 0 | AC34: =COUNTIFS($L$14:$L$300,AC$15,$C$14:$C$300,$U34,$N$14:$N$300,"Cancelado") -> 0 | ... AG34: =COUNTIFS($L$14:$L$300,AG$15,$C$14:$C$300,$U34,$N$14:$N$300,"Cancelado") -> 0 | AH34: =SUM(V34:AG34) -> 0
A35: 47731 | C35: SPRN | D35: ACTIVO DE PRODUCCIÓN POZA RICA - ALTAMIRA | E35: ÁCIDO SULFHÍDRICO (H2S) | F35: 449433 | G35: MORAL JORDAN GONZALO | H35: 12 | I35: 45079 | J35: 45079 | K35: ALTAMIRA, TAMAULIPAS | L35: =MONTH(J35) -> 6 | M35: =IF(AND(J35>=$B$2,J35<=$C$2),1,0) -> 1 | N35: Realizado | O35: 10 | P35: 449433 | Q35: =IFERROR((VLOOKUP(P35,Padrón[[Ficha]:[Nombre]],2,FALSE)),"-") -> GONZALO MORAL JORDAN | S35: =IF(N35="Cancelado","◄ ◄ ◄ Favor de indicar la causa","-") -> - | U35: SPMP | V35: =COUNTIFS($L$14:$L$300,V$15,$C$14:$C$300,$U35,$N$14:$N$300,"Cancelado") -> 0 | W35: =COUNTIFS($L$14:$L$300,W$15,$C$14:$C$300,$U35,$N$14:$N$300,"Cancelado") -> 0 | X35: =COUNTIFS($L$14:$L$300,X$15,$C$14:$C$300,$U35,$N$14:$N$300,"Cancelado") -> 0 | Y35: =COUNTIFS($L$14:$L$300,Y$15,$C$14:$C$300,$U35,$N$14:$N$300,"Cancelado") -> 0 | Z35: =COUNTIFS($L$14:$L$300,Z$15,$C$14:$C$300,$U35,$N$14:$N$300,"Cancelado") -> 0 | AA35: =COUNTIFS($L$14:$L$300,AA$15,$C$14:$C$300,$U35,$N$14:$N$300,"Cancelado") -> 0 | AB35: =COUNTIFS($L$14:$L$300,AB$15,$C$14:$C$300,$U35,$N$14:$N$300,"Cancelado") -> 0 | AC35: =COUNTIFS($L$14:$L$300,AC$15,$C$14:$C$300,$U35,$N$14:$N$300,"Cancelado") -> 0 | ... AG35: =COUNTIFS($L$14:$L$300,AG$15,$C$14:$C$300,$U35,$N$14:$N$300,"Cancelado") -> 0 | AH35: =SUM(V35:AG35) -> 0
A36: 47793 | C36: SPRN | D36: ACTIVO DE PRODUCCIÓN POZA RICA - ALTAMIRA | E36: BÁSICO DE SEGURIDAD (BS) | F36: 449433 | G36: MORAL JORDAN GONZALO | H36: 16 | I36: 45082 | J36: 45083 | K36: ALTAMIRA, TAMAULIPAS | L36: =MONTH(J36) -> 6 | M36: =IF(AND(J36>=$B$2,J36<=$C$2),1,0) -> 1 | N36: Realizado | O36: 15 | P36: 449433 | Q36: =IFERROR((VLOOKUP(P36,Padrón[[Ficha]:[Nombre]],2,FALSE)),"-") -> GONZALO MORAL JORDAN | S36: =IF(N36="Cancelado","◄ ◄ ◄ Favor de indicar la causa","-") -> - | U36: SPRMNE | V36: =COUNTIFS($L$14:$L$300,V$15,$C$14:$C$300,$U36,$N$14:$N$300,"Cancelado") -> 0 | W36: =COUNTIFS($L$14:$L$300,W$15,$C$14:$C$300,$U36,$N$14:$N$300,"Cancelado") -> 0 | X36: =COUNTIFS($L$14:$L$300,X$15,$C$14:$C$300,$U36,$N$14:$N$300,"Cancelado") -> 0 | Y36: =COUNTIFS($L$14:$L$300,Y$15,$C$14:$C$300,$U36,$N$14:$N$300,"Cancelado") -> 0 | Z36: =COUNTIFS($L$14:$L$300,Z$15,$C$14:$C$300,$U36,$N$14:$N$300,"Cancelado") -> 0 | AA36: =COUNTIFS($L$14:$L$300,AA$15,$C$14:$C$300,$U36,$N$14:$N$300,"Cancelado") -> 0 | AB36: =COUNTIFS($L$14:$L$300,AB$15,$C$14:$C$300,$U36,$N$14:$N$300,"Cancelado") -> 0 | AC36: =COUNTIFS($L$14:$L$300,AC$15,$C$14:$C$300,$U36,$N$14:$N$300,"Cancelado") -> 0 | ... AG36: =COUNTIFS($L$14:$L$300,AG$15,$C$14:$C$300,$U36,$N$14:$N$300,"Cancelado") -> 0 | AH36: =SUM(V36:AG36) -> 0
A37: 49097 | C37: SMLIC | D37: GERENCIA DE SERVICIOS DE LOGÍSTICA TERRESTRE | E37: PLANEACIÓN Y SUPERVISIÓN SEGURA DE LOS TRABAJOS (PSST) | F37: 451509 | G37: BORJAS ENRIQUEZ PABLO JESUS | H37: 8 | I37: 45089 | J37: 45090 | K37: ALTAMIRA, TAMAULIPAS | L37: =MONTH(J37) -> 6 | M37: =IF(AND(J37>=$B$2,J37<=$C$2),1,0) -> 1 | N37: Realizado | O37: 8 | P37: 451509 | Q37: =IFERROR((VLOOKUP(P37,Padrón[[Ficha]:[Nombre]],2,FALSE)),"-") -> PABLO JESUS BORJAS ENRIQUEZ | S37: =IF(N37="Cancelado","◄ ◄ ◄ Favor de indicar la causa","-") -> - | U37: SPRMSO | V37: =COUNTIFS($L$14:$L$300,V$15,$C$14:$C$300,$U37,$N$14:$N$300,"Cancelado") -> 0 | W37: =COUNTIFS($L$14:$L$300,W$15,$C$14:$C$300,$U37,$N$14:$N$300,"Cancelado") -> 0 | X37: =COUNTIFS($L$14:$L$300,X$15,$C$14:$C$300,$U37,$N$14:$N$300,"Cancelado") -> 0 | Y37: =COUNTIFS($L$14:$L$300,Y$15,$C$14:$C$300,$U37,$N$14:$N$300,"Cancelado") -> 0 | Z37: =COUNTIFS($L$14:$L$300,Z$15,$C$14:$C$300,$U37,$N$14:$N$300,"Cancelado") -> 0 | AA37: =COUNTIFS($L$14:$L$300,AA$15,$C$14:$C$300,$U37,$N$14:$N$300,"Cancelado") -> 0 | AB37: =COUNTIFS($L$14:$L$300,AB$15,$C$14:$C$300,$U37,$N$14:$N$300,"Cancelado") -> 0 | AC37: =COUNTIFS($L$14:$L$300,AC$15,$C$14:$C$300,$U37,$N$14:$N$300,"Cancelado") -> 0 | ... AG37: =COUNTIFS($L$14:$L$300,AG$15,$C$14:$C$300,$U37,$N$14:$N$300,"Cancelado") -> 0 | AH37: =SUM(V37:AG37) -> 0
A38: 50087 | C38: SPRN | D38: GERENCIA DE MANTENIMIENTO, CONFIABILIDAD Y CONSTRUCCIÓN | E38: BÁSICO DE SEGURIDAD (BS) | F38: 457409 | G38: SAVINO COMSILLE MARIA GUADALUPE | H38: 8 | I38: 45090 | J38: 45091 | K38: ALTAMIRA, TAMAULIPAS | L38: =MONTH(J38) -> 6 | M38: =IF(AND(J38>=$B$2,J38<=$C$2),1,0) -> 1 | N38: Realizado | O38: 7 | P38: 457409 | Q38: =IFERROR((VLOOKUP(P38,Padrón[[Ficha]:[Nombre]],2,FALSE)),"-") -> MARIA GUADALUPE SAVINO COMSILLE | S38: =IF(N38="Cancelado","◄ ◄ ◄ Favor de indicar la causa","-") -> - | U38: SPRN | V38: =COUNTIFS($L$14:$L$300,V$15,$C$14:$C$300,$U38,$N$14:$N$300,"Cancelado") -> 0 | W38: =COUNTIFS($L$14:$L$300,W$15,$C$14:$C$300,$U38,$N$14:$N$300,"Cancelado") -> 0 | X38: =COUNTIFS($L$14:$L$300,X$15,$C$14:$C$300,$U38,$N$14:$N$300,"Cancelado") -> 0 | Y38: =COUNTIFS($L$14:$L$300,Y$15,$C$14:$C$300,$U38,$N$14:$N$300,"Cancelado") -> 0 | Z38: =COUNTIFS($L$14:$L$300,Z$15,$C$14:$C$300,$U38,$N$14:$N$300,"Cancelado") -> 0 | AA38: =COUNTIFS($L$14:$L$300,AA$15,$C$14:$C$300,$U38,$N$14:$N$300,"Cancelado") -> 0 | AB38: =COUNTIFS($L$14:$L$300,AB$15,$C$14:$C$300,$U38,$N$14:$N$300,"Cancelado") -> 0 | AC38: =COUNTIFS($L$14:$L$300,AC$15,$C$14:$C$300,$U38,$N$14:$N$300,"Cancelado") -> 0 | ... AG38: =COUNTIFS($L$14:$L$300,AG$15,$C$14:$C$300,$U38,$N$14:$N$300,"Cancelado") -> 0 | AH38: =SUM(V38:AG38) -> 0
